Workbook

Sheet Original
A1: MONTHLY FIRE ALARM TESTING - NOVEMBER 2011 - OCTOBER 2012
A2: ADDRESS | B2: PROPERTY MANAGER | C2: TEST DAY | D2: ANNUAL | E2: 2011 NOV | F2: DEC | G2: 2012 JAN | H2: FEB | I2: MAR | J2: APR | K2: MAY | L2: JUN | M2: JLY | N2: AUG | O2: SEPT | P2: OCT
A3: 703 Broughton | B3: 486261 BC LTD | C3: W1 | D3: April | E3: 3 | F3: 3 | G3: 3 | H3: 3 | I3: 3 | J3: A | K3: 3 | L3: 3 | M3: 3 | N3: 3
A4: 1133A Reynolds | B4: Abbeyfield S. Peters | C4: W4 | D4: May | E4: 3 | F4: 3 | G4: 3 | H4: 3 | I4: 3 | J4: 3 | K4: A | L4: 3 | M4: 3
A5: 707 Courtney @ $112.50/mth | B5: AWM Alliance | C5: W1 | D5: Aug | E5: 3 | F5: 3 | G5: 3 | H5: 3 | I5: 3 | J5: 3 | K5: 3 | L5: A | M5: 3 | N5: 3
A6: 770 Fisgard | B6: AWM Alliance | C6: W2 | D6: Sept | E6: 3 | F6: 3 | G6: 3 | H6: 3 | I6: 3 | J6: 3 | K6: 3 | L6: 3 | M6: 3 | N6: 3 | O6: A
A7: 545 Manchester/520 Dunedin | B7: Baywood | C7: W2 | D7: May | E7: 3 | F7: 3 | G7: 3 | H7: NA | I7: 3 | J7: 3 | K7: X | L7: A | M7: 3 | N7: 3 | Q7: MBT- not done in May as annual moved to June 2012
A8: 120 Douglas | B8: Boorman | C8: T | D8: Jan | E8: 3 | F8: 3 | G8: A | H8: 3 | I8: 3 | J8: 3 | K8: 3 | L8: 3 | M8: 3 | N8: 3
A9: 945 McClure | B9: Boorman | C9: T | D9: Dec | E9: 3 | F9: A | G9: 3 | H9: 3 | I9: 3 | J9: 3 | K9: 3 | L9: 3 | M9: 3 | N9: 3
A10: 1436 Harrison | B10: Boormans | C10: T | D10: Feb | E10: 3 | F10: 3 | G10: 3 | H10: A | I10: 3 | J10: 3 | K10: 3 | L10: 3 | M10: 3 | N10: 3
A11: 515 Foul Bay | B11: Brian McLoughlin Inv.4229 pd to Oct/12 @ $40/mth | C11: W1 | D11: April | E11: NA | F11: NA | G11: NA | H11: 3 | I11: 3 | J11: 3 | K11: 3 | L11: 3 | M11: 3 | N11: 3
A12: 2020 Richmond | B12: Brown Bros | C12: W1 | D12: July | E12: 3 | F12: 3 | G12: 3 | H12: 3 | I12: 3 | J12: 3 | K12: 3 | L12: 3 | M12: A | N12: 3
A13: 605 Cook | B13: Brown Bros | C13: T | D13: Feb | E13: 3 | F13: 3 | G13: 3 | H13: A | I13: 3 | J13: 3 | K13: 3 | L13: 3 | M13: 3 | N13: 3
A14: 655 Herald | B14: Brown Bros | C14: W2 | D14: March | E14: 3 | F14: 3 | G14: 3 | H14: 3 | I14: A | J14: 3 | K14: 3 | L14: 3 | M14: 3 | N14: 3
A15: 55 Songhees | B15: Brown Bros | C15: W4 | D15: Jan | E15: 3 | F15: 3 | G15: A | H15: 3 | I15: 3 | J15: 3 | K15: 3 | L15: 3 | M15: 3
A16: 2626 Blackwood | B16: Brown Bros Inv. 4838 pd to Feb.29/12 @ $45/mth | C16: W4 | D16: April | E16: 3 | F16: 3 | G16: 3 | H16: 3 | I16: Cancelled
A17: 50 & 60 Bastion/ 1200 Government | B17: Colliers | C17: W2 | D17: Jan | E17: 3 | F17: 3 | G17: A | H17: 3 | I17: 3 | J17: 3 | K17: 3 | L17: 3 | M17: 3 | N17: 3
A18: 1000-1012 Douglas | B18: Colliers | C18: W1 | D18: Sept | E18: 3 | F18: 3 | G18: 3 | H18: 3 | I18: 3 | J18: 3 | K18: 3 | L18: 3 | M18: 3 | N18: 3 | O18: A
A19: 1005 Broad | B19: Colliers | C19: W1 | D19: Sept | E19: 3 | F19: 3 | G19: 3 | H19: 3 | I19: 3 | J19: 3 | K19: 3 | L19: 3 | M19: 3 | N19: 3 | O19: A
A20: 1205 Broad Street/650 View Street | B20: Newport | C20: W2 | D20: April | I20: 3 | J20: A | K20: 3 | L20: 3 | M20: 3 | N20: 3
A21: 1205 Broad Street/650 View Street | B21: Colliers | C21: W2 | D21: April | E21: 3 | F21: NA | G21: 3 | H21: 3 | I21: CANCELLED
A22: 1207 Douglas | B22: Colliers | C22: W1 | D22: May | E22: 3 | F22: 3 | G22: 3 | H22: 3 | I22: 3 | J22: 3 | K22: A | L22: 3 | M22: 3 | N22: 3
A23: 1581 Hillside | B23: Colliers | C23: T | D23: June | E23: 3 | F23: 3 | G23: 3 | H23: 3 | I23: 3 | J23: 3 | K23: 3 | L23: A | M23: 3 | N23: 3
A24: 230 Cook | B24: 230 Cook Street Holdings c/o Colliers | C24: T | D24: Oct | E24: 3 | F24: 3 | G24: 3 | H24: 3 | I24: 3 | J24: 3 | K24: 3 | L24: 3 | M24: 3 | N24: 3 | P24: A
A25: 2250 Oak Bay | B25: Colliers | C25: T | D25: Dec | E25: 3 | F25: A | G25: 3 | H25: 3 | I25: 3 | J25: 3 | K25: 3 | L25: 3 | M25: 3 | N25: 3
A26: 3045 Douglas Street | B26: Colliers | C26: W4 | D26: May | E26: 3 | F26: 3 | G26: 3 | H26: NA | I26: 3 | J26: 3 | K26: A | L26: 3 | M26: 3
A27: 3400 Davidson | B27: Colliers | C27: W4 | D27: March | E27: 3 | F27: 3 | G27: 3 | H27: 3 | I27: A | J27: 3 | K27: 3 | L27: 3 | M27: 3
A28: 609 Broughton | B28: Colliers | C28: W1 | D28: March | E28: 3 | F28: 3 | G28: 3 | H28: 3 | I28: A | J28: 3 | K28: 3 | L28: 3 | M28: 3 | N28: 3
A29: 721-725 Yates | B29: Colliers - Inv. 4888 Nov. 1/11 - Apr. 30/12 | C29: W1 | D29: May | E29: 3 | F29: 3 | G29: 3 | H29: 3 | I29: 3 | J29: 3 | K29: A | L29: 3 | M29: 3 | N29: 3
A30: 765-777 Broughton | B30: Colliers | C30: W1 | D30: Sept | E30: 3 | F30: 3 | G30: 3 | H30: 3 | I30: 3 | J30: 3 | K30: 3 | L30: 3 | M30: 3 | N30: 3 | O30: A
A31: 777 Fort | B31: Colliers | C31: W1 | D31: July | E31: 3 | F31: 3 | G31: 3 | H31: 3 | I31: 3 | J31: 3 | K31: 3 | L31: 3 | M31: A | N31: 3
A32: 825-827 Fort | B32: Colliers | C32: W1 | D32: May | E32: 3 | F32: 3 | G32: 3 | H32: 3 | I32: 3 | J32: 3 | K32: A | L32: 3 | M32: 3 | N32: 3
A33: 838 Fort | B33: Colliers | C33: W1 | D33: Aug | E33: 3 | F33: 3 | G33: 3 | H33: 3 | I33: 3 | J33: 3 | K33: 3 | L33: 3 | M33: A | N33: NA
A34: 914 Yates | B34: Colliers | C34: W2 | D34: Jan | E34: 3 | F34: 3 | G34: A | H34: 3 | I34: 3 | J34: 3 | K34: 3 | L34: 3 | M34: 3 | N34: 3
A35: 1223 Johnson | B35: Complete Res. | C35: W2 | D35: Jan | E35: 3 | F35: 3 | G35: A | H35: 3 | I35: 3 | J35: 3 | K35: 3 | L35: 3 | M35: 3 | N35: 3
A36: 1111 Hillside | B36: Complete Res. | C36: W4 | D36: Nov | E36: A | F36: 3 | G36: 3 | H36: 3 | I36: 3 | J36: 3 | K36: 3 | L36: 3 | M36: 3
A37: 845 Yates | B37: Cornerstone | C37: W2 | D37: Jan by Others | E37: 3 | F37: 3 | G37: A | H37: 3 | I37: 3 | J37: 3 | K37: 3 | L37: 3 | M37: 3 | N37: 3
A38: 710 Redbrick | B38: Gulf Pacific | C38: W4 | D38: March | E38: 3 | F38: NA | G38: 3 | H38: 3 | I38: A | J38: 3 | K38: 3 | L38: 3 | M38: 3
A39: 836 Yates | B39: Coronet Ventures | C39: W2 | D39: Mar | E39: 3 | F39: 3 | G39: 3 | H39: 3 | I39: A | J39: 3 | K39: 3 | L39: 3 | M39: 3 | N39: 3
A40: 708 View | B40: DVN Investments | C40: W2 | D40: Dec | E40: 3 | F40: A | G40: 3 | H40: 3 | I40: 3 | J40: 3 | K40: 3 | L40: 3 | M40: 3 | N40: 3
A41: 1026 Johnson | B41: Firm Management | C41: W2 | D41: August | E41: 3 | F41: 3 | G41: 3 | H41: 3 | I41: 3 | J41: 3 | K41: 3 | L41: 3 | M41: 3 | N41: A
A42: 1034 Johnson | B42: Firm Management | C42: W2 | D42: Oct | E42: NA | F42: 3 | G42: 3 | H42: 3 | I42: 3 | J42: NA | K42: 3 | L42: 3 | M42: 3 | N42: 3 | P42: A
A43: 415 Linden | B43: Firm Management | C43: T | D43: June | E43: 3 | F43: 3 | G43: 3 | H43: 3 | I43: 3 | J43: 3 | K43: 3 | L43: A | M43: 3 | N43: 3
A44: 770 Cormorant | B44: Firm Management | C44: W2 | D44: June | E44: 3 | F44: 3 | G44: 3 | H44: 3 | I44: 3 | J44: 3 | K44: 3 | L44: A | M44: 3 | N44: 3
A45: 1510 Hillside | B45: Firm Management | C45: T | D45: March | E45: 3 | F45: 3 | G45: 3 | H45: 3 | I45: A | J45: 3 | K45: 3 | L45: 3 | M45: 3 | N45: 3
A46: 2626 Blackwood | B46: Firm Management Brown Bros billed till Feb. 29/12 | C46: W4 | D46: April | I46: 3 | J46: 3 | K46: A | L46: 3 | M46: 3
A47: 1166 Rockland | B47: Freelance | C47: T | D47: Jan | E47: 3 | F47: 3 | G47: A | H47: 3 | I47: 3 | J47: 3 | K47: 3 | L47: 3 | M47: 3 | N47: 3
A48: 31 Bastion | B48: Gateway | C48: W2 | D48: July | E48: 3 | F48: 3 | G48: 3 | H48: 3 | I48: 3 | J48: 3 | K48: 3 | L48: 3 | M48: A | N48: NA
A49: 425-435 Simcoe | B49: Gateway | C49: T | D49: Jan? | E49: 3 | F49: 3 | G49: 3 | H49: A | I49: 3 | J49: 3 | K49: 3 | L49: 3 | M49: 3 | N49: 3
A50: 1252 Pandora | B50: Gibraltar | C50: W2 | D50: August | E50: 3 | F50: 3 | G50: 3 | H50: 3 | I50: 3 | J50: 3 | K50: 3 | L50: 3 | M50: 3 | N50: A
A51: 1366 Hillside | B51: Gibraltar | C51: T | D51: May | E51: 3 | F51: 3 | G51: 3 | H51: 3 | I51: 3 | J51: 3 | K51: A | L51: 3 | M51: 3 | N51: 3
A52: 410 Garbally | B52: Homewood | C52: W4 | D52: Nov | E52: A | F52: 3 | G52: 3 | H52: 3 | I52: 3 | J52: 3 | K52: 3 | L52: 3 | M52: 3
A53: 415 Dunedin | B53: Homewood | C53: W4 | D53: Nov | E53: A | F53: NA | G53: 3 | H53: 3 | I53: 3 | J53: 3 | K53: 3 | L53: 3 | M53: 3
A54: 1005 & 1009 McKenzie | B54: Hutton | C54: W4 | D54: Feb - by Others | E54: 3 | F54: 3 | G54: 3 | H54: A | I54: 3 | J54: A | K54: 3 | L54: 3 | M54: 3
A55: 1012 Collinson | B55: Hutton | C55: T | D55: Jan | E55: 3 | F55: 3 | G55: A | H55: 3 | I55: 3 | J55: 3 | K55: 3 | L55: 3 | M55: 3 | N55: 3
A56: 10459 Resthaven | B56: Hutton cancelled July 26/12 tw-billed to June 30/12 inv.5115 | C56: W4 | D56: Feb | E56: 3 | F56: 3 | G56: 3 | H56: A | I56: 3 | J56: 3 | K56: 3 | L56: 3 | M56: Cancelled
A57: 10461 Resthaven | B57: Hutton cancelled July 26/12 tw-billed to June 30/12 inv. 5116 | C57: W4 | D57: Feb | E57: 3 | F57: 3 | G57: 3 | H57: A | I57: 3 | J57: 3 | K57: 3 | L57: 3 | M57: Cancelled
A58: 1560 Hillside | B58: Hutton | C58: T | D58: Oct | E58: 3 | F58: 3 | G58: 3 | H58: 3 | I58: 3 | J58: 3 | K58: 3 | L58: 3 | M58: 3 | N58: 3 | P58: A
A59: 188 Douglas | B59: Hutton | C59: W1 | D59: April | E59: 3 | F59: 3 | G59: 3 | H59: 3 | I59: 3 | J59: A | K59: 3 | L59: 3 | M59: 3 | N59: 3
A60: 1975 Lee | B60: Hutton | C60: T | D60: August | E60: NA | F60: 3 | G60: 3 | H60: 3 | I60: 3 | J60: 3 | K60: A | L60: 3 | M60: 3 | N60: 3
A61: 370-380 Waterfront | B61: Hutton | C61: W4 | D61: June | E61: 3 | F61: 3 | G61: 3 | H61: 3 | I61: 3 | J61: 3 | K61: 3 | L61: A | M61: 3
A62: 670 Dallas | B62: Hutton | C62: T | D62: Sept | E62: 3 | F62: 3 | G62: 3 | H62: 3 | I62: 3 | J62: 3 | K62: 3 | L62: 3 | M62: 3 | N62: 3 | O62: A
A63: 800 Johnson | B63: Invermay | C63: W2 | D63: Mar | E63: 3 | F63: 3 | G63: 3 | H63: 3 | I63: A | J63: 3 | K63: 3 | L63: 3 | M63: 3 | N63: 3
A64: 3939 Quadra Street | B64: Jorgorian | C64: W4 | D64: July | E64: 3 | F64: 3 | G64: 3 | H64: 3 | I64: 3 | J64: NA | K64: NA | L64: 3 | M64: A
A65: 851 Yates | B65: Newport | C65: W2 | D65: Feb | E65: 3 | F65: 3 | G65: 3 | H65: A | I65: 3 | J65: 3 | L65: 3 | M65: 3 | N65: NA
A66: 1250 Quadra Street | B66: Newport | C66: W2 | D66: Jan | E66: 3 | F66: 3 | G66: A | H66: 3 | I66: 3 | J66: 3 | K66: 3 | L66: 3 | M66: 3 | N66: 3
A67: 1368 Pandora | B67: Pandale Place | C67: W2 | D67: April | E67: 3 | F67: 3 | G67: 3 | H67: 3 | I67: 3 | J67: A | K67: 3 | L67: 3 | M67: 3 | N67: 3
A68: 1117 Wharf | B68: Pemberton Holmes | C68: W1 | D68: March | E68: 3 | F68: 3 | G68: 3 | H68: 3 | I68: A | J68: 3 | K68: 3 | L68: 3 | M68: 3 | N68: 3
A69: 1000-1002 Government 536 Broughton | B69: Pemberton Holmes | C69: W2 | D69: Nov | E69: A | F69: 3 | G69: 3 | H69: 3 | I69: 3 | J69: 3 | K69: 3 | L69: 3 | M69: 3 | N69: 3
A70: 1005 Langley | B70: Pemberton Holmes | C70: W4 | D70: May | E70: 3 | F70: 3 | G70: 3 | H70: 3 | I70: 3 | J70: 3 | K70: A | L70: 3 | M70: 3
A71: 1006 Govt/ 1007-09 Langley | B71: Pemberton Holmes | C71: W2 | D71: Nov | E71: A | F71: 3 | G71: 3 | H71: 3 | J71: 3 | K71: 3 | L71: 3 | M71: 3 | N71: 3
A72: 505 Fisgard | B72: Pemberton Holmes | C72: W4 | D72: March | E72: 3 | F72: NA | G72: 3 | H72: 3 | I72: A | J72: 3 | K72: 3 | L72: 3 | M72: NA
A73: 625 Hillside | B73: Pemberton Holmes | C73: T | D73: January | E73: 3 | F73: 3 | G73: A | H73: 3 | I73: 3 | J73: 3 | K73: 3 | L73: 3 | M73: 3 | N73: 3
A74: 1640 Oak Bay | B74: Pemberton Holmes | C74: W1 | D74: January | E74: 3 | F74: 3 | G74: A | H74: 3 | I74: 3 | J74: 3 | K74: 3 | L74: 3 | M74: 3 | N74: 3
A75: 725 Yates | B75: Primex Investments | C75: W1 | D75: May | F75: Done thru Colliers | K75: A
A76: 3008 Washington | B76: Proline | C76: W4 | D76: Dec | E76: 3 | F76: A | G76: 3 | H76: 3 | I76: 3 | J76: 3 | K76: 3 | L76: 3 | M76: 3
A77: 909 Pembroke | B77: Proline | C77: W1 | D77: Jan | F77: 3 | G77: A | H77: 3 | I77: 3 | J77: 3 | K77: 3 | L77: 3 | M77: 3 | N77: 3
A78: 1655 Begbie | B78: Proline | C78: T | D78: March | E78: 3 | F78: 3 | G78: 3 | H78: 3 | I78: A | J78: 3 | K78: 3 | L78: 3 | M78: 3 | N78: 3
A79: 468 Belleville | B79: Prov. Cap. Com. | C79: W2 | D79: Dec | F79: A | G79: NA - Till Further notice | J79: 3 | K79: 3 | L79: 3 | M79: 3 | N79: 3
A80: 812 Wharf Street | B80: Prov. Cap. Com. Cancelled by PCC, requested to resume August per Jim Karakai requires monthly PO | C80: W2 | D80: April | E80: 3 | F80: 3 | G80: 3 | H80: 3 | I80: A | J80: Cancelled | N80: 3
A81: 613 Pandora | B81: Prov. Cap. Com. | C81: W2 | D81: March | E81: 3 | F81: 3 | G81: 3 | H81: 3 | I81: A | J81: 3 | K81: 3 | L81: 3 | M81: 3 | N81: 3
A82: 713 Douglas | B82: Prov. Capital Comm, Cancelled by PCC, requested to resume August per Jim Karakai requires monthly PO | C82: W2 | D82: Sept - Edwards | E82: 3 | F82: 3 | G82: 3 | H82: 3 | I82: 3 | J82: Cancelled | N82: 3 | O82: A
A83: 2151 Haultain | B83: Quadra Pacific | C83: T | D83: Oct | E83: 3 | F83: 3 | G83: 3 | H83: 3 | I83: 3 | J83: 3 | K83: 3 | L83: 3 | M83: 3 | N83: 3 | P83: A
A84: 2230 Cadboro Bay | B84: Quadra Pacific | C84: T | D84: Nov | E84: A | F84: 3 | G84: 3 | H84: 3 | I84: 3 | J84: 3 | K84: 3 | L84: 3 | M84: 3 | N84: 3
A85: 3244 Quadra | B85: Quadra Pacific | C85: W4 | D85: May | E85: 3 | F85: Cancelled | K85: A
A86: 350 & 360 Douglas | B86: Quadra Pacific | C86: T | D86: April | E86: 3 | F86: 3 | G86: 3 | H86: 3 | I86: 3 | J86: A | K86: 3 | L86: 3 | M86: 3 | N86: 3
A87: 415 Michigan | B87: Quadra Pacific | C87: T | D87: Feb | E87: 3 | F87: 3 | G87: 3 | H87: A | I87: 3 | J87: 3 | K87: 3 | L87: 3 | M87: 3 | N87: 3
A88: 435 Michigan | B88: Quadra Pacific | C88: T | D88: Feb | E88: 3 | F88: 3 | G88: 3 | H88: A | I88: 3 | J88: 3 | K88: 3 | L88: 3 | M88: 3 | N88: 3
A89: 890 Academy Close | B89: Quadra Pacific | C89: T | D89: May | E89: 3 | F89: 3 | G89: 3 | H89: 3 | I89: 3 | J89: 3 | K89: A | L89: 3 | M89: 3 | N89: 3
A90: 1551 Cedar Hill X Rd. | B90: Richmond Prop. | C90: W4 | D90: Nov | E90: A | F90: 3 | G90: 3 | H90: 3 | I90: 3 | J90: 3 | K90: 3 | L90: 3 | M90: 3
A91: 3301 Douglas Street | B91: Richmond Prop. | C91: W4 | D91: Feb | E91: 3 | F91: 3 | G91: 3 | H91: A | I91: 3 | J91: 3 | K91: 3 | L91: 3 | M91: 3
A92: 752 - 756 Fort | B92: Richmond Prop. | C92: W1 | D92: Jan | E92: 3 | F92: 3 | G92: A | H92: 3 | I92: 3 | J92: 3 | K92: 3 | L92: 3 | M92: 3 | N92: 3
A93: 595 Pandora | B93: Richmond Prop. | C93: W2 | D93: May | E93: 3 | F93: 3 | G93: 3 | H93: 3 | I93: 3 | J93: 3 | K93: A | L93: 3 | M93: 3 | N93: 3
A94: 710 Fort | B94: Ritz Hotel | C94: W1 | D94: July | L94: 3 | M94: A | N94: 3
A95: 1019 Wharf @ $50/mth | B95: SDM Realty | C95: W1 | D95: August | E95: NA - Till Further notice
A96: 1149 Rockland | B96: Strata Plan Vis 248 | C96: T | D96: May-by others | E96: 3 | F96: 3 | G96: 3 | H96: 3 | I96: 3 | J96: 3 | K96: A | L96: 3 | M96: 3 | N96: 3
A97: 1721 Quadra | B97: Strata Plan Vis 5799 | C97: W1 | D97: August | E97: 3 | F97: 3 | G97: 3 | H97: 3 | I97: 3 | J97: 3 | K97: 3 | L97: 3 | M97: 3 | N97: A
A98: 950 Kings | B98: Univ. Canada West | C98: W4 | D98: April | E98: 3 | F98: 3 | G98: 3 | H98: 3 | I98: 3 | J98: A | K98: 3 | L98: 3 | M98: 3
A99: 636 Fisgard | B99: Vic Chinese Sch | C99: T | D99: Jan | E99: 3 | F99: 3 | G99: A | H99: 3 | I99: 3 | J99: 3 | K99: 3 | L99: 3 | M99: NA | N99: NA
A100: 727 Fisgard | B100: Victoria Place Prop | C100: W2 | D100: Sept | E100: 3 | F100: 3 | G100: 3 | H100: 3 | I100: Rung during Ver | J100: 3 | K100: 3 | L100: 3 | M100: 3 | N100: A
...

Sheet MBT - summary
A2: STATUS- (ACTIVE, CANCELLED, ON HOLD) | B2: (Multiple Items) | D2: TEST DAY | E2: T | G2: Apr-13 | H2: (All)
A4: Row Labels | B4: ANNUAL | C4: ADDRESS | D4: SITE NAME | E4: KEYS | F4: MONITORING | G4: PANEL | H4: MBT NOTES
A5: 1 | B5: January | C5: 625 Hillside | D5: n/a
D6: Pemberton Holmes | E6: Y 526 | F6: none | G6: Edwards 6616 | H6: (blank)
A7: 2 | B7: June | C7: 1581 Hillside | D7: n/a
D8: Colliers | E8: W 1851 | F8: M6 T A | G8: Edwards EST 6616 | H8: in room by McDonalds 24hr drive thru. Annunciator at 1581 lobby to 2nd floor
A9: 3 | B9: Oct | C9: 1560 Hillside | D9: n/a
D10: Hutton | E10: B 0561 | F10: none | G10: Edwards Custom 6500 | H10: Strata#1214 site contact Jerry 250-519-4728. Lock Power Rm door. Press reset button on Mag-Lock supply box. Aux disconnect.
A11: 4 | B11: March | C11: 1510 Hillside | D11: The Pearl
D12: Firm Management | E12: BT 0151 | F12: PRICES T A | G12: Mircom 1000 | H12: Entrance at left side of bldg. Elec. Rm off driveway. Signal silence LED may not illuminate but bells will stop.
A13: 5 | B13: May | C13: 1366 Hillside | D13: (blank)
D14: Gibraltar | E14: A 6631 | F14: (blank) | G14: (blank) | H14: (blank)
A15: 6 | B15: Oct | C15: 2151 Haultain | D15: (blank)
D16: Quadra Pacific | E16: C 1512 | F16: (blank) | G16: (blank) | H16: (blank)
A17: 7 | B17: Nov | C17: 2230 Cadboro Bay | D17: (blank)
D18: Quadra Pacific | E18: D 0322 | F18: (blank) | G18: (blank) | H18: (blank)
A19: 8 | B19: Dec | C19: 2250 Oak Bay | D19: (blank)
D20: Colliers | E20: E 0522 | F20: (blank) | G20: (blank) | H20: (blank)
A21: 9 | B21: March | C21: 2119 Oak Bay | D21: (blank)
D22: Hutton | E22: P 9112 | F22: (blank) | G22: (blank) | H22: (blank)
A23: 10 | B23: August | C23: 1975 Lee | D23: (blank)
D24: Hutton | E24: F 5791 | F24: (blank) | G24: (blank) | H24: (blank)
A25: 11 | B25: May | C25: 1655 Begbie | D25: (blank)
D26: Proline | E26: G 5561 | F26: (blank) | G26: (blank) | H26: (blank)
A27: 12 | B27: Jan | C27: 2211 Shelbourne | D27: (blank)
D28: Boormans | E28: GT 1122 | F28: (blank) | G28: (blank) | H28: (blank)
A29: 13 | B29: Feb | C29: 1436 Harrison | D29: (blank)
D30: Boormans | E30: H 6341 | F30: (blank) | G30: (blank) | H30: (blank)
A31: 14 | B31: May-by others | C31: 1149 Rockland | D31: (blank)
D32: Strata Plan Vis 248 | E32: J 9411 | F32: (blank) | G32: (blank) | H32: (blank)
A33: 15 | B33: Jan | C33: 1166 Rockland | D33: (blank)
D34: Freelance | E34: K 6611 | F34: (blank) | G34: (blank) | H34: (blank)
A35: 16 | B35: Dec | C35: 945 McClure | D35: (blank)
D36: Boormans | E36: L 549 | F36: (blank) | G36: (blank) | H36: (blank)
A37: 17 | B37: Jan | C37: 1012 Collinson | D37: (blank)
D38: Hutton | E38: M 1201 | F38: (blank) | G38: (blank) | H38: (blank)
A39: 18 | B39: Feb | C39: 605 Cook | D39: (blank)
D40: Brown Bros | E40: N 506 | F40: (blank) | G40: (blank) | H40: (blank)
A41: 19 | B41: June | C41: 415 Linden | D41: (blank)
D42: Firm Management | E42: R 514 | F42: (blank) | G42: (blank) | H42: (blank)
A43: 20 | B43: April | C43: 906 Southgate Street | D43: (blank)
D44: Strata Plan Vis 742 | E44: HT 609 | F44: (blank) | G44: (blank) | H44: (blank)
A45: 21 | B45: Oct | C45: 230 Cook | D45: (blank)
D46: Colliers (230 Cook Street Holdings c/o Colliers) | E46: Z 032 | F46: (blank) | G46: (blank) | H46: (blank)
A47: 22 | B47: Nov | C47: 209 Cook | D47: (blank)
D48: William Apartments | E48: Q 902 | F48: (blank) | G48: (blank) | H48: (blank)
A49: 23 | B49: Sept | C49: 670 Dallas | D49: (blank)
D50: Hutton | E50: O 076 | F50: (blank) | G50: (blank) | H50: (blank)
A51: 24 | B51: Sept | C51: 502 Dallas | D51: (blank)
D52: Brown Bros | E52: CT 205 | F52: (blank) | G52: (blank) | H52: (blank)
A53: 25 | B53: Jan | C53: 120 Douglas | D53: (blank)
D54: Boormans | E54: AT 021 | F54: (blank) | G54: (blank) | H54: (blank)
A55: 26 | B55: April | C55: 350 & 360 Douglas | D55: (blank)
D56: Quadra Pacific | E56: T 053 | F56: (blank) | G56: (blank) | H56: (blank)
A57: 27 | B57: May | C57: 890 Academy | D57: (blank)
D58: Quadra Pacific | E58: S 098 | F58: (blank) | G58: (blank) | H58: (blank)
A59: 28 | B59: Feb | C59: 420 Parry | D59: (blank)
D60: Firm Management | E60: ET 024 | F60: (blank) | G60: (blank) | H60: (blank)
A61: 29 | B61: Feb | C61: 435 Michigan | D61: (blank)
D62: Quadra Pacific | E62: V 534 | F62: (blank) | G62: (blank) | H62: (blank)
A63: 30 | B63: Feb | C63: 415 Michigan | D63: (blank)
D64: Quadra Pacific | E64: U 514 | F64: (blank) | G64: (blank) | H64: (blank)
A65: 31 | B65: Oct | C65: 60 Dallas | D65: (blank)
D66: Boormans | E66: FT 06 | F66: (blank) | G66: (blank) | H66: (blank)
A67: 32 | B67: Feb | C67: 425-435 Simcoe | D67: (blank)
D68: Gateway | E68: DT 524 | F68: (blank) | G68: (blank) | H68: (blank)
A69: (blank) | B69: August | C69: 1230 Fort Street | D69: (blank)
D70: Randall North | E70: OT 0321 | F70: (blank) | G70: (blank) | H70: (blank)
A71: 33 | B71: Oct- Edwards | C71: 625 Fisgard | D71: (blank)
D72: CRD | E72: KEY AT SITE | F72: (blank) | G72: (blank) | H72: (blank)
A73: 34 | B73: Jan | C73: 636 Fisgard | D73: (blank)
D74: Vic Chinese Sch | E74: KEY AT SITE | F74: (blank) | G74: (blank) | H74: (blank)

Sheet Monthly- key by address
A1: Street # | B1: Street Name | C1: Site Address | D1: Key code | E1: 123 | F1: Key | G1: code | H1: # keys | I1: Day of Monthly
A2: 890 | B2: Academy Close | C2: =CONCATENATE(A2," ",B2) -> 890 Academy Close | D2: S 098 | E2: 1 | F2: S | G2: 98 | H2: 2 KEYS | I2: 1st Thursday
A3: 28 | B3: Bastion | C3: =CONCATENATE(A3," ",B3) -> 28 Bastion | D3: KEY AT SITE | E3: 0 | F3: KEY AT SITE | H3: n/a | I3: 2nd Wednesday
A4: 31 | B4: Bastion | C4: =CONCATENATE(A4," ",B4) -> 31 Bastion | H4: 2 KEYS | I4: 2nd Wednesday
A5: 1655 | B5: Begbie | C5: =CONCATENATE(A5," ",B5) -> 1655 Begbie | D5: G 5561 | E5: 1 | F5: G | G5: 5561 | H5: 2 KEYS | I5: 1st Thursday
A6: 470 | B6: Belleville | C6: =CONCATENATE(A6," ",B6) -> 470 Belleville | D6: KEY AT SITE | E6: 0 | F6: KEY AT SITE | H6: n/a | I6: 1st Wednesday
A7: 2626 | B7: Blackwood | C7: =CONCATENATE(A7," ",B7) -> 2626 Blackwood | D7: BC 6262 | E7: 3 | F7: BC | G7: 6262 | H7: 2 KEYS | I7: 4th Wednesday
A8: 780 | B8: Blanshard | C8: =CONCATENATE(A8," ",B8) -> 780 Blanshard | D8: B 087 | E8: 1 | F8: B | G8: 87 | H8: 1 KEY, PROXCARD | I8: 1st Wednesday
A9: 810 | B9: Blanshard | C9: =CONCATENATE(A9," ",B9) -> 810 Blanshard | D9: XN 810 | E9: 3 | F9: XN | G9: 810 | H9: 1 KEY, PROXCARD | I9: 1st Wednesday
A10: 1810 | B10: Blanshard | C10: =CONCATENATE(A10," ",B10) -> 1810 Blanshard | D10: RR 0181 | E10: 2 | F10: RR | G10: 181 | H10: 1 KEY, 1 LOCKBOX, PROXCARD | I10: 2nd Wednesday
A11: 1322 | B11: Broad | C11: =CONCATENATE(A11," ",B11) -> 1322 Broad | D11: KEY AT SITE | E11: 0 | F11: KEY AT SITE | H11: n/a | I11: 1st Wednesday
A12: 1221 | B12: Broad | C12: =CONCATENATE(A12," ",B12) -> 1221 Broad | D12: XX 1221 | E12: 2 | F12: XX | G12: 1221 | I12: 2nd Wednesday
A13: 1005 | B13: Broad | C13: =CONCATENATE(A13," ",B13) -> 1005 Broad | D13: K 5001 | E13: 1 | F13: K | G13: 5001 | H13: 3 KEYS | I13: 1st Wednesday
A14: 1205 | B14: Broad/650 View | C14: =CONCATENATE(A14," ",B14) -> 1205 Broad/650 View | D14: BB 5021 | E14: 2 | F14: BB | G14: 5021 | H14: 2 KEYS | I14: 2nd Wednesday
A15: 609 | B15: Broughton | C15: =CONCATENATE(A15," ",B15) -> 609 Broughton | D15: I 906 | E15: 1 | F15: I | G15: 906 | H15: 3 KEYS, FOB | I15: 1st Wednesday
A16: 765-777 | B16: Broughton | C16: =CONCATENATE(A16," ",B16) -> 765-777 Broughton | D16: KEY AT SITE | E16: 0 | F16: KEY AT SITE | H16: n/a | I16: 1st Wednesday
A17: 703 | B17: Broughton | C17: =CONCATENATE(A17," ",B17) -> 703 Broughton | D17: H 307 | E17: 1 | F17: H | G17: 307 | H17: 2 KEYS | I17: 1st Wednesday
A18: 850 | B18: Burdett | C18: =CONCATENATE(A18," ",B18) -> 850 Burdett | D18: A 058 | E18: 1 | F18: A | G18: 58 | H18: 2 KEYS, 2 LOCKBOX KEYS | I18: 1st Wednesday
A19: 2230 | B19: Cadboro Bay | C19: =CONCATENATE(A19," ",B19) -> 2230 Cadboro Bay | D19: D 0322 | E19: 1 | F19: D | G19: 322 | H19: 2 KEYS | I19: 1st Thursday
A20: 1551 | B20: Cedar Hill X Rd | C20: =CONCATENATE(A20," ",B20) -> 1551 Cedar Hill X Rd | D20: KL 1551 | E20: 3 | F20: KL | G20: 1551 | H20: 1 KEY | I20: 4th Wednesday
A21: 1012 | B21: Collinson | C21: =CONCATENATE(A21," ",B21) -> 1012 Collinson | D21: M 2101 | E21: 1 | F21: M | G21: 2101 | H21: 3 KEYS | I21: 1st Thursday
A22: 1947 | B22: Cook | C22: =CONCATENATE(A22," ",B22) -> 1947 Cook | D22: KEY AT SITE | E22: 0 | F22: KEY AT SITE | H22: n/a | I22: 1st Wednesday
A23: 605 | B23: Cook | C23: =CONCATENATE(A23," ",B23) -> 605 Cook | D23: N 506 | E23: 1 | F23: N | G23: 506 | H23: 3 KEYS | I23: 1st Thursday
A24: 230 | B24: Cook | C24: =CONCATENATE(A24," ",B24) -> 230 Cook | D24: Z 032 | E24: 1 | F24: Z | G24: 32 | H24: 1 KEY | I24: 1st Thursday
A25: 209 | B25: Cook | C25: =CONCATENATE(A25," ",B25) -> 209 Cook | D25: Q 902 | E25: 1 | F25: Q | G25: 902 | H25: 1 KEY | I25: 1st Thursday
A26: 722 | B26: Cormorant | C26: =CONCATENATE(A26," ",B26) -> 722 Cormorant | D26: QQ 227 | E26: 2 | F26: QQ | G26: 227 | H26: 2 KEYS | I26: 2nd Wednesday
A27: 770 | B27: Cormorant | C27: =CONCATENATE(A27," ",B27) -> 770 Cormorant | D27: KK 077 | E27: 2 | F27: KK | G27: 77 | H27: 5 KEYS | I27: 2nd Wednesday
A28: 707 | B28: Courtney | C28: =CONCATENATE(A28," ",B28) -> 707 Courtney | D28: A 707 | E28: 1 | F28: A | G28: 707 | H28: 1 KEY, 1 FOB | I28: 1st Wednesday
A29: 3400 | B29: Davidson | C29: =CONCATENATE(A29," ",B29) -> 3400 Davidson | D29: KEY AT SITE | E29: 0 | F29: KEY AT SITE | H29: n/a | I29: 4th Wednesday
A30: 670 | B30: Dallas | C30: =CONCATENATE(A30," ",B30) -> 670 Dallas | D30: O 076 | E30: 1 | F30: O | G30: 76 | H30: 2 KEYS | I30: 1st Thursday
A31: 188 | B31: Douglas | C31: =CONCATENATE(A31," ",B31) -> 188 Douglas | D31: S 881 | E31: 1 | F31: S | G31: 881 | H31: 13 KEYS (May be reduced) | I31: 1st Wednesday
A32: 210 | B32: Douglas | C32: =CONCATENATE(A32," ",B32) -> 210 Douglas | D32: AT 021 | E32: 3 | F32: AT | G32: 21 | H32: 2 KEYS | I32: 1st Thursday
A33: 3045 | B33: Douglas | C33: =CONCATENATE(A33," ",B33) -> 3045 Douglas | D33: GH 5403 | E33: 3 | F33: GH | G33: 5403 | H33: 1KEY | I33: 4th Wednesday
A34: 3301 | B34: Douglas | C34: =CONCATENATE(A34," ",B34) -> 3301 Douglas | D34: HI 1033 | E34: 3 | F34: HI | G34: 1033 | H34: 1 KEY | I34: 4th Wednesday
A35: 713 | B35: Douglas | C35: =CONCATENATE(A35," ",B35) -> 713 Douglas | D35: KEY AT SITE | E35: 0 | F35: KEY AT SITE | H35: n/a | I35: 2nd Wednesday
A36: 1207 | B36: Douglas | C36: =CONCATENATE(A36," ",B36) -> 1207 Douglas | D36: L 7021 | E36: 1 | F36: L | G36: 7021 | H36: 4 KEYS | I36: 1st Wednesday
A37: 350 & 360 | B37: Douglas | C37: =CONCATENATE(A37," ",B37) -> 350 & 360 Douglas | D37: T 053 | E37: 1 | F37: T | G37: 53 | H37: 3 KEYS | I37: 1st Thursday
A38: 1000 - 1012 | B38: Douglas | C38: =CONCATENATE(A38," ",B38) -> 1000 - 1012 Douglas | D38: J 2101 | E38: 1 | F38: J | G38: 2101 | H38: 2 KEYS | I38: 1st Wednesday
A39: 415 | B39: Dunedin | C39: =CONCATENATE(A39," ",B39) -> 415 Dunedin | D39: FG 514 | E39: 3 | F39: FG | G39: 514 | H39: 1 KEY | I39: 4th Wednesday
A40: 1500 | B40: Elford | C40: =CONCATENATE(A40," ",B40) -> 1500 Elford | D40: I 0051 | E40: 1 | F40: I | G40: 51 | H40: 2 KEYS | I40: 1st Thursday
A41: 636 | B41: Fisgard | C41: =CONCATENATE(A41," ",B41) -> 636 Fisgard | D41: KEY AT SITE | E41: 0 | F41: KEY AT SITE | H41: n/a | I41: 1st Thursday
A42: 625 | B42: Fisgard | C42: =CONCATENATE(A42," ",B42) -> 625 Fisgard | D42: KEY AT SITE | E42: 0 | F42: KEY AT SITE | H42: n/a | I42: 2nd Wednesday
A43: 727 | B43: Fisgard | C43: =CONCATENATE(A43," ",B43) -> 727 Fisgard | D43: KEY AT SITE | E43: 0 | F43: KEY AT SITE | H43: n/a | I43: 2nd Wednesday
A44: 770 | B44: Fisgard | C44: =CONCATENATE(A44," ",B44) -> 770 Fisgard | D44: RR 077 | I44: 2nd Wednesday
A45: 530 | B45: Fort | C45: =CONCATENATE(A45," ",B45) -> 530 Fort | D45: NN 035 | E45: 2 | F45: NN | G45: 35 | H45: Pending | I45: 2nd Wednesday
A46: 825-827 | B46: Fort | C46: =CONCATENATE(A46," ",B46) -> 825-827 Fort | D46: O 528 | E46: 1 | F46: O | G46: 528 | H46: 4 KEYS, PROXCARD | I46: 1st Wednesday
A47: 838 | B47: Fort | C47: =CONCATENATE(A47," ",B47) -> 838 Fort | D47: E 838 | E47: 1 | F47: E | G47: 838 | H47: 1 KEY | I47: 1st Wednesday
A48: 752 | B48: Fort | C48: =CONCATENATE(A48," ",B48) -> 752 Fort | D48: F 257 | E48: 1 | F48: F | G48: 257 | H48: 1 KEY, 1 LOCKBOX | I48: 1st Wednesday
A49: 777 | B49: Fort | C49: =CONCATENATE(A49," ",B49) -> 777 Fort | D49: G 777 | E49: 1 | F49: G | G49: 777 | H49: 1 KEY | I49: 1st Wednesday
A50: 530 | B50: Fraser | C50: =CONCATENATE(A50," ",B50) -> 530 Fraser | D50: KEY AT SITE | E50: 0 | F50: KEY AT SITE | H50: n/a | I50: 4th Wednesday
A51: 410 | B51: Garbally | C51: =CONCATENATE(A51," ",B51) -> 410 Garbally | D51: EF 014 | E51: 3 | F51: EF | G51: 14 | H51: 1 KEY | I51: 4th Wednesday
A52: 155-157 | B52: Gorge East | C52: =CONCATENATE(A52," ",B52) -> 155-157 Gorge East | D52: BC 551 | E52: 3 | F52: BC | G52: 551 | H52: 3 KEYS | I52: 4th Wednesday
A53: 217 - 219 | B53: Gorge | C53: =CONCATENATE(A53," ",B53) -> 217 - 219 Gorge | D53: OP 712 | E53: 3 | F53: OP | G53: 712 | H53: 4 KEYS | I53: 4th Wednesday
A54: 1022 | B54: Government | C54: =CONCATENATE(A54," ",B54) -> 1022 Government | D54: KEY AT SITE | E54: 0 | F54: KEY AT SITE | H54: n/a | I54: 2nd Wednesday
A55: 1000 | B55: Government [536 Broughton] | C55: =CONCATENATE(A55," ",B55) -> 1000 Government [536 Broughton] | D55: OO 0001 | E55: 2 | F55: OO | G55: 1 | H55: 1 KEY | I55: 2nd Wednesday
A56: 1006 | B56: Government/ 1007-9 Langley | C56: =CONCATENATE(A56," ",B56) -> 1006 Government/ 1007-9 Langley | D56: PP 6001 | E56: 2 | F56: PP | G56: 6001 | H56: 1 KEY | I56: 2nd Wednesday
A57: 1200 | B57: Government/50 Bastion | C57: =CONCATENATE(A57," ",B57) -> 1200 Government/50 Bastion | D57: AA 0021 | E57: 2 | F57: AA | G57: 21 | H57: 2 KEYS | I57: 2nd Wednesday
A58: 1436 | B58: Harrison | C58: =CONCATENATE(A58," ",B58) -> 1436 Harrison | D58: H 6341 | E58: 1 | F58: H | G58: 6341 | H58: 1 KEY, BLACK FOB | I58: 1st Thursday
A59: 2151 | B59: Haultain | C59: =CONCATENATE(A59," ",B59) -> 2151 Haultain | D59: C 1512 | E59: 1 | F59: C | G59: 1512 | H59: 2 KEYS | I59: 1st Thursday
A60: 655 | B60: Herald | C60: =CONCATENATE(A60," ",B60) -> 655 Herald | D60: LL 556 | E60: 2 | F60: LL | G60: 556 | H60: 2 KEYS | I60: 2nd Wednesday
A61: 625 | B61: Hillside | C61: =CONCATENATE(A61," ",B61) -> 625 Hillside | D61: Y 526 | E61: 1 | F61: Y | G61: 526 | H61: 2 KEYS | I61: 1st Thursday
A62: 1111 | B62: Hillside | C62: =CONCATENATE(A62," ",B62) -> 1111 Hillside | D62: OP 1111 | E62: 3 | F62: OP | G62: 1111 | H62: 3 KEYS | I62: 4th Wednesday
A63: 1366 | B63: Hillside | C63: =CONCATENATE(A63," ",B63) -> 1366 Hillside | D63: A 6631 | E63: 1 | F63: A | G63: 6631 | H63: 4 KEYS (2 x 2 - duplicated, spare in drawer) | I63: 1st Thursday
A64: 1510 | B64: Hillside | C64: =CONCATENATE(A64," ",B64) -> 1510 Hillside | D64: BT 0151 | E64: 3 | F64: BT | G64: 151 | H64: 2 KEYS | I64: 1st Thursday
A65: 1560 | B65: Hillside | C65: =CONCATENATE(A65," ",B65) -> 1560 Hillside | D65: B 0561 | E65: 1 | F65: B | G65: 561 | H65: 2 KEYS | I65: 1st Thursday
A66: 1581 | B66: Hillside | C66: =CONCATENATE(A66," ",B66) -> 1581 Hillside | D66: W 1851 | E66: 1 | F66: W | G66: 1851 | H66: 2 KEYS | I66: 1st Thursday
... A70: 1223 | B70: Johnson | C70: =CONCATENATE(A70," ",B70) -> 1223 Johnson | D70: II 3221 | E70: 2 | F70: II | G70: 3221 | H70: 2 KEYS | I70: 2nd Wednesday
A71: 545 | B71: Johnson | C71: =CONCATENATE(A71," ",B71) -> 545 Johnson | D71: KEY AT SITE | E71: 0 | F71: KEY AT SITE | H71: n/a | I71: 1st Wednesday
A72: 553/563 | B72: Johnson | C72: =CONCATENATE(A72," ",B72) -> 553/563 Johnson | D72: KEY AT SITE | E72: 0 | F72: KEY AT SITE | H72: n/a | I72: 1st Wednesday
A73: 1034 | B73: Johnson | C73: =CONCATENATE(A73," ",B73) -> 1034 Johnson | D73: MM 4301 | E73: 2 | F73: MM | G73: 4301 | H73: 2 KEYS | I73: 2nd Wednesday
A74: 1975 | B74: Lee | C74: =CONCATENATE(A74," ",B74) -> 1975 Lee | D74: F 5791 | E74: 1 | F74: F | G74: 5791 | H74: 2 KEYS | I74: 1st Thursday
A75: 945 | B75: McClure | C75: =CONCATENATE(A75," ",B75) -> 945 McClure | D75: L 549 | E75: 1 | F75: L | G75: 549 | H75: 2 KEYS | I75: 1st Thursday
A76: 1005 & 1009 | B76: McKenzie | C76: =CONCATENATE(A76," ",B76) -> 1005 & 1009 McKenzie | D76: MN 5001 | E76: 3 | F76: MN | G76: 5001 | H76: 4 KEYS | I76: 4th Wednesday
A77: 545 | B77: Manchester/520 Dunedin | C77: =CONCATENATE(A77," ",B77) -> 545 Manchester/520 Dunedin | D77: TT 545 | E77: 2 | F77: TT | G77: 545 | H77: 3 KEYS, 1 TOUCH KEY | I77: 2nd Wednesday
A78: 435 | B78: Michigan | C78: =CONCATENATE(A78," ",B78) -> 435 Michigan | D78: V 534 | E78: 1 | F78: V | G78: 534 | H78: 2 KEYS | I78: 1st Thursday
A79: 415 | B79: Michigan | C79: =CONCATENATE(A79," ",B79) -> 415 Michigan | D79: U 514 | E79: 1 | F79: U | G79: 514 | H79: 1 KEY | I79: 1st Thursday
A80: 2170 | B80: Mt. Newton X | C80: =CONCATENATE(A80," ",B80) -> 2170 Mt. Newton X | D80: KEY AT SITE | E80: 0 | F80: KEY AT SITE | H80: n/a | I80: 4th Wednesday
A81: 1640 | B81: Oak Bay | C81: =CONCATENATE(A81," ",B81) -> 1640 Oak Bay | D81: N 0461 | E81: 1 | F81: N | G81: 461 | H81: 3 KEYS | I81: 1st Wednesday
A82: 2250 | B82: Oak Bay | C82: =CONCATENATE(A82," ",B82) -> 2250 Oak Bay | D82: E 0522 | E82: 1 | F82: E | G82: 522 | H82: 2 KEYS | I82: 1st Thursday
A83: 595 | B83: Pandora | C83: =CONCATENATE(A83," ",B83) -> 595 Pandora | D83: CC 595 | E83: 2 | F83: CC | G83: 595 | H83: 1 KEY. PROXCARD | I83: 2nd Wednesday
A84: 1368 | B84: Pandora | C84: =CONCATENATE(A84," ",B84) -> 1368 Pandora | D84: JJ 8631 | E84: 2 | F84: JJ | G84: 8631 | H84: 2 KEYS | I84: 2nd Wednesday
A85: 506 | B85: Pandora | C85: =CONCATENATE(A85," ",B85) -> 506 Pandora | D85: KEY AT SITE | E85: 0 | F85: KEY AT SITE | H85: n/a | I85: 1st Wednesday
A86: 613 | B86: Pandora | C86: =CONCATENATE(A86," ",B86) -> 613 Pandora | D86: KEY AT SITE | E86: 0 | F86: KEY AT SITE | H86: n/a | I86: 2nd Wednesday
A87: 909 | B87: Pembroke | C87: =CONCATENATE(A87," ",B87) -> 909 Pembroke | D87: M 909 | E87: 1 | F87: M | G87: 909 | H87: 3 KEYS | I87: 1st Wednesday
A88: 1250 | B88: Quadra | C88: =CONCATENATE(A88," ",B88) -> 1250 Quadra | D88: SS 0521 | E88: 2 | F88: SS | G88: 521 | H88: 2 KEYS | I88: 2nd Wednesday
A89: 1721 | B89: Quadra | C89: =CONCATENATE(A89," ",B89) -> 1721 Quadra | D89: P 1271 | E89: 1 | F89: P | G89: 1271 | H89: 2 KEYS | I89: 1st Wednesday
A90: 3939 | B90: Quadra | C90: =CONCATENATE(A90," ",B90) -> 3939 Quadra | D90: JK 9393 | E90: 3 | F90: JK | G90: 9393 | H90: 2 KEYS | I90: 4th Wednesday
A91: 3244 | B91: Quadra | C91: =CONCATENATE(A91," ",B91) -> 3244 Quadra | D91: IJ 4423 | E91: 3 | F91: IJ | G91: 4423 | H91: 2 KEYS | I91: 4th Wednesday
A92: 710 | B92: Redbrick | C92: =CONCATENATE(A92," ",B92) -> 710 Redbrick | D92: NO 017 | E92: 3 | F92: NO | G92: 17 | H92: 2 KEYS | I92: 4th Wednesday
A93: 10459 & 10461 | B93: Resthaven | C93: =CONCATENATE(A93," ",B93) -> 10459 & 10461 Resthaven | D93: LM 95401 | E93: 3 | F93: LM | G93: 95401 | H93: 2 KEYS | I93: 4th Wednesday
A94: 1133A | B94: Reynolds | C94: =CONCATENATE(A94," ",B94) -> 1133A Reynolds | D94: PQ 3311 | E94: 3 | F94: PQ | G94: 3311 | H94: 2 KEYS | I94: 4th Wednesday
A95: 2020 | B95: Richmond | C95: =CONCATENATE(A95," ",B95) -> 2020 Richmond | D95: KEY AT SITE | E95: 0 | F95: KEY AT SITE | H95: n/a | I95: 1st Wednesday
A96: 1149 | B96: Rockland | C96: =CONCATENATE(A96," ",B96) -> 1149 Rockland | D96: J 9411 | E96: 1 | F96: J | G96: 9411 | H96: 2 KEYS, PROXCARD | I96: 1st Thursday
A97: 1166 | B97: Rockland | C97: =CONCATENATE(A97," ",B97) -> 1166 Rockland | D97: K 6611 | E97: 1 | F97: K | G97: 6611 | H97: 2 KEYS | I97: 1st Thursday
A98: 55 | B98: Songhees | C98: =CONCATENATE(A98," ",B98) -> 55 Songhees | D98: AB 55 | E98: 3 | F98: AB | G98: 55 | H98: 3 KEYS | I98: 4th Wednesday
A99: 990 | B99: View & 911 Yates | C99: =CONCATENATE(A99," ",B99) -> 990 View & 911 Yates | D99: EE 099 | E99: 2 | F99: EE | G99: 99 | H99: 1 KEY | I99: 2nd Wednesday
A100: 708 | B100: View | C100: =CONCATENATE(A100," ",B100) -> 708 View | D100: KEY AT SITE | E100: 0 | F100: KEY AT SITE | H100: n/a | I100: 2nd Wednesday
A101: 3008 - 10 | B101: Washington | C101: =CONCATENATE(A101," ",B101) -> 3008 - 10 Washington | D101: CD 8003 | E101: 3 | F101: CD | G101: 8003 | H101: 4 KEYS | I101: 4th Wednesday
A102: 380 | B102: Waterfront | C102: =CONCATENATE(A102," ",B102) -> 380 Waterfront | D102: DE 083 | E102: 3 | F102: DE | G102: 83 | H102: 2 KEYS | I102: 4th Wednesday
A103: 1019 | B103: Wharf | C103: =CONCATENATE(A103," ",B103) -> 1019 Wharf | D103: D 9101 | E103: 1 | F103: D | G103: 9101 | H103: 3 KEYS, PROXCARD | I103: 1st Wednesday
...

Sheet Jan 2026 - Dec 2026
A1: ADDRESS | B1: PROPERTY MANAGEMENT COMPANY | C1: NOTES | D1: BARCODE # | E1: Price/month | F1: Area | G1: start up date | H1: STATUS- (ACTIVE, CANCELLED, ON HOLD) | I1: KEYS | J1: TEST DAY | K1: ANNUAL | L1: 46023 | M1: 46054 | N1: 46082 | O1: 46113 | P1: 46143 | Q1: 46174 | R1: 46204 | S1: 46235 | T1: 46266 | U1: 46296 | V1: 46327 | W1: 46357
A2: #103-4475 Viewmont | B2: Hansbraun | C2: MONTHLY EXT & ELU TESTS - Cancelled in November 2025 | D2: - | E2: 75 | F2: Saanich, BC | G2: 45559 | H2: CANCELLED | I2: No keys | J2: - | K2: May | L2: - | M2: - | N2: - | O2: - | P2: - | Q2: - | R2: - | S2: - | T2: - | U2: - | V2: - | W2: -
A3: 10 Paul Kane/11 Cooperage Place | B3: Proline | D3: 100161 | E3: 55 | F3: Esquimalt, BC | G3: 41730 | H3: ACTIVE | I3: UV 01 | J3: W1-R7 | K3: May | L3: Y | M3: Y | N3: Y | O3: Y | P3: ANNUAL
A4: 1000 Mckenzie Avenue | B4: Starlight/Devon | C4: Increase to $65 after January 2026 | D4: 100229 | E4: 65 | F4: Saanich, BC | G4: 45559 | H4: ACTIVE | I4: M 0001 | J4: W1-R6 | K4: May | L4: Y | M4: Y | N4: Y | O4: X
A5: 1000-1012 Douglas Street | B5: Itziar Management Ltd. (0824606 BC Ltd.) | D5: 100539 | E5: 60 | F5: Victoria, BC | G5: 45589 | H5: ACTIVE | I5: D 2101 | J5: TH2-R15 | K5: June | L5: Y | M5: Y | N5: Y | O5: Y
A6: 1001 Wharf Street | B6: Pastoral Developments Ltd. | D6: 100861 | E6: 55 | F6: Victoria, BC | G6: 43313 | H6: ACTIVE | I6: NA 1001 K2-F1 | J6: TH2-R15 | K6: October | L6: Y | M6: Y | N6: Y | O6: Y
A7: 10016 3rd Street | B7: Cornerstone | D7: 100203 | E7: 50 | F7: Sidney, BC | G7: 44949 | H7: ACTIVE | I7: 358 | J7: F2-R16 | K7: February | L7: Y | M7: Y | N7: ANNUAL | O7: Y
A8: 10017 Avenger Way | B8: Lumberworld Operations Ltd. | C8: Cancelled April 2026 - R16 | D8: - | E8: 75 | F8: Sidney, BC | G8: 45863 | H8: CANCELLED | I8: VG 71001 | J8: - | K8: October | L8: Y | M8: Y | N8: X | O8: Y | P8: - | Q8: - | R8: - | S8: - | T8: - | U8: - | V8: - | W8: -
A9: 1002 Mckenzie Avenue | B9: Starlight/Devon | C9: Increase to $65 after January 2026 | D9: 100966 | E9: 65 | F9: Saanich, BC | G9: 45559 | H9: ACTIVE | I9: M 2001 | J9: W1-R6 | K9: May | L9: Y | M9: Y | N9: Y | O9: X
A10: 1002 Pakington | B10: Proline | D10: 100903 | E10: 50 | F10: Victoria, BC | G10: 44949 | H10: ACTIVE | I10: 146 | J10: TU3-R18 | K10: September | L10: Y | M10: Y | N10: Y | O10: Y
A11: 1002 Wharf Street | B11: Malahat Properties | D11: - | E11: 55 | F11: Victoria, BC | G11: 44174 | H11: ACTIVE | I11: At Reception | J11: TH2-R15 | K11: January | L11: ANNUAL | M11: Y | N11: Y | O11: Y
A12: 10025 Resthaven Drive | B12: Inken Roller c/o Richmond Property Group | D12: 100398 | E12: 50 | F12: Sidney, BC | G12: 44949 | H12: ACTIVE | I12: 349 | J12: F2-R16 | K12: February | L12: Y | M12: ANNUAL | N12: Y | O12: Y
A13: 10030 Resthaven Drive | B13: Raven Property Management Ltd. | D13: 100998 | E13: 75 | F13: Sidney, BC | G13: 44949 | H13: ACTIVE | I13: SC 03001 | J13: F2-R16 | K13: May | L13: Y | M13: Y | N13: Y | O13: Y
A14: 1004 Pemberton Road | B14: Raul Caballero | D14: 100404 | E14: 70 | F14: Victoria, BC | G14: 45161 | H14: ACTIVE | I14: PB 4001 | J14: M1-R1 | K14: December | L14: Y | M14: Y | N14: Y | O14: Y
A15: 1005 & 1009 McKenzie Avenue | B15: Firm Management | C15: Price increase after June 2026 - $60 before that | D15: 100535 | E15: 130 | F15: Saanich, BC | H15: ACTIVE | I15: MN 5001 | J15: TU1-R4 | K15: May | L15: Y | M15: Y | N15: Y | O15: Y | P15: ANNUAL
A16: 1005 Broad Street | B16: Richmond Property Group | D16: 100340 | E16: 55 | F16: Victoria, BC | H16: ACTIVE | I16: K 5001 K4 | J16: TH2-R15 | K16: March | L16: Y | M16: Y | N16: ANNUAL | O16: Y
A17: 1005 Pakington Street | B17: Century 21 Queenswood | D17: 100590 | E17: 50 | F17: Victoria, BC | G17: 44949 | H17: ACTIVE | I17: 171 | J17: TU3-R18 | K17: August | L17: Y | M17: Y | N17: Y | O17: Y
A18: 1005 St. Charles Street | B18: Bross Holdings | D18: 100464 | E18: 55 | F18: Victoria, BC | G18: 45713 | H18: ACTIVE | I18: HC 5001 | J18: TH1-R9 | K18: May | L18: Y | M18: Y | N18: Y | O18: Y
A19: 1006 Fort Street | B19: Colliers | D19: 100619 | E19: 75 | F19: Victoria, BC | G19: 41214 | H19: ACTIVE | I19: ZZ 6001 K3-F1 | J19: M1-R2 | K19: September | L19: Y | M19: Y | N19: Y | O19: Y
A20: 1006 Tolmie Avenue | B20: Century 21 Queenswood | C20: $63.00 credit in QB to be applied to Q2 | D20: 100251 | E20: 60 | F20: Victoria, BC | H20: ACTIVE | I20: 163 | J20: M1-R1 | K20: January | L20: ANNUAL | M20: Y | N20: Y | O20: Y
A21: 1007 Esquimalt Road | B21: Starlight Properties | C21: Increase to $65 after January 2026 | D21: 100595 | E21: 65 | F21: Esquimalt, BC | H21: ACTIVE | I21: LT 7001 | J21: W1-R7 | K21: May | L21: Y | M21: Y | N21: Y | O21: Y
A22: 101 Ontario Street | B22: Proline Property Management | D22: 100210 | E22: 55 | F22: Victoria, BC | G22: 45712 | H22: ACTIVE | I22: TO 101 | J22: W3-R20 | K22: November | L22: Y | M22: Y | N22: X | O22: X
A23: 1010 Mckenzie Avenue | B23: Starlight/Devon | C23: Increase to $65 after January 2026 | D23: 100836 | E23: 65 | F23: Saanich, BC | G23: 45559 | H23: ACTIVE | I23: M 101 | J23: W1-R6 | K23: February | L23: Y | M23: ANNUAL | N23: Y | O23: Y
A24: 1012 Collinson Street | B24: Hutton | D24: 100792 | E24: 55 | F24: Victoria, BC | H24: ACTIVE | I24: M 2101 K3 | J24: TH1-R9 | K24: October | L24: Y | M24: Y | N24: Y | O24: Y
A25: 1013 Vancouver Street | B25: Devon Properties | D25: 100959 | E25: 50 | F25: Victoria, BC | G25: 44949 | H25: ACTIVE | I25: 183 | J25: TH1-R8 | K25: May | L25: Y | M25: Y | N25: Y | O25: Y | P25: ANNUAL
A26: 1015 Kings Road | B26: Darioush Diba | D26: 100272 | E26: 55 | F26: Victoria, BC | G26: 44075 | H26: ACTIVE | I26: KQ 5101 | J26: M1-R3 | K26: June | L26: Y | M26: Y | N26: Y | O26: Y
A27: 10159 Third Street | B27: Realstar Management | D27: 100807 | E27: 55 | F27: Sidney, BC | H27: ACTIVE | I27: 93 | J27: F2-R16 | K27: October | L27: Y | M27: Y | N27: Y | O27: Y
A28: 1017 Queens Avenue | B28: Starlight/Devon | C28: Increase to $65 after January 2026 | D28: 100242 | E28: 65 | F28: Victoria, BC | G28: 44949 | H28: ACTIVE | I28: 111 | J28: M1-R3 | K28: March | L28: Y | M28: Y | N28: ANNUAL | O28: Y
A29: 1019 McClure Street | B29: Strata Plan VIS 308 | D29: 100450 | E29: 65 | F29: Victoria, BC | G29: 45253 | H29: ACTIVE | I29: CL 9101 | J29: TH1-R9 | K29: April | L29: Y | M29: Y | N29: Y | O29: ANNUAL
A30: 1019 Rockland Avenue | B30: Proline | D30: 100558 | E30: 55 | F30: Victoria, BC | G30: 42186 | H30: ACTIVE | I30: ST 9101 K2 | J30: M1-R2 | K30: April | L30: Y | M30: Y | N30: Y | O30: ANNUAL
A31: 1020 Park Boulevard | B31: Pemberton Holmes | D31: 100728 | E31: 50 | F31: Victoria, BC | G31: 44949 | H31: ACTIVE | I31: 92 | J31: TU3-R18 | K31: October | L31: Y | M31: Y | N31: Y | O31: Y
A32: 1020 Pembroke Street | B32: Brown Bros. | D32: 100397 | E32: 55 | F32: Victoria, BC | G32: 42476 | H32: ACTIVE | I32: RT 0201 K2 | J32: M1-R3 | K32: July | L32: Y | M32: Y | N32: Y | O32: Y
A33: 1024 Fairfield Road | B33: Firm Management | D33: 100782 | E33: 55 | F33: Victoria, BC | G33: 41791 | H33: ACTIVE | I33: WT 4201 K3 | J33: TH1-R9 | K33: December | L33: Y | M33: Y | N33: Y | O33: Y
A34: 1025 Johnson Street | B34: Devon Properties | D34: 100923 | E34: 60 | F34: Victoria, BC | G34: 45017 | H34: ACTIVE | I34: JD 5201 K5-F2 | J34: TH1-R8 | K34: January | L34: ANNUAL | M34: Y | N34: Y | O34: Y
A35: 1026 Johnson Street | B35: Firm Management | C35: Cancelled February 2026 - Previously R8 | D35: - | E35: 55 | F35: Victoria, BC | G35: 41821 | H35: CANCELLED | I35: WS 6201 K4-F1 | J35: - | K35: July | L35: Y | M35: - | N35: - | O35: - | P35: - | Q35: - | R35: - | S35: - | T35: - | U35: - | V35: - | W35: -
A36: 1030 Pendergast Street | B36: Starlight/Devon | D36: 100580 | E36: 70 | F36: Victoria, BC | G36: 45192 | H36: ACTIVE | I36: GT 0301 | J36: TU3-R18 | K36: July | L36: Y | M36: Y | N36: Y | O36: Y
A37: 1031 Burdett Avenue | B37: Hutton | C37: cancelled service- Nov 8/24 (tw) | D37: - | E37: 55 | F37: Victoria, BC | G37: 42256 | H37: CANCELLED | I37: BA 1301 K2 | J37: - | K37: December | L37: - | M37: - | N37: - | O37: - | P37: - | Q37: - | R37: - | S37: - | T37: - | U37: - | V37: - | W37: -
A38: 1032 North Park | B38: Pacific Quorum $55 | D38: 100547 | E38: 55 | F38: Victoria, BC | G38: 45039 | H38: ACTIVE | I38: 435 | J38: M1-R3 | K38: March | L38: Y | M38: Y | N38: Y | O38: ANNUAL
A39: 1035 Belmont Avenue | B39: Belmont Properties | D39: 100083 | E39: 55 | F39: Victoria, BC | G39: 45017 | H39: ACTIVE | I39: 445 | J39: TH1-R9 | K39: August | L39: Y | M39: Y | N39: Y | O39: Y
A40: 1035 North Park / 1720 Cook Street | B40: First Service Residential | D40: 100909 | E40: 75 | F40: Victoria, BC | G40: 46016 | H40: ACTIVE | I40: TH 5301 | J40: M1-R3 | K40: April* | L40: Y | M40: Y | N40: Y | O40: ANNUAL
A41: 1035 Pendergast Street | B41: Starlight/Devon | D41: 100580 | E41: 70 | F41: Victoria, BC | G41: 45192 | H41: ACTIVE | I41: GT 0301 | J41: TU3-R18 | K41: July | L41: Y | M41: Y | N41: Y | O41: Y
A42: 1036 Stellys Cross Road | B42: Aleutian Property Management Ltd | C42: 2026 1st quarter, sent. Mgt change | D42: 100565 | E42: 50 | F42: Brentwood Bay, BC | H42: ACTIVE | I42: 424 | J42: TU2-R12 | K42: December | L42: Y | M42: Y | N42: Y | O42: Y
A43: 104 Dallas Road | B43: Strata #1374 The Dolphins | D43: 100373 | E43: 55 | F43: Victoria, BC | G43: 43891 | H43: ACTIVE | I43: SP 401 K1-F1 | J43: W3-R20 | K43: August | L43: Y | M43: Y | N43: X | O43: Y
A44: 1040 Stellys Cross Road | B44: Aleutian Property Management Ltd | C44: 2026 1st quarter, sent. Mgt change | D44: 100565 | E44: 50 | F44: Brentwood Bay, BC | H44: ACTIVE | I44: 424 | J44: TU2-R12 | K44: December | L44: Y | M44: Y | N44: Y | O44: Y
A45: 1041 Fairfield Road | B45: Pemberton Holmes | D45: 100206 | E45: 50 | F45: Victoria, BC | H45: ACTIVE | I45: 68 | J45: M1-R2 | K45: April | L45: Y | M45: Y | N45: Y | O45: ANNUAL
A46: 1041 Richardson Road | B46: Capital West | D46: 100149 | E46: 60 | F46: Victoria, BC | G46: 45078 | H46: ACTIVE | I46: RR 1401 | J46: TH1-R9 | K46: June | L46: Y | M46: Y | N46: Y | O46: Y
A47: 1045 McClure Street | B47: Brown Bros. | C47: Last test done March 2026 | D47: 100543 | E47: 50 | F47: Victoria, BC | H47: CANCELLED | I47: 332 | J47: - | K47: November - TO | L47: Y | M47: Y | N47: Y | O47: - | P47: - | Q47: - | R47: - | S47: - | T47: - | U47: - | V47: - | W47: -
A48: 10459 Resthaven Drive | B48: Proline | D48: 100335 | E48: 50 | F48: Sidney, BC | G48: 44949 | H48: ACTIVE | I48: 392 | J48: F2-R16 | K48: May | L48: Y | M48: Y | N48: Y | O48: Y
A49: 10461 Resthaven Drive | B49: Proline | D49: 100335 | E49: 50 | F49: Sidney, BC | G49: 44949 | H49: ACTIVE | I49: 392 | J49: F2-R16 | K49: May | L49: Y | M49: Y | N49: Y | O49: Y
A50: 1049 Southgate Street | B50: Devon Properties | D50: 100822 | E50: 50 | F50: Victoria, BC | G50: 44949 | H50: ACTIVE | I50: 186 | J50: TU3-R18 | K50: September | L50: Y | M50: Y | N50: Y | O50: Y
A51: 105 Wilson Street | B51: Pacifica Housing | D51: 100379 | E51: 65 | F51: Esquimalt, BC | G51: 45505 | H51: ACTIVE | I51: W 501 | J51: W1-R7 | K51: July | L51: Y | M51: Y | N51: X | O51: Y
A52: 1050 Park Boulevard | B52: Hutton | C52: $60/month (incl. hose, ext, mag lock check) | D52: 100168 | E52: 60 | F52: Victoria, BC | G52: 44559 | H52: ACTIVE | I52: P 0501 K2 | J52: M2-R11 | K52: March | L52: Y | M52: Y | N52: ANNUAL | O52: Y
A53: 10520 McDonald Park | B53: Complete Residential Property Management | D53: 100337 | E53: 75 | F53: Sidney, BC | G53: 45772 | H53: ACTIVE | I53: DN 02501 | J53: F2-R16 | K53: October | L53: Y | M53: Y | N53: Y | O53: Y
A54: 1055 Hillside Avenue | B54: Firm Management | D54: 100864 | E54: 55 | F54: Victoria, BC | G54: 42689 | H54: ACTIVE | I54: LM 5501 | J54: W1-R6 | K54: January | L54: ANNUAL | M54: Y | N54: Y | O54: Y
A55: 1057 Moss Street | B55: Tim Slater | C55: Charge CC in ST and email receipt | D55: 100122 | E55: 60 | F55: Victoria, BC | G55: 45346 | H55: ACTIVE | I55: SM 7501 | J55: TH1-R9 | K55: September | L55: Y | M55: Y | N55: Y | O55: Y
A56: 1060 Craigdarroch Road | B56: Pemberton Holmes | C56: Increase to $65 after January 2026 | D56: 100247 | E56: 65 | F56: Esquimalt, BC | H56: ACTIVE | I56: 373 | J56: TH1-R9 | K56: March | L56: Y | M56: Y | N56: Y | O56: Y
A57: 1060 Goldstream Avenue | B57: Centurion Properties | C57: Months on invoice | D57: 100522 | E57: 55 | F57: Langford, BC | G57: 44949 | H57: ACTIVE | I57: 412 | J57: TU1-R5 | K57: September | L57: Y | M57: Y | N57: Y | O57: Y
A58: 1060 Southgate Street | B58: Southgate Manor | D58: 100974 | E58: 50 | F58: Victoria, BC | G58: 44949 | H58: ACTIVE | I58: 42 | J58: TU3-R18 | K58: September | L58: Y | M58: Y | N58: Y | O58: Y
A59: 1066 Foul Bay Road | B59: Newport Property | D59: 100843 | E59: 50 | F59: Victoria, BC | G59: 44949 | H59: ACTIVE | I59: 124 | J59: TU2-R13 | K59: July | L59: Y | M59: Y | N59: X | O59: Y | P59: ANNUAL
A60: 1069 Southgate Street | B60: Newport Property Management | D60: 100138 | E60: 50 | F60: Victoria, BC | H60: ACTIVE | I60: 307 | J60: M1-R2 | K60: March | L60: Y | M60: Y | N60: Y | O60: Y | P60: ANNUAL
A61: 1080 Cypress Road | B61: Storyoga Inc. | D61: 100497 | E61: 75 | F61: North Saanich, BC | G61: 46016 | H61: ACTIVE | I61: CP 801 | J61: F1-R10 | K61: October | L61: Y | M61: Y | N61: Y | O61: Y
A62: 1088 Johnson Street | B62: Centurion Property Associates Inc. | D62: 100979 | E62: 125 | F62: Victoria, BC | G62: 45833 | H62: ACTIVE | I62: HJ 8801 | J62: TH1-R8 | K62: May | L62: Y | M62: Y | N62: Y | O62: Y | P62: ANNUAL
A63: 109 Wilson Street | B63: Pacifica Housing | D63: 100795 | E63: 65 | F63: Esquimalt, BC | G63: 45505 | H63: ACTIVE | I63: A 901 | J63: W1-R7 | K63: July | L63: Y | M63: Y | N63: Y | O63: Y
A64: 1090 Johnson Street | B64: Firm Management | D64: 100365 | E64: 60 | F64: Victoria, BC | G64: 45017 | H64: ACTIVE | I64: TM 0901 | J64: TH1-R8 | K64: March | L64: Y | M64: Y | N64: Y | O64: Y | P64: ANNUAL
A65: 1097 View Street | B65: Firm Management | D65: 100077 | E65: 125 | F65: Victoria, BC | G65: 45346 | H65: ACTIVE | I65: VS 7901 | J65: TH1-R9 | K65: May | L65: Y | M65: Y | N65: Y | O65: Y
A66: 110 Douglas Street | B66: Devon Properties | D66: 100483 | E66: 50 | F66: Victoria, BC | H66: ACTIVE | I66: 344 | J66: TU3-R18 | K66: August | L66: Y | M66: Y | N66: Y | O66: Y
A67: 1106 Balmoral Road | B67: Peter Hejjas | C67: $52.50 credit - apply to Q2 | D67: 100458 | E67: 50 | F67: Victoria, BC | G67: 44949 | H67: ACTIVE | I67: 127 | J67: M1-R3 | K67: March | L67: Y | M67: Y | N67: ANNUAL | O67: Y
A68: 1110 Samar Crescent | B68: Breakwater Realty Inc. | C68: Building A | D68: 100627 | E68: 75 | F68: Langford, BC | G68: 45833 | H68: ACTIVE | I68: MS 0111 | J68: TU1-R5 | K68: November | L68: Y | M68: Y | N68: Y | O68: Y
A69: 1111 Hillside Avenue | B69: Century 21 | D69: 100921 | E69: 55 | F69: Victoria, BC | H69: ACTIVE | I69: OP 1111 | J69: M1-R1 | K69: July | L69: Y | M69: Y | N69: Y | O69: Y
A70: 1114 Samar Crescent | B70: Breakwater Realty Inc. | C70: Building B | D70: 100627 | E70: 75 | F70: Langford, BC | G70: 45833 | H70: ACTIVE | I70: MS 0111 | J70: TU1-R5 | K70: November | L70: Y | M70: Y | N70: Y | O70: Y
A71: 1115 Craigflower Road | B71: Proline | C71: $65/month (A) | D71: 100437 | E71: 65 | F71: Esquimalt, BC | G71: 44378 | H71: ACTIVE | I71: IW 5111 K6-G1 | J71: W2-R22 | K71: August | L71: Y | M71: Y | N71: Y | O71: Y
A72: 1118 Balmoral Road | B72: Devon Properties Ltd. | D72: 100042 | E72: 65 | F72: Victoria, BC | G72: 46138 | H72: ACTIVE | I72: BM 8111 | J72: M1-R3 | K72: March | L72: - | M72: - | N72: - | O72: Y
A73: 1120 Blanshard Street | B73: Equitex | D73: - | E73: 50 | F73: Victoria, BC | G73: 44949 | H73: ACTIVE | I73: No keys | J73: TH2-R15 | K73: February | L73: Y | M73: Y | N73: Y | O73: ANNUAL
A74: 1120 Burdett Ave | B74: Devon Properties | D74: 100153 | E74: 55 | F74: Victoria, BC | G74: 45589 | H74: ACTIVE | I74: B0211 | J74: TH1-R9 | K74: October | L74: Y | M74: Y | N74: Y | O74: Y
A75: 1120 Richardson Street | B75: Gibraltar | D75: 100477 | E75: 50 | F75: Victoria, BC | G75: 44949 | H75: ACTIVE | I75: 4 | J75: TH1-R9 | K75: September | L75: Y | M75: Y | N75: Y | O75: Y
A76: 1120 Yates Street | B76: Colliers | D76: 100550 | E76: 50 | F76: Victoria, BC | G76: 44949 | H76: ACTIVE | I76: 321 | J76: TH1-R8 | K76: November | L76: Y | M76: Y | N76: Y | O76: Y
A77: 1122 Hilda Street | B77: Pemberton Strata | D77: 100013 | E77: 50 | F77: Victoria, BC | H77: ACTIVE | I77: 427 | J77: TU2-R13 | K77: November | L77: Y | M77: Y | N77: X | O77: Y
A78: 1122 McKenzie Street | B78: Pemberton Holmes | D78: 100226 | E78: 50 | F78: Victoria, BC | H78: ACTIVE | I78: 100 | J78: M1-R2 | K78: March | L78: Y | M78: Y | N78: ANNUAL | O78: Y
A79: 1125 Douglas Street | B79: Arpeg Holdings Cactus Club | C79: single panel share with 702 Fort Street - On hold January 2026 | D79: - | E79: 65 | F79: Victoria, BC | G79: 41153 | H79: ACTIVE | I79: MEET KEN COOPER | J79: TH2-R15 | K79: April | L79: Y | M79: X | N79: Y | O79: Y
A80: 1125 Hillside Avenue | B80: Devon Properties | D80: - | E80: 55 | F80: Victoria, BC | G80: 45539 | H80: CANCELLED | I80: H 5211 | J80: - | K80: August | L80: - | M80: - | N80: - | O80: - | P80: - | Q80: - | R80: - | S80: - | T80: - | U80: - | V80: - | W80: -
A81: 1126 Rockland Avenue | B81: Starlight/Devon | D81: 100410 | E81: 70 | F81: Victoria, BC | G81: 45170 | H81: ACTIVE | I81: LD 6211 | J81: TH1-R9 | K81: June | L81: Y | M81: Y | N81: Y | O81: Y
A82: 1127 Wharf Street | B82: Darcy's Pub | D82: - | E82: 55 | F82: Victoria, BC | G82: 41791 | H82: ACTIVE | I82: KEY AT SITE | J82: TH2-R15 | K82: April | L82: Y | M82: Y | N82: Y | O82: ANNUAL
A83: 1130 Fort Street | B83: Pacifica Housing | D83: 100080 | E83: 65 | F83: Victoria, BC | G83: 45527 | H83: ACTIVE | I83: F 0311 | J83: TH1-R9 | K83: July | L83: Y | M83: Y | N83: Y | O83: X
A84: 1130 Pandora Avenue | B84: Devon Properties Ltd. | D84: 100752 | E84: 65 | F84: Victoria, BC | G84: 46168 | H84: ACTIVE | I84: PD 311 | J84: TH1-R8 | K84: March | L84: - | M84: - | N84: - | O84: -
A85: 1132 McClure Street | B85: Devon Properties | D85: 100791 | E85: 50 | F85: Victoria, BC | G85: 44949 | H85: ACTIVE | I85: 162 | J85: TH1-R9 | K85: August | L85: Y | M85: Y | N85: Y | O85: Y
A86: 1133A Reynolds Road | B86: Abbeyfield St. Peters | D86: 100304 | E86: 55 | F86: Saanich, BC | H86: ACTIVE | I86: PQ 3311 | J86: TU1-R4 | K86: February | L86: Y | M86: Y | N86: Y | O86: Y
A87: 1137-1139 Yates Street | B87: Equitex Property Management | D87: 100964 | E87: 75 | F87: Victoria, BC | G87: 45863 | H87: ACTIVE | I87: TY 7311 | J87: M1-R1 | K87: October | L87: Y | M87: Y | N87: Y | O87: Y
A88: 1145 Bay Street | B88: Ashton Oaks c/o Gateway Prop | D88: 100095 | E88: 50 | F88: Victoria, BC | G88: 44949 | H88: ACTIVE | I88: 322 | J88: M1-R3 | K88: September | L88: Y | M88: Y | N88: Y | O88: Y
A89: 1150 Hilda Street | B89: Devon Properties | D89: 100134 | E89: 60 | F89: Victoria, BC | G89: 45448 | H89: ACTIVE | I89: AH 0511 | J89: M1-R2 | K89: August | L89: Y | M89: Y | N89: Y | O89: Y
A90: 1150 Queens Avenue | B90: Pacific Quorum | D90: 100452 | E90: 65 | F90: Victoria, BC | H90: ACTIVE | I90: 406 | J90: M1-R1 | K90: January | L90: ANNUAL | M90: Y | N90: Y | O90: Y
A91: 1150 Rockland Avenue | B91: Pemberton Holmes | D91: 100259 | E91: 50 | F91: Victoria, BC | H91: ACTIVE | I91: 346 | J91: M1-R2 | K91: September | L91: Y | M91: Y | N91: Y | O91: Y
A92: 1160 Esquimalt Road | B92: Starlight/Devon | D92: 100443 | E92: 65 | F92: Victoria, BC | G92: 45620 | H92: ACTIVE | I92: EQ 611 | J92: W1-R7 | K92: January | L92: ANNUAL | M92: Y | N92: Y | O92: Y
A93: 1160 Richardson Street | B93: Lee & Sharpe | C93: $52.50 credit - apply to Q2 | D93: 100364 | E93: 50 | F93: Victoria, BC | H93: ACTIVE | I93: 164 | J93: M1-R2 | K93: March | L93: Y | M93: Y | N93: ANNUAL | O93: Y
A94: 1165 Meares Street | B94: Pemberton Holmes (new June 13/24) | D94: 100094 | E94: 55 | F94: Victoria, BC | G94: 42005 | H94: ACTIVE | I94: MA 5611 K2 | J94: M1-R2 | K94: July | L94: Y | M94: Y | N94: Y | O94: Y
A95: 1165 Yates Street | B95: Devon properties | D95: 100463 | E95: 50 | F95: Victoria, BC | H95: ACTIVE | I95: 340 | J95: M1-R1 | K95: February | L95: Y | M95: ANNUAL | N95: Y | O95: Y
A96: 1166 Rockland Avenue | B96: Freelance | D96: 100160 | E96: 55 | F96: Victoria, BC | H96: ACTIVE | I96: K 6611 K3 | J96: TH1-R9 | K96: September | L96: Y | M96: Y | N96: Y | O96: Y
A97: 1177 Esquimalt Road | B97: Devon Properties | D97: 100290 | E97: 50 | F97: Esquimalt, BC | G97: 44949 | H97: ACTIVE | I97: 368 | J97: W1-R7 | K97: April | L97: Y | M97: Y | N97: Y | O97: Y | P97: ANNUAL
A98: 1178 Beach Drive | B98: Devon Properties | D98: 100656 | E98: 50 | F98: Oak Bay, BC | G98: 44949 | H98: ACTIVE | I98: 108 | J98: TU2-R13 | K98: July | L98: Y | M98: Y | N98: X | O98: Y
A99: 118 Croft Street | B99: Brown Bros. | D99: 100395 | E99: 50 | F99: Victoria, BC | H99: ACTIVE | I99: 366 | J99: W3-R20 | K99: May | L99: Y | M99: Y | N99: X | O99: Y | P99: ANNUAL
A100: 1180 Colville Road | B100: Starlight Properties c/o Devon Properties | D100: 100479 | E100: 65 | F100: Esquimalt, BC | G100: 45253 | H100: ACTIVE | I100: CR 0811 | J100: W2-R22 | K100: September | L100: Y | M100: Y | N100: Y | O100: Y
...

Sheet Jan 2024-Dec 2024
A1: ADDRESS | B1: PROPERTY MANAGEMENT COMPANY | C1: NOTES | D1: Price/month | E1: Area | F1: start up date | G1: STATUS- (ACTIVE, CANCELLED, ON HOLD) | H1: KEYS | I1: TEST DAY | J1: ANNUAL | K1: 45292 | L1: 45323 | M1: 45352 | N1: 45383 | O1: 45413 | P1: 45444 | Q1: 45474 | R1: 45505 | S1: 45536 | T1: 45566 | U1: 45597 | V1: 45627
A2: #103-4475 Viewmont | B2: Hansbraun | C2: $75/month MONTHLY EXT & ELU TESTS | D2: 75 | E2: Saanich, BC | F2: 45559 | G2: ACTIVE | H2: NONE | I2: TU1-R4 | J2: May | K2: X | L2: X | M2: X | N2: X | O2: X | P2: X | Q2: X | R2: X | S2: Y | T2: Y | U2: Y | V2: Y
A3: 10 Paul Kane/11 Cooperage Place | B3: Proline | D3: 55 | E3: Esquimalt, BC | F3: 41730 | G3: ACTIVE | H3: UV 01 | I3: W1-R7 | J3: May | K3: Y | L3: Y | M3: Y | N3: Y | O3: ANNUAL | P3: Y | Q3: Y | R3: Y | S3: Y | T3: Y | U3: Y | V3: Y
A4: 1000 Mckenzie Avenue | B4: Devon Properties | D4: 55 | E4: Saanich, BC | F4: 45559 | G4: ACTIVE | H4: M 0001 | I4: W1-R6 | J4: May | K4: X | L4: X | M4: X | N4: X | O4: X | P4: X | Q4: X | R4: X | S4: Y | T4: X | U4: Y | V4: Y
A5: 1000-1012 Douglas Street | B5: Itziar Management Ltd. (0824606 BC Ltd.) | D5: 60 | E5: Victoria, BC | F5: 45589 | G5: ACTIVE | H5: D 2101 | I5: TH2-R15 | J5: June | K5: X | L5: X | M5: X | N5: X | O5: X | P5: X | Q5: X | R5: X | S5: X | T5: X | U5: X | V5: Y
A6: 1001 Wharf Street | B6: Pastoral Developments Ltd. | D6: 55 | E6: Victoria, BC | F6: 43313 | G6: ACTIVE | H6: NA 1001 K2-F1 | I6: TH2-R15 | J6: Oct | K6: Y | L6: Y | M6: Y | N6: Y | O6: Y | P6: Y | Q6: Y | R6: Y | S6: Y | T6: ANNUAL | U6: Y | V6: Y
A7: 10016 3rd Street | B7: Cornerstone | D7: 50 | E7: Sidney, BC | F7: 44949 | G7: ACTIVE | H7: 358 | I7: F2-R16 | J7: Feb | K7: Y | L7: Y | M7: ANNUAL | N7: Y | O7: Y | P7: Y | Q7: Y | R7: Y | S7: Y | T7: Y | U7: Y | V7: Y
A8: 1002 Mckenzie Avenue | B8: Devon Properties | D8: 55 | E8: Saanich, BC | F8: 45559 | G8: ACTIVE | H8: M 0001 | I8: W1-R6 | J8: May | K8: X | L8: X | M8: X | N8: X | O8: X | P8: X | Q8: X | R8: X | S8: Y | T8: X | U8: Y | V8: Y
A9: 1002 Pakington | B9: Devon Properties | D9: 50 | E9: Victoria, BC | F9: 44949 | G9: ACTIVE | H9: 146 | I9: TU3-R18 | J9: Sept* | K9: Y | L9: Y | M9: Y | N9: Y | O9: Y | P9: Y | Q9: Y | R9: Y | S9: ANNUAL | T9: Y | U9: Y | V9: Y
A10: 1002 Wharf Street | B10: Malahat Properties | D10: 55 | E10: Victoria, BC | F10: 44174 | G10: ACTIVE | H10: At Reception | I10: TH2-R15 | J10: Nov | K10: Y | L10: Y | M10: Y | N10: Y | O10: Y | P10: Y | Q10: Y | R10: Y | S10: Y | T10: Y | U10: Y | V10: Y
A11: 10025 Resthaven Drive | B11: Inken Roller c/o Richmond Property Group | D11: 50 | E11: Sidney, BC | F11: 44949 | G11: ACTIVE | H11: 349 | I11: F2-R16 | J11: Feb | K11: Y | L11: Y | M11: Y | N11: Y | O11: Y | P11: X | Q11: Y | R11: Y | S11: Y | T11: Y | U11: Y | V11: Y
A12: 10030 Resthaven Drive | B12: Raven Property Management Ltd. | C12: $75/month (MISC1) | D12: 75 | E12: Sidney, BC | F12: 44228 | G12: ACTIVE | H12: SC 03001 | I12: F2-R16 | J12: May | K12: Y | L12: Y | M12: Y | N12: Y | O12: ANNUAL | P12: X | Q12: Y | R12: Y | S12: Y | T12: Y | U12: Y | V12: Y
A13: 1004 Pemberton Road | B13: Raul Caballero | D13: 70 | E13: Victoria, BC | F13: 45161 | G13: ACTIVE | H13: PB 4001 | I13: M1-R1 | J13: Nov | K13: Y | L13: Y | M13: Y | N13: Y | O13: X | P13: Y | Q13: Y | R13: Y | S13: Y | T13: Y | U13: X | V13: Y
A14: 1005 & 1009 McKenzie Avenue | B14: Firm Management | C14: $60/mth - mthly bell test (B) | D14: 60 | E14: Saanich, BC | G14: ACTIVE | H14: MN 5001 | I14: TU1-R4 | J14: May* | K14: Y | L14: Y | M14: Y | N14: Y | O14: Annual | P14: Y | Q14: Y | R14: Y | S14: Y | T14: Y | U14: Y | V14: Y
A15: 1005 Broad Street | B15: Richmond Property Group | D15: 55 | E15: Victoria, BC | G15: ACTIVE | H15: K 5001 K4 | I15: TH2-R15 | J15: March | K15: Y | L15: Y | M15: ANNUAL | N15: Y | O15: Y | P15: Y | Q15: Y | R15: Y | S15: Y | T15: Y | U15: Y | V15: Y
A16: 1005 Pakington Street | B16: Century 21 Queenswood | D16: 50 | E16: Victoria, BC | F16: 44949 | G16: ACTIVE | H16: 171 | I16: TU3-R18 | J16: August | K16: Y | L16: Y | M16: Y | N16: Y | O16: Y | P16: Y | Q16: Y | R16: Y | S16: X | T16: ANNUAL | U16: Y | V16: Y
A17: 1006 Fort Street | B17: Colliers | C17: $75/month if special service call. PO Required | D17: 75 | E17: Victoria, BC | F17: 41214 | G17: ACTIVE | H17: ZZ 6001 K3-F1 | I17: M1-R2 | J17: September | K17: X | L17: X | M17: X | N17: X | O17: Y | P17: Y | Q17: Y | R17: Y | S17: ANNUAL | T17: Y | U17: Y | V17: Y
A18: 1006 Tolmie Avenue | B18: Century 21 Queenswood | D18: 60 | E18: Victoria, BC | G18: ACTIVE | H18: 163 | I18: M1-R1 | J18: Feb | K18: Y | L18: X & Annual | M18: Y | N18: Y | O18: Y | P18: Y | Q18: Y | R18: Y | S18: Y | T18: Y | U18: X | V18: Y
A19: 1007 Esquimalt Road | B19: Sorenson & Bowers | D19: 50 | E19: Esquimalt, BC | G19: ACTIVE | H19: LT 7001 | I19: W1-R7 | J19: May* | K19: Y | L19: Y | M19: Y | N19: Y | O19: Annual | P19: Y | Q19: Y | R19: Y | S19: Y | T19: Y | U19: Y | V19: Y
A20: 1010 Mckenzie Avenue | B20: Devon Properties | D20: 55 | E20: Saanich, BC | F20: 45559 | G20: ACTIVE | H20: M 0001 | I20: W1-R6 | J20: Febuary | K20: X | L20: X | M20: X | N20: X | O20: X | P20: X | Q20: X | R20: X | S20: Y | T20: X | U20: Y | V20: Y
A21: 1012 Collinson Street | B21: Hutton | D21: 55 | E21: Victoria, BC | G21: ACTIVE | H21: M 2101 K3 | I21: TH1-R9 | J21: Oct | K21: Y | L21: Y | M21: Y | N21: Y | O21: Y | P21: Y | Q21: Y | R21: Y | S21: Y | T21: ANNUAL | U21: Y | V21: Y
A22: 1013 Vancouver Street | B22: Devon Properties | D22: 50 | E22: Victoria, BC | F22: 44949 | G22: ACTIVE | H22: 183 | I22: TH1-R8 | J22: May* | K22: Y | L22: Y | M22: Y | N22: Y | O22: Annual | P22: Y | Q22: Y | R22: Y | S22: Y | T22: Y | U22: Y | V22: Y
A23: 1015 Kings Road | B23: Darioush Diba | D23: 55 | E23: Victoria, BC | F23: 44075 | G23: ACTIVE | H23: KQ 5101 | I23: M1-R3 | J23: June | K23: Y | L23: Y | M23: Y | N23: Y | O23: Y | P23: ANNUAL | Q23: Y | R23: Y | S23: Y | T23: Y | U23: X | V23: Y
A24: 10159 Third Street | B24: Realstar Management | D24: 55 | E24: Sidney, BC | G24: ACTIVE | H24: 93 | I24: F2-R16 | J24: Nov | K24: Y | L24: Y | M24: Y | N24: Y | O24: Y | P24: X | Q24: Y | R24: Y | S24: Y | T24: ANNUAL | U24: Y | V24: Y
A25: 1017 Queens Avenue | B25: Starlight/Devon | C25: Changed to R20 Jan/24 | D25: 50 | E25: Victoria, BC | F25: 44949 | G25: ACTIVE | H25: 111 | I25: M1-R3 | J25: Feb | K25: Y | L25: Y | M25: Y | N25: Y | O25: Y | P25: X | Q25: Y | R25: Y | S25: Y | T25: Y | U25: Y | V25: Y
A26: 1019 McClure Street | B26: Strata Plan VIS 308 | D26: 65 | E26: Victoria, BC | F26: 45253 | G26: ACTIVE | H26: CL 9101 | I26: TH1-R9 | J26: April | K26: Y | L26: Y | M26: Y | N26: ANNUAL | O26: Y | P26: Y | Q26: Y | R26: Y | S26: Y | T26: Y | U26: Y | V26: Y
A27: 1019 Rockland Avenue | B27: Proline | D27: 55 | E27: Victoria, BC | F27: 42186 | G27: ACTIVE | H27: JT 9101 K2 | I27: M1-R2 | J27: Dec | K27: Y | L27: Y | M27: Y | N27: Y | O27: Y | P27: Y | Q27: Y | R27: Y | S27: Y | T27: Y | U27: Y | V27: Y
A28: 1020 Park Boulevard | B28: Pemberton Holmes | D28: 50 | E28: Victoria, BC | F28: 44949 | G28: ACTIVE | H28: 92 | I28: TU3-R18 | J28: Nov | K28: Y | L28: Y | M28: Y | N28: Y | O28: Y | P28: Y | Q28: Y | R28: Y | S28: Y | T28: Y | U28: ANNUAL | V28: Y
A29: 1020 Pembroke Street | B29: Brown Bros. | D29: 55 | E29: Victoria, BC | F29: 42476 | G29: ACTIVE | H29: RT 0201 K2 | I29: M1-R3 | J29: July* | K29: Y | L29: Y | M29: Y | N29: Y | O29: Y | P29: Y | Q29: Y | R29: Y | S29: Y | T29: Y | U29: Y | V29: Y
A30: 1024 Fairfield Road | B30: Firm Management | D30: 55 | E30: Victoria, BC | F30: 41791 | G30: ACTIVE | H30: WT 4201 K3 | I30: TH1-R9 | J30: Dec | K30: Y | L30: Y | M30: Y | N30: Y | O30: Y | P30: Y | Q30: Y | R30: Y | S30: Y | T30: Y | U30: ANNUAL | V30: Y
A31: 1025 Johnson Street | B31: Devon Properties | D31: 60 | E31: Victoria, BC | F31: 45017 | G31: ACTIVE | H31: JD 5201 K5-F2 | I31: TH1-R8 | J31: Dec | K31: Y | L31: Y | M31: Y | N31: Y | O31: Y | P31: Y | Q31: Y | R31: Y | S31: Y | T31: Y | U31: Y | V31: Y
A32: 1026 Johnson Street | B32: Firm Management | D32: 55 | E32: Victoria, BC | F32: 41821 | G32: ACTIVE | H32: WS 6201 K4-F1 | I32: TH1-R8 | J32: July | K32: Y | L32: Y | M32: Y | N32: Y | O32: Y | P32: Y | Q32: Y | R32: Y | S32: Y | T32: Y | U32: Y | V32: Y
A33: 1030 Pendergast Street | B33: Starlight/Devon | D33: 70 | E33: Victoria, BC | F33: 45192 | G33: ACTIVE | H33: GT 0301 | I33: TU3-R18 | J33: July* | K33: Y | L33: Y | M33: Y | N33: Y | O33: X | P33: Y | Q33: ANNUAL | R33: Y | S33: Y | T33: Y | U33: Y | V33: Y
A34: 1031 Burdett Avenue | B34: Hutton | C34: cancelled service- Nov 8/24 (tw) | D34: 55 | E34: Victoria, BC | F34: 42256 | G34: CANCELLED | H34: BA 1301 K2 | I34: - | J34: Dec | K34: Y | L34: Y | M34: Y | N34: Y | O34: Y | P34: Y | Q34: Y | R34: Y | S34: Y | T34: Y | U34: Y | V34: X
A35: 1032 North Park | B35: Pacific Quorum $55 | D35: 55 | E35: Victoria, BC | F35: 45039 | G35: ACTIVE | H35: 435 | I35: M1-R3 | J35: March | K35: Y | L35: Y | M35: Y | N35: ANNUAL | O35: Y | P35: Y | Q35: Y | R35: Y | S35: Y | T35: Y | U35: Y | V35: Y
A36: 1035 Belmont Avenue | B36: Belmont Properties | C36: $47.50/m for 2023 $50/m for 2024 | D36: 50 | E36: Victoria, BC | F36: 45017 | G36: ACTIVE | H36: 445 | I36: TH1-R9 | J36: August* | K36: Y | L36: Y | M36: X | N36: Y | O36: X | P36: Y | Q36: Y | R36: ANNUAL | S36: Y | T36: Y | U36: Y | V36: Y
A37: 1035 Pendergast Street | B37: Starlight/Devon | D37: 70 | E37: Victoria, BC | F37: 45192 | G37: ACTIVE | H37: GT 0301 | I37: TU3-R18 | J37: July* | K37: Y | L37: Y | M37: Y | N37: Y | O37: Y | P37: Y | Q37: ANNUAL | R37: Y | S37: Y | T37: Y | U37: Y | V37: Y
A38: 1036 Stellys Cross Road | B38: Devon Properties | D38: 50 | E38: Brentwood Bay, BC | G38: ACTIVE | H38: 424 | I38: TU2-R12 | J38: Dec | K38: Y | L38: Y | M38: Y | N38: Y | O38: Y | P38: Y | Q38: Y | R38: Y | S38: X | T38: Y | U38: Y | V38: ANNUAL
A39: 104 Dallas Road | B39: Strata #1374 The Dolphins | D39: 55 | E39: Victoria, BC | F39: 43891 | G39: ACTIVE | H39: SP 401 K1-F1 | I39: W3-R20 | J39: August | K39: Y | L39: Y | M39: Y | N39: Y | O39: Y | P39: Y | Q39: Y | R39: ANNUAL | S39: Y | T39: X | U39: X | V39: Y
A40: 1040 Stellys Cross Road | B40: Devon Properties | D40: 50 | E40: Brentwood Bay, BC | G40: ACTIVE | H40: 424 | I40: TU2-R12 | J40: Dec | K40: Y | L40: Y | M40: Y | N40: Y | O40: Y | P40: Y | Q40: Y | R40: Y | S40: X | T40: Y | U40: Y | V40: ANNUAL
A41: 1041 Fairfield Road | B41: Pemberton Holmes | D41: 50 | E41: Victoria, BC | G41: ACTIVE | H41: 68 | I41: M1-R2 | J41: April* | K41: Y | L41: Y | M41: Y | N41: ANNUAL | O41: Y | P41: Y | Q41: Y | R41: Y | S41: Y | T41: Y | U41: Y | V41: Y
A42: 1041 Richardson Road | B42: Capital West | D42: 60 | E42: Victoria, BC | F42: 45078 | G42: ACTIVE | H42: RR 1401 | I42: TH1-R9 | J42: June | K42: Y | L42: Y | M42: Y | N42: Y | O42: ANNUAL | P42: Y | Q42: Y | R42: Y | S42: Y | T42: Y | U42: Y | V42: Y
A43: 1045 McClure Street | B43: Brown Bros. | D43: 50 | E43: Victoria, BC | G43: ACTIVE | H43: 332 | I43: M1-R2 | J43: Dec | K43: Y | L43: Y | M43: Y | N43: Y | O43: Y | P43: Y | Q43: Y | R43: Y | S43: Y | T43: Y | U43: Y | V43: Y
A44: 10459 Resthaven Drive | B44: Proline | D44: 50 | E44: Sidney, BC | F44: 44949 | G44: ACTIVE | H44: 392 | I44: F2-R16 | J44: May | K44: Y | L44: Y | M44: Y | N44: Y | O44: Y | P44: ANNUAL | Q44: Y | R44: Y | S44: Y | T44: Y | U44: Y | V44: Y
A45: 10461 Resthaven Drive | B45: Proline | D45: 50 | E45: Sidney, BC | F45: 44949 | G45: ACTIVE | H45: 392 | I45: F2-R16 | J45: May | K45: Y | L45: Y | M45: Y | N45: Y | O45: Y | P45: ANNUAL | Q45: Y | R45: Y | S45: Y | T45: Y | U45: Y | V45: Y
A46: 1049 Southgate Street | B46: Devon Properties | D46: 50 | E46: Victoria, BC | F46: 44949 | G46: ACTIVE | H46: 186 | I46: TU3-R18 | J46: Sept | K46: Y | L46: Y | M46: Y | N46: Y | O46: Y | P46: Y | Q46: Y | R46: Y | S46: Y | T46: Y | U46: ANNUAL | V46: Y
A47: 105 Wilson Street | B47: Pacifica Housing | D47: 65 | E47: Esquimalt, BC | F47: 45505 | G47: ACTIVE | H47: W 501 | I47: W1-R7 | J47: July | K47: X | L47: X | M47: X | N47: X | O47: X | P47: X | Q47: ANNUAL | R47: Y | S47: Y | T47: X | U47: Y | V47: Y
A48: 1050 Park Boulevard | B48: Hutton | C48: $60/month (incl. hose, ext, mag lock check) | D48: 60 | E48: Victoria, BC | F48: 44559 | G48: ACTIVE | H48: P 0501 K2 | I48: M2-R11 | J48: Feb | K48: Y | L48: ANNUAL | M48: Y | N48: Y | O48: Y | P48: Y | Q48: Y | R48: Y | S48: Y | T48: Y | U48: Y | V48: Y
A49: 1055 Hillside Avenue | B49: Firm Management | D49: 55 | E49: Victoria, BC | F49: 42689 | G49: ACTIVE | H49: LM 5501 | I49: W1-R6 | J49: Dec | K49: Y | L49: Y | M49: Y | N49: Y | O49: Y | P49: Y | Q49: Y | R49: Y | S49: Y | T49: X | U49: Y | V49: Y
A50: 1057 Moss Street | B50: Tim Slater | D50: 60 | E50: Victoria, BC | F50: 45346 | G50: ACTIVE | H50: SM 7501 | I50: TH1-R9 | J50: Sept | K50: X | L50: Y | M50: Y | N50: Y | O50: Y | P50: Y | Q50: Y | R50: Y | S50: Y | T50: Y | U50: Y | V50: Y
A51: 1060 Craigdarroch Road | B51: Pemberton Holmes | D51: 50 | E51: Esquimalt, BC | G51: ACTIVE | H51: 373 | I51: M1-R1 | J51: March | K51: Y | L51: Y | M51: Y | N51: ANNUAL | O51: Y | P51: Y | Q51: Y | R51: Y | S51: Y | T51: Y | U51: X | V51: Y
A52: 1060 Goldstream Avenue | B52: Centurion Properties | C52: *SEE NOTE IN JULY* Months on invoice | D52: 55 | E52: Langford, BC | F52: 44949 | G52: ACTIVE | H52: 412 | I52: TU1-R5 | J52: September | K52: Y | L52: Y | M52: Y | N52: Y | O52: Y | P52: Y | Q52: Y | R52: Y | S52: ANNUAL | T52: Y | U52: Y | V52: Y
A53: 1060 Southgate Street | B53: Southgate Manor | D53: 50 | E53: Victoria, BC | F53: 44949 | G53: ACTIVE | H53: 42 | I53: TU3-R18 | J53: Sept | K53: Y | L53: Y | M53: Y | N53: Y | O53: Y | P53: Y | Q53: Y | R53: Y | S53: Y | T53: Y | U53: ANNUAL | V53: Y
A54: 1066 Foul Bay Road | B54: Newport Property | D54: 50 | E54: Victoria, BC | F54: 44949 | G54: ACTIVE | H54: 124 | I54: TU2-R13 | J54: July* | K54: Y | L54: Y | M54: Y | N54: Y | O54: Y | P54: Y | Q54: ANNUAL | R54: Y | S54: Y | T54: Y | U54: Y | V54: Y
A55: 1069 Southgate Street | B55: Newport Property Management | D55: 50 | E55: Victoria, BC | G55: ACTIVE | H55: 307 | I55: M1-R2 | J55: March | K55: Y | L55: Y | M55: Y | N55: Y | O55: ANNUAL | P55: Y | Q55: Y | R55: Y | S55: Y | T55: Y | U55: Y | V55: Y
A56: 109 Wilson Street | B56: Pacifica Housing | D56: 65 | E56: Esquimalt, BC | F56: 45505 | G56: ACTIVE | H56: A 901 | I56: W1-R7 | J56: July | K56: X | L56: X | M56: X | N56: X | O56: X | P56: X | Q56: ANNUAL | R56: Y | S56: Y | T56: Y | U56: Y | V56: Y
A57: 1090 Johnson Street | B57: Firm Management | D57: 60 | E57: Victoria, BC | F57: 45017 | G57: ACTIVE | H57: TM 0901 | I57: TH1-R8 | J57: March | K57: Y | L57: Y | M57: Y | N57: ANNUAL | O57: Y | P57: Y | Q57: Y | R57: X | S57: Y | T57: Y | U57: Y | V57: Y
A58: 1097 View Street | B58: Firm Management | C58: NEW FEB/24 | D58: 125 | E58: Victoria, BC | F58: 45346 | G58: ACTIVE | H58: VS 7901 | I58: TH1-R8 | J58: TBD | K58: X | L58: X | M58: Y | N58: Y | O58: Y | P58: Y | Q58: Y | R58: Y | S58: Y | T58: Y | U58: Y | V58: ANNUAL
A59: 110 Douglas Street | B59: Devon Properties | D59: 50 | E59: Victoria, BC | G59: ACTIVE | H59: 344 | I59: TU3-R18 | J59: August | K59: Y | L59: Y | M59: Y | N59: Y | O59: Y | P59: Y | Q59: Y | R59: Y | S59: Y | T59: Y | U59: ANNUAL | V59: Y
A60: 1106 Balmoral Road | B60: Peter Hejjas 45 + GST | D60: 50 | E60: Victoria, BC | F60: 44949 | G60: ACTIVE | H60: 127 | I60: M1-R3 | J60: Jan | K60: Y | L60: Y | M60: ANNUAL | N60: Y | O60: Y | P60: Y | Q60: Y | R60: Y | S60: Y | T60: Y | U60: Y | V60: Y
A61: 1111 Hillside Avenue | B61: Complete Residential | D61: 55 | E61: Victoria, BC | G61: ACTIVE | H61: OP 1111 | I61: M1-R1 | J61: July | K61: Y | L61: Y | M61: Y | N61: Y | O61: Y | P61: Y | Q61: ANNUAL | R61: Y | S61: Y | T61: Y | U61: X | V61: Y
A62: 1115 Craigflower Road | B62: Proline | C62: $65/month (A) | D62: 65 | E62: Esquimalt, BC | F62: 44378 | G62: ACTIVE | H62: IW 5111 K6-G1 | I62: W1-R7 | J62: August | K62: Y | L62: Y | M62: Y | N62: Y | O62: Y | P62: Y | Q62: Y | R62: Y | S62: ANNUAL | T62: Y | U62: Y | V62: Y
A63: 1120 Blanshard Street | B63: Equitex | D63: 50 | E63: Victoria, BC | F63: 44949 | G63: ACTIVE | H63: N/A | I63: TH2-R15 | J63: Feb | K63: Y | L63: Y | M63: ANNUAL | N63: Y | O63: Y | P63: X | Q63: X | R63: Y | S63: Y | T63: Y | U63: Y | V63: Y
A64: 1120 Burdett Ave | B64: Devon Properties | D64: 55 | E64: Victoria, BC | F64: 45589 | G64: ACTIVE | H64: B0211 | I64: TH1-R9 | K64: X | L64: X | M64: X | N64: X | O64: X | P64: X | Q64: X | R64: X | S64: X | T64: X | U64: Y | V64: Y
A65: 1120 Richardson Street | B65: Gibraltar | D65: 50 | E65: Victoria, BC | F65: 44949 | G65: ACTIVE | H65: 4 | I65: TH1-R9 | J65: September | K65: Y | L65: Y | M65: Y | N65: Y | O65: Y | P65: Y | Q65: Y | R65: Y | S65: ANNUAL | T65: Y | U65: Y | V65: Y
A66: 1120 Yates Street | B66: Chard Property | D66: 50 | E66: Victoria, BC | F66: 44949 | G66: ACTIVE | H66: 321 | I66: TH1-R8 | J66: Nov | K66: Y | L66: Y | M66: Y | N66: Y | O66: Y | P66: Y | Q66: Y | R66: Y | S66: Y | T66: X | U66: X | V66: X
A67: 1122 Hilda Street | B67: Pemberton Strata | D67: 50 | E67: Victoria, BC | G67: ACTIVE | H67: 427 | I67: TU2-R13 | J67: Nov* | K67: Y | L67: Y | M67: Y | N67: Y | O67: Y | P67: Y | Q67: Y | R67: Y | S67: Y | T67: Y | U67: Y | V67: ANNUAL
A68: 1122 McKenzie Street | B68: Pemberton Holmes | D68: 50 | E68: Victoria, BC | G68: ACTIVE | H68: 100 | I68: M1-R2 | J68: March | K68: Y | L68: Y | M68: Y | N68: Y | O68: Y | P68: Y | Q68: Y | R68: Y | S68: Y | T68: Y | U68: Y | V68: Y
A69: 1125 Douglas Street | B69: Arpeg Holdings Cactus Club | C69: single panel share with 702 Fort Street | D69: 65 | E69: Victoria, BC | F69: 41153 | G69: ACTIVE | H69: MEET KEN COOPER | I69: TH2-R15 | J69: April | K69: X | L69: Y | M69: Y | N69: X | O69: Y | P69: ANNUAL | Q69: Y | R69: Y | S69: Y | T69: ON HOLD | U69: Y | V69: Y
A70: 1125 Hillside Avenue | B70: Devon Properties | D70: 55 | E70: Victoria, BC | F70: 45539 | G70: ACTIVE | H70: H 5211 | I70: W1-R6 | J70: August | K70: X | L70: X | M70: X | N70: X | O70: X | P70: X | Q70: X | R70: X | S70: Y | T70: X | U70: Y | V70: Y
A71: 1126 Rockland Avenue | B71: Starlight/Devon | D71: 70 | E71: Victoria, BC | F71: 45170 | G71: ACTIVE | H71: LD 6211 | I71: TH1-R9 | J71: July* | K71: Y | L71: Y | M71: Y | N71: Y | O71: Y | P71: Y | Q71: ANNUAL | R71: Y | S71: Y | T71: Y | U71: Y | V71: Y
A72: 1127 Wharf Street | B72: Darcy's Pub | D72: 55 | E72: Victoria, BC | F72: 41791 | G72: ACTIVE | H72: KEY AT SITE | I72: TH2-R15 | J72: April* | K72: Y | L72: Y | M72: Y | N72: ANNUAL | O72: Y | P72: Y | Q72: Y | R72: Y | S72: Y | T72: Y | U72: Y | V72: Y
A73: 1130 Fort Street | B73: Pacifica Housing | D73: 65 | E73: Victoria, BC | F73: 45527 | G73: ACTIVE | H73: F 0311 | I73: TH1-R8 | J73: July | K73: X | L73: X | M73: X | N73: X | O73: X | P73: X | Q73: ANNUAL | R73: Y | S73: Y | T73: Y | U73: Y | V73: Y
A74: 1132 McClure Street | B74: Devon Properties | D74: 50 | E74: Victoria, BC | F74: 44949 | G74: ACTIVE | H74: 162 | I74: TH1-R9 | J74: August | K74: Y | L74: Y | M74: Y | N74: Y | O74: Y | P74: Y | Q74: Y | R74: Y | S74: Y & ANNUAL | T74: Y | U74: Y | V74: Y
A75: 1133A Reynolds Road | B75: Abbeyfield St. Peters | D75: 55 | E75: Saanich, BC | G75: ACTIVE | H75: PQ 3311 | I75: TU1-R4 | J75: Feb | K75: Y | L75: Y | M75: Y | N75: Y | O75: Y | P75: Y | Q75: Y | R75: Y | S75: Y | T75: Y | U75: Y | V75: Y
A76: 1145 Bay Street | B76: Ashton Oaks c/o Gateway Prop | D76: 50 | E76: Victoria, BC | F76: 44949 | G76: ACTIVE | H76: 322 | I76: M1-R3 | J76: Sept* | K76: Y | L76: Y | M76: Y | N76: Y | O76: Y | P76: X | Q76: Y | R76: Y | S76: ANNUAL | T76: Y | U76: Y | V76: Y
A77: 1150 Hilda Street | B77: Devon Properties | D77: 60 | E77: Victoria, BC | F77: 45448 | G77: ACTIVE | H77: AH 0511 | I77: M1-R2 | J77: August | K77: X | L77: X | M77: X | N77: X | O77: X | P77: Y | Q77: Y | R77: Y | S77: Y | T77: Y | U77: Y | V77: Y
A78: 1150 Queens Queens | B78: Pacific Quorum | D78: 65 | E78: Victoria, BC | G78: ACTIVE | H78: 406 | I78: M1-R1 | J78: Jan | K78: Annual & Y | L78: Y | M78: Y | N78: Y | O78: Y | P78: Y | Q78: Y | R78: Y | S78: Y | T78: Y | U78: X | V78: Y
A79: 1150 Rockland Avenue | B79: Pemberton Holmes | D79: 50 | E79: Victoria, BC | G79: ACTIVE | H79: 346 | I79: M1-R2 | J79: Sept | K79: Y | L79: Y | M79: Y | N79: Y | O79: Y | P79: Y | Q79: Y | R79: Y | S79: Y | T79: Y & ANNUAL | U79: Y | V79: Y
A80: 1160 Esquimalt Road | B80: Devon Properties | C80: Starting November 2024 | D80: 55 | E80: Victoria, BC | F80: 45620 | G80: ACTIVE | H80: Pick keys at site (Lockbox) | I80: W1-R7 | J80: Dec | Q80: X | R80: X | S80: X | T80: X | U80: Y | V80: Y
A81: 1160 Richardson Street | B81: Lee & Sharpe | D81: 50 | E81: Victoria, BC | G81: ACTIVE | H81: 164 | I81: M1-R2 | J81: March | K81: Y | L81: Y | M81: ANNUAL | N81: Y | O81: Y | P81: Y | Q81: Y | R81: Y | S81: Y | T81: Y | U81: Y | V81: Y
A82: 1165 Meares Street | B82: Pemberton Holmes (new June 13/24) | C82: June 13/24- switched to Pemberton Holmes from Raven | D82: 55 | E82: Victoria, BC | F82: 42005 | G82: ACTIVE | H82: MA 5611 K2 | I82: M1-R2 | J82: July | K82: Y | L82: Y | M82: Y | N82: Y | O82: Y | P82: Y | Q82: Y & ANNUAL | R82: Y | S82: Y | T82: Y | U82: Y | V82: Y
A83: 1165 Yates Street | B83: Devon properties | D83: 50 | E83: Victoria, BC | G83: ACTIVE | H83: 340 | I83: M1-R1 | J83: Nov | K83: Y | L83: Y | M83: Y | N83: Y | O83: Y | P83: Y | Q83: Y | R83: Y | S83: Y | T83: Y | U83: X | V83: Y
A84: 1166 Rockland Avenue | B84: Freelance | D84: 55 | E84: Victoria, BC | G84: ACTIVE | H84: K 6611 K3 | I84: TH1-R9 | J84: September | K84: Y | L84: Y | M84: Y | N84: Y | O84: Y | P84: Y | Q84: Y | R84: Y | S84: ANNUAL | T84: Y | U84: Y | V84: Y
A85: 1177 Esquimalt Road | B85: Devon Properties | D85: 50 | E85: Esquimalt, BC | F85: 44949 | G85: ACTIVE | H85: 368 | I85: W1-R7 | J85: March | K85: Y | L85: Y | M85: Y + ANNUAL | N85: Y | O85: Y | P85: Y | Q85: Y | R85: Y | S85: Y | T85: Y | U85: Y | V85: Y
A86: 1178 Beach Drive | B86: Devon Properties | D86: 50 | E86: Oak Bay, BC | F86: 44949 | G86: ACTIVE | H86: 108 | I86: TU2-R13 | J86: July* | K86: Y | L86: Y | M86: Y | N86: Y | O86: Y | P86: Y | Q86: ANNUAL | R86: Y | S86: Y | T86: Y | U86: Y | V86: Y
A87: 118 Croft Street | B87: Brown Bros. | D87: 50 | E87: Victoria, BC | G87: ACTIVE | H87: 366 | I87: W3-R20 | J87: May* | K87: Y | L87: Y | M87: Y | N87: Y | O87: ANNUAL | P87: Y | Q87: Y | R87: Y | S87: Y | T87: X | U87: Y | V87: Y
A88: 1180 Colville Road | B88: Starlight Properties c/o Devon Properties | D88: 65 | E88: Esquimalt, BC | F88: 45253 | G88: ACTIVE | H88: CR 0811 | I88: W1-R7 | J88: Sept | K88: Y | L88: Y | M88: Y | N88: Y | O88: Y | P88: Y | Q88: Y | R88: Y | S88: Y | T88: Y & ANNUAL | U88: Y | V88: Y
A89: 1180 View Street | B89: Devon Properties | D89: 50 | E89: Victoria, BC | G89: ACTIVE | H89: 404 | I89: M1-R1 | J89: July | K89: Y | L89: Y | M89: Y | N89: X | O89: Y | P89: Y | Q89: ANNUAL | R89: Y | S89: Y | T89: Y | U89: X | V89: Y
A90: 1185 Yates Street | B90: Devon Properties | D90: 50 | E90: Victoria, BC | F90: 44949 | G90: ACTIVE | H90: 386 | I90: TH1-R8 | J90: April* | K90: Y | L90: Y | M90: Y | N90: ANNUAL | O90: Y | P90: Y | Q90: Y | R90: Y | S90: Y | T90: Y | U90: Y | V90: Y
A91: 1190 May Street | B91: Devon Properties | D91: 50 | E91: Victoria, BC | F91: 44949 | G91: ACTIVE | H91: 409 | I91: TU2-R13 | J91: Feb | K91: Y | L91: ANNUAL | M91: Y | N91: Y | O91: Y | P91: Y | Q91: Y | R91: Y | S91: Y | T91: Y | U91: Y | V91: Y
A92: 1194 Esquimalt Road | B92: Capital West | D92: 60 | E92: Esquimalt, BC | F92: 45078 | G92: ACTIVE | H92: FM 4911 | I92: W1-R7 | J92: March | K92: Y | L92: Y | M92: ANNUAL | N92: Y | O92: Y | P92: Y | Q92: Y | R92: Y | S92: Y | T92: Y | U92: Y | V92: Y
A93: 1196 Clovelly Terrace | B93: 1196 Strata Corp VIS5164 | D93: 55 | E93: Victoria, BC | F93: 44287 | G93: ACTIVE | H93: No Key | I93: W1-R6 | J93: March | K93: Y | L93: Y | M93: ANNUAL | N93: Y | O93: Y | P93: Y | Q93: Y | R93: Y | S93: Y | T93: X | U93: Y | V93: Y
A94: 1196 Sluggett Road | B94: Firm Management | D94: 55 | E94: Brentwood Bay, BC | F94: 44348 | G94: ACTIVE | H94: OW 6911 | I94: TU2-R12 | J94: August | K94: Y | L94: Y | M94: Y | N94: Y | O94: Y | P94: Y | Q94: Y | R94: Y | S94: X | T94: ANNUAL | U94: Y | V94: Y
A95: 120 Douglas Street | B95: Oakwood | D95: 55 | E95: Victoria, BC | G95: ACTIVE | H95: AT 021 K3 | I95: TU3-R18 | J95: Sept | K95: Y | L95: Y | M95: Y | N95: Y | O95: Y | P95: Y | Q95: Y | R95: Y | S95: Y | T95: Y | U95: Y | V95: ANNUAL
A96: 1208 Rockland Avenue | B96: Devon Properties | D96: 50 | E96: Victoria, BC | F96: 44949 | G96: ACTIVE | H96: 133 | I96: TH1-R9 | J96: March | K96: Y | L96: Y | M96: Y | N96: ANNUAL | O96: Y | P96: Y | Q96: Y | R96: Y | S96: Y | T96: Y | U96: Y | V96: Y
A97: 1209 & 1229 Clarke Road | B97: Central Saanich Municipality | C97: $65/month (A). PO & Months Required | D97: 65 | E97: Brentwood Bay, BC | F97: 44185 | G97: ACTIVE | H97: CC 9021 K4 | I97: TU2-R12 | J97: April | K97: Y | L97: Y | M97: Y | N97: Annual | O97: Y | P97: Y | Q97: Y | R97: Y | S97: X | T97: Y | U97: Y | V97: Y
A98: 1216 Johnson Street | B98: Devon Properties | D98: 50 | E98: Victoria, BC | F98: 44949 | G98: ACTIVE | H98: 180 | I98: TH1-R8 | J98: Dec | K98: Y | L98: Y | M98: Y | N98: Y | O98: Y | P98: Y | Q98: X | R98: Y | S98: Y | T98: Y | U98: Y | V98: Y
A99: 1220 Pandora Avenue | B99: Devon Properties | D99: 50 | E99: Victoria, BC | F99: 44949 | G99: ACTIVE | H99: 136 | I99: M1-R3 | J99: Nov | K99: Y | L99: Y | M99: Y | N99: Y | O99: Y | P99: Y | Q99: Y | R99: Y | S99: Y | T99: Y | U99: ANNUAL | V99: Y
A100: 1222 Douglas Street | B100: Firm Management | D100: 50 | E100: Victoria, BC | F100: 44949 | G100: ACTIVE | H100: DR 2221 | I100: TH2-R15 | J100: Oct | K100: Y | L100: X | M100: Y | N100: Y | O100: Y | P100: Y | Q100: Y | R100: Y | S100: Y | T100: Y | U100: Y | V100: ANNUAL
...

Sheet Detail1
A1: Details for Count of STATUS- (ACTIVE, CANCELLED, ON HOLD) - STATUS- (ACTIVE, CANCELLED, ON HOLD): ACTIVE
A3: ADDRESS | B3: PROPERTY MANAGEMENT COMPANY | C3: NOTES | D3: Price/month | E3: Area | F3: start up date | G3: STATUS- (ACTIVE, CANCELLED, ON HOLD) | H3: KEYS | I3: TEST DAY | J3: ANNUAL | K3: Jan-25 | L3: Feb-25 | M3: Mar-25 | N3: Apr-25 | O3: May-25 | P3: Jun-25 | Q3: Jul-25 | R3: Aug-25 | S3: Sep-25 | T3: Oct-25 | U3: Nov-25 | V3: Dec-25
A4: #103-4475 Viewmont | B4: Hansbraun | C4: MONTHLY EXT & ELU TESTS | D4: 75 | E4: Saanich, BC | F4: 45559 | G4: ACTIVE | H4: NONE | I4: TU1-R4 | J4: May | K4: Y | L4: Y | M4: Y | N4: Y | O4: ANNUAL | P4: Y | Q4: Y | R4: Y
A5: 10 Paul Kane/11 Cooperage Place | B5: Proline | D5: 55 | E5: Esquimalt, BC | F5: 41730 | G5: ACTIVE | H5: UV 01 | I5: W1-R7 | J5: May | K5: Y | L5: X | M5: Y | N5: Y | O5: ANNUAL | P5: X | Q5: Y | R5: Y
A6: 1000 Mckenzie Avenue | B6: Starlight/Devon | D6: 55 | E6: Saanich, BC | F6: 45559 | G6: ACTIVE | H6: M 0001 | I6: W1-R6 | J6: May | K6: Y | L6: Y | M6: Y | N6: Y | O6: Y | P6: ANNUAL | Q6: X | R6: X
A7: 1000-1012 Douglas Street | B7: Itziar Management Ltd. (0824606 BC Ltd.) | D7: 60 | E7: Victoria, BC | F7: 45589 | G7: ACTIVE | H7: D 2101 | I7: TH2-R15 | J7: June | K7: Y | L7: Y | M7: Y | N7: Y | O7: Y | P7: Y | Q7: Y
A8: 1001 Wharf Street | B8: Pastoral Developments Ltd. | D8: 55 | E8: Victoria, BC | F8: 43313 | G8: ACTIVE | H8: NA 1001 K2-F1 | I8: TH2-R15 | J8: October | K8: Y | L8: Y | M8: Y | N8: Y | O8: Y | P8: Y | Q8: Y
A9: 10016 3rd Street | B9: Cornerstone | D9: 50 | E9: Sidney, BC | F9: 44949 | G9: ACTIVE | H9: 358 | I9: F2-R16 | J9: February | K9: Y | L9: Y | M9: ANNUAL | N9: Y | O9: Y | P9: Y | Q9: Y
A10: 10017 Avenger Way | B10: Lumberworld Operations Ltd. | D10: 75 | E10: Sidney, BC | F10: 45863 | G10: ACTIVE | H10: VG 71001 | I10: F2-R16 | J10: October | K10: X | L10: X | M10: X | N10: X | O10: X | P10: X | Q10: X
A11: 1002 Mckenzie Avenue | B11: Starlight/Devon | D11: 55 | E11: Saanich, BC | F11: 45559 | G11: ACTIVE | H11: M 0001 | I11: W1-R6 | J11: May | K11: Y | L11: Y | M11: Y | N11: Y | O11: Y | P11: ANNUAL | Q11: X | R11: Y
A12: 1002 Pakington | B12: Devon Properties | D12: 50 | E12: Victoria, BC | F12: 44949 | G12: ACTIVE | H12: 146 | I12: TU3-R18 | J12: September | K12: Y | L12: Y | M12: Y | N12: Y | O12: Y | P12: Y | Q12: Y | S12: ANNUAL
A13: 1002 Wharf Street | B13: Malahat Properties | D13: 55 | E13: Victoria, BC | F13: 44174 | G13: ACTIVE | H13: At Reception | I13: TH2-R15 | J13: January | K13: Y | L13: ANNUAL | M13: Y | N13: Y | O13: Y | P13: Y | Q13: Y
A14: 10025 Resthaven Drive | B14: Inken Roller c/o Richmond Property Group | D14: 50 | E14: Sidney, BC | F14: 44949 | G14: ACTIVE | H14: 349 | I14: F2-R16 | J14: February | K14: Y | L14: ANNUAL | M14: X | N14: Y | O14: Y | P14: Y | Q14: Y
A15: 10030 Resthaven Drive | B15: Raven Property Management Ltd. | D15: 75 | E15: Sidney, BC | F15: 44228 | G15: ACTIVE | H15: SC 03001 | I15: F2-R16 | J15: May | K15: Y | L15: Y | M15: Y | N15: Y | O15: Y | P15: ANNUAL | Q15: Y
A16: 1004 Pemberton Road | B16: Raul Caballero | D16: 70 | E16: Victoria, BC | F16: 45161 | G16: ACTIVE | H16: PB 4001 | I16: M1-R1 | J16: December | K16: ANNUAL | L16: Y | M16: Y | N16: Y | O16: Y | P16: Y | Q16: Y | R16: Y
A17: 1005 & 1009 McKenzie Avenue | B17: Firm Management | D17: 60 | E17: Saanich, BC | G17: ACTIVE | H17: MN 5001 | I17: TU1-R4 | J17: May | K17: X | L17: X | M17: X | N17: X | O17: X | P17: ANNUAL | Q17: Y | R17: Y
A18: 1005 Broad Street | B18: Richmond Property Group | D18: 55 | E18: Victoria, BC | G18: ACTIVE | H18: K 5001 K4 | I18: TH2-R15 | J18: March | K18: Y | L18: Y | M18: ANNUAL | N18: Y | O18: Y | P18: Y | Q18: Y
A19: 1005 Pakington Street | B19: Century 21 Queenswood | D19: 50 | E19: Victoria, BC | F19: 44949 | G19: ACTIVE | H19: 171 | I19: TU3-R18 | J19: August | K19: Y | L19: Y | M19: Y | N19: Y | O19: Y | P19: Y | Q19: Y
A20: 1005 St. Charles Street | B20: Bross Holdings | D20: 55 | E20: Victoria, BC | F20: 45713 | G20: ACTIVE | H20: HC 5001 | I20: TH1-R9 | J20: May | K20: X | L20: Y | M20: Y | N20: Y | O20: Y | P20: ANNUAL | Q20: Y | R20: Y
A21: 1006 Fort Street | B21: Colliers | D21: 75 | E21: Victoria, BC | F21: 41214 | G21: ACTIVE | H21: ZZ 6001 K3-F1 | I21: M1-R2 | J21: September | K21: Y | L21: Y | M21: Y | N21: Y | O21: Y | P21: Y | Q21: Y | R21: ANNUAL
A22: 1006 Tolmie Avenue | B22: Century 21 Queenswood | D22: 60 | E22: Victoria, BC | G22: ACTIVE | H22: 163 | I22: M1-R1 | J22: January | K22: Y | L22: ANNUAL | M22: Y | N22: Y | O22: Y | P22: Y | Q22: Y | R22: Y
A23: 1007 Esquimalt Road | B23: Starlight Properties | D23: 50 | E23: Esquimalt, BC | G23: ACTIVE | H23: LT 7001 | I23: W1-R7 | J23: May | K23: Y | L23: Y | M23: Y | N23: Y | O23: ANNUAL | P23: X | Q23: Y | R23: Y
A24: 101 Ontario Street | B24: Proline Property Management | D24: 55 | E24: Victoria, BC | F24: 45712 | G24: ACTIVE | H24: OT 101 | I24: W3-R20 | J24: November | K24: X | L24: Y | M24: Y | N24: Y | O24: Y | P24: Y | Q24: Y
A25: 1010 Mckenzie Avenue | B25: Starlight/Devon | D25: 55 | E25: Saanich, BC | F25: 45559 | G25: ACTIVE | H25: M 0001 | I25: W1-R6 | J25: February | K25: Y | L25: ANNUAL | M25: Y | N25: Y | O25: Y | P25: X | Q25: X | R25: Y
A26: 1012 Collinson Street | B26: Hutton | D26: 55 | E26: Victoria, BC | G26: ACTIVE | H26: M 2101 K3 | I26: TH1-R9 | J26: October | K26: Y | L26: Y | M26: Y | N26: Y | O26: Y | P26: Y | Q26: Y | R26: Y
A27: 1013 Vancouver Street | B27: Devon Properties | D27: 50 | E27: Victoria, BC | F27: 44949 | G27: ACTIVE | H27: 183 | I27: TH1-R8 | J27: May | K27: Y | L27: Y | M27: Y | N27: Y | O27: X | P27: Y | Q27: Y | R27: Y
A28: 1015 Kings Road | B28: Darioush Diba | D28: 55 | E28: Victoria, BC | F28: 44075 | G28: ACTIVE | H28: KQ 5101 | I28: M1-R3 | J28: June | K28: Y | L28: Y | M28: Y | N28: Y | O28: Y | P28: ANNUAL | Q28: Y | R28: Y
A29: 10159 Third Street | B29: Realstar Management | D29: 55 | E29: Sidney, BC | G29: ACTIVE | H29: 93 | I29: F2-R16 | J29: November | K29: Y | L29: Y | M29: Y | N29: Y | O29: Y | P29: Y | Q29: Y
A30: 1017 Queens Avenue | B30: Starlight/Devon | D30: 50 | E30: Victoria, BC | F30: 44949 | G30: ACTIVE | H30: 111 | I30: M1-R3 | J30: March | K30: Y | L30: Y | M30: Y | N30: ANNUAL | O30: Y | P30: Y | Q30: Y | R30: Y
A31: 1019 McClure Street | B31: Strata Plan VIS 308 | D31: 65 | E31: Victoria, BC | F31: 45253 | G31: ACTIVE | H31: CL 9101 | I31: TH1-R9 | J31: April | K31: Y | L31: Y | M31: Y | N31: ANNUAL | O31: Y | P31: Y | Q31: Y | R31: Y
A32: 1019 Rockland Avenue | B32: Proline | D32: 55 | E32: Victoria, BC | F32: 42186 | G32: ACTIVE | H32: ST 9101 K2 | I32: M1-R2 | J32: December | K32: Y | L32: Y | M32: Y | N32: ANNUAL | O32: Y | P32: Y | Q32: Y | R32: Y
A33: 1020 Park Boulevard | B33: Pemberton Holmes | D33: 50 | E33: Victoria, BC | F33: 44949 | G33: ACTIVE | H33: 92 | I33: TU3-R18 | J33: November | K33: Y | L33: Y | M33: Y | N33: Y | O33: Y | P33: Y | Q33: Y
A34: 1020 Pembroke Street | B34: Brown Bros. | D34: 55 | E34: Victoria, BC | F34: 42476 | G34: ACTIVE | H34: RT 0201 K2 | I34: M1-R3 | J34: July | K34: Y | L34: Y | M34: Y | N34: Y | O34: Y | P34: Y | Q34: ANNUAL | R34: Y
A35: 1024 Fairfield Road | B35: Firm Management | D35: 55 | E35: Victoria, BC | F35: 41791 | G35: ACTIVE | H35: WT 4201 K3 | I35: TH1-R9 | J35: December | K35: Y | L35: Y | M35: Y | N35: Y | O35: ANNUAL | P35: Y | Q35: Y | R35: Y
A36: 1025 Johnson Street | B36: Devon Properties | D36: 60 | E36: Victoria, BC | F36: 45017 | G36: ACTIVE | H36: JD 5201 K5-F2 | I36: TH1-R8 | J36: January | K36: ANNUAL | L36: Y | M36: Y | N36: Y | O36: Y | P36: Y | Q36: Y | R36: Y
A37: 1026 Johnson Street | B37: Firm Management | D37: 55 | E37: Victoria, BC | F37: 41821 | G37: ACTIVE | H37: WS 6201 K4-F1 | I37: TH1-R8 | J37: July | K37: Y | L37: Y | M37: Y | N37: Y | O37: Y | P37: Y | Q37: Y | R37: Y
A38: 1030 Pendergast Street | B38: Starlight/Devon | D38: 70 | E38: Victoria, BC | F38: 45192 | G38: ACTIVE | H38: GT 0301 | I38: TU3-R18 | J38: July | K38: Y | L38: Y | M38: Y | N38: Y | O38: Y | P38: Y | Q38: ANNUAL
A39: 9993 Fourth Street | B39: Complete Residential | D39: 50 | E39: Sidney, BC | G39: ACTIVE | H39: 417 | I39: F1-R10 | J39: April | K39: Y | L39: Y | M39: Y | N39: ANNUAL | O39: Y | P39: Y | Q39: Y | R39: Y
A40: 1032 North Park | B40: Pacific Quorum $55 | D40: 55 | E40: Victoria, BC | F40: 45039 | G40: ACTIVE | H40: 435 | I40: M1-R3 | J40: March | K40: X | L40: Y | M40: X | N40: ANNUAL | O40: X | P40: X | Q40: X | R40: Y
A41: 1035 Belmont Avenue | B41: Belmont Properties | D41: 55 | E41: Victoria, BC | F41: 45017 | G41: ACTIVE | H41: 445 | I41: TH1-R9 | J41: August | K41: Y | L41: Y | M41: Y | N41: Y | O41: Y | P41: Y | Q41: Y | R41: Y | S41: ANNUAL
A42: 1035 Pendergast Street | B42: Starlight/Devon | D42: 70 | E42: Victoria, BC | F42: 45192 | G42: ACTIVE | H42: GT 0301 | I42: TU3-R18 | J42: July | K42: Y | L42: Y | M42: Y | N42: Y | O42: Y | P42: Y | Q42: ANNUAL
A43: 1036 Stellys Cross Road | B43: Devon Properties | D43: 50 | E43: Brentwood Bay, BC | G43: ACTIVE | H43: 424 | I43: TU2-R12 | J43: December | K43: Y | L43: Y | M43: Y | N43: Y | O43: Y | P43: Y | Q43: Y | R43: Y | S43: Y
A44: 104 Dallas Road | B44: Strata #1374 The Dolphins | D44: 55 | E44: Victoria, BC | F44: 43891 | G44: ACTIVE | H44: SP 401 K1-F1 | I44: W3-R20 | J44: August | K44: Y | L44: Y | M44: Y | N44: Y | O44: Y | P44: Y | Q44: Y | R44: ANNUAL
A45: 1040 Stellys Cross Road | B45: Devon Properties | D45: 50 | E45: Brentwood Bay, BC | G45: ACTIVE | H45: 424 | I45: TU2-R12 | J45: December | K45: Y | L45: Y | M45: Y | N45: Y | O45: Y | P45: Y | Q45: Y | R45: Y | S45: Y
A46: 1041 Fairfield Road | B46: Pemberton Holmes | D46: 50 | E46: Victoria, BC | G46: ACTIVE | H46: 68 | I46: M1-R2 | J46: April | K46: Y | L46: Y | M46: Y | N46: ANNUAL | O46: Y | P46: Y | Q46: Y | R46: Y
A47: 1041 Richardson Road | B47: Capital West | D47: 60 | E47: Victoria, BC | F47: 45078 | G47: ACTIVE | H47: RR 1401 | I47: TH1-R9 | J47: June | K47: Y | L47: Y | M47: Y | N47: Y | O47: ANNUAL | P47: Y | Q47: Y | R47: Y
A48: 1045 McClure Street | B48: Brown Bros. | D48: 50 | E48: Victoria, BC | G48: ACTIVE | H48: 332 | I48: M1-R2 | J48: December | K48: Y | L48: Y | M48: Y | N48: Y | O48: Y | P48: Y | Q48: Y | R48: Y
A49: 10459 Resthaven Drive | B49: Proline | D49: 50 | E49: Sidney, BC | F49: 44949 | G49: ACTIVE | H49: 392 | I49: F2-R16 | J49: May | K49: Y | L49: Y | M49: Y | N49: Y | O49: Y | P49: ANNUAL | Q49: Y
A50: 10461 Resthaven Drive | B50: Proline | D50: 50 | E50: Sidney, BC | F50: 44949 | G50: ACTIVE | H50: 392 | I50: F2-R16 | J50: May | K50: Y | L50: Y | M50: Y | N50: Y | O50: Y | P50: ANNUAL | Q50: Y
A51: 1049 Southgate Street | B51: Devon Properties | D51: 50 | E51: Victoria, BC | F51: 44949 | G51: ACTIVE | H51: 186 | I51: TU3-R18 | J51: September | K51: Y | L51: Y | M51: Y | N51: Y | O51: Y | P51: Y | Q51: Y
A52: 105 Wilson Street | B52: Pacifica Housing | D52: 65 | E52: Esquimalt, BC | F52: 45505 | G52: ACTIVE | H52: W 501 | I52: W1-R7 | J52: July | K52: Y | L52: X | M52: Y | N52: Y | O52: Y | P52: Y | Q52: Y | R52: ANNUAL
A53: 1050 Park Boulevard | B53: Hutton | C53: $60/month (incl. hose, ext, mag lock check) | D53: 60 | E53: Victoria, BC | F53: 44559 | G53: ACTIVE | H53: P 0501 K2 | I53: M2-R11 | J53: March | K53: Y | L53: Y | M53: ANNUAL | N53: X | O53: Y | P53: Y | Q53: Y | R53: Y
A54: 10520 McDonald Park | B54: Complete Residential Property Management | D54: 75 | E54: Sidney, BC | F54: 45772 | G54: ACTIVE | H54: DN 02501 | I54: F2-R16 | J54: November | K54: X | L54: X | M54: X | N54: Y | O54: Y | P54: Y | Q54: Y
A55: 1055 Hillside Avenue | B55: Firm Management | D55: 55 | E55: Victoria, BC | F55: 42689 | G55: ACTIVE | H55: LM 5501 | I55: W1-R6 | J55: January | K55: ANNUAL | L55: Y | M55: Y | N55: Y | O55: Y | P55: Y | Q55: Y | R55: Y
A56: 1057 Moss Street | B56: Tim Slater | C56: Charge CC in ST and email receipt | D56: 60 | E56: Victoria, BC | F56: 45346 | G56: ACTIVE | H56: SM 7501 | I56: TH1-R9 | J56: September | K56: Y | L56: Y | M56: Y | N56: Y | O56: Y | P56: Y | Q56: Y | R56: Y
A57: 1060 Craigdarroch Road | B57: Pemberton Holmes | D57: 50 | E57: Esquimalt, BC | G57: ACTIVE | H57: 373 | I57: M1-R1 | J57: March | K57: Y | L57: Y | M57: Y | N57: Y | O57: Y | P57: Y | Q57: Y | R57: Y
A58: 1060 Goldstream Avenue | B58: Centurion Properties | C58: Months on invoice | D58: 55 | E58: Langford, BC | F58: 44949 | G58: ACTIVE | H58: 412 | I58: TU1-R5 | J58: September | K58: Y | L58: Y | M58: Y | N58: Y | O58: Y | P58: Y | Q58: Y | R58: Y | S58: ANNUAL
A59: 1060 Southgate Street | B59: Southgate Manor | D59: 50 | E59: Victoria, BC | F59: 44949 | G59: ACTIVE | H59: 42 | I59: TU3-R18 | J59: September | K59: Y | L59: Y | M59: Y | N59: Y | O59: Y | P59: Y | Q59: Y
A60: 1066 Foul Bay Road | B60: Newport Property | D60: 50 | E60: Victoria, BC | F60: 44949 | G60: ACTIVE | H60: 124 | I60: TU2-R13 | J60: July | K60: Y | L60: Y | M60: Y | N60: Y | O60: Y | P60: ANNUAL | Q60: Y | R60: Y
A61: 1069 Southgate Street | B61: Newport Property Management | D61: 50 | E61: Victoria, BC | G61: ACTIVE | H61: 307 | I61: M1-R2 | J61: March | K61: Y | L61: Y | M61: Y | N61: Y | O61: Y | P61: Y | Q61: Y | R61: Y
A62: 1088 Johnson Street | B62: Centurion Property Associates Inc. | D62: 125 | E62: Victoria, BC | F62: 45833 | G62: ACTIVE | H62: HJ 8801 | I62: TH1-R8 | J62: May | K62: X | L62: X | M62: X | N62: X | O62: Y | P62: X | Q62: Y | R62: Y
A63: 109 Wilson Street | B63: Pacifica Housing | D63: 65 | E63: Esquimalt, BC | F63: 45505 | G63: ACTIVE | H63: A 901 | I63: W1-R7 | J63: July | K63: Y | L63: X | M63: Y | N63: Y | O63: Y | P63: Y | Q63: Y | R63: ANNUAL
A64: 1090 Johnson Street | B64: Firm Management | D64: 60 | E64: Victoria, BC | F64: 45017 | G64: ACTIVE | H64: TM 0901 | I64: TH1-R8 | J64: March | K64: Y | L64: Y | M64: Y | N64: Y | O64: Y | P64: Y | Q64: Y | R64: Y
A65: 1097 View Street | B65: Firm Management | C65: NEW FEB/24 | D65: 125 | E65: Victoria, BC | F65: 45346 | G65: ACTIVE | H65: VS 7901 | I65: TH1-R9 | J65: May | K65: Y | L65: Y | M65: Y | N65: Y | O65: ANNUAL | P65: Y | Q65: Y | R65: Y
A66: 110 Douglas Street | B66: Devon Properties | D66: 50 | E66: Victoria, BC | G66: ACTIVE | H66: 344 | I66: TU3-R18 | J66: August | K66: Y | L66: Y | M66: Y | N66: Y | O66: Y | P66: Y | Q66: Y
A67: 1106 Balmoral Road | B67: Peter Hejjas | D67: 50 | E67: Victoria, BC | F67: 44949 | G67: ACTIVE | H67: 127 | I67: M1-R3 | J67: March | K67: Y | L67: Y | M67: Y | N67: ANNUAL | O67: Y | P67: Y | Q67: Y | R67: Y
A68: 1110 Samar Crescent | B68: Breakwater Realty Inc. | C68: Building A | D68: 75 | E68: Langford, BC | F68: 45833 | G68: ACTIVE | H68: MS 0111 | I68: TU1-R5 | J68: October | K68: X | L68: X | M68: X | N68: X | O68: X | P68: Y | Q68: Y | R68: Y
A69: 1111 Hillside Avenue | B69: Complete Residential | D69: 55 | E69: Victoria, BC | G69: ACTIVE | H69: OP 1111 | I69: M1-R1 | J69: July | K69: Y | L69: Y | M69: Y | N69: Y | O69: Y | P69: Y | Q69: Y | R69: ANNUAL
A70: 1114 Samar Crescent | B70: Breakwater Realty Inc. | C70: Building B | D70: 75 | E70: Langford, BC | F70: 45833 | G70: ACTIVE | H70: MS 0111 | I70: TU1-R5 | J70: October | K70: X | L70: X | M70: X | N70: X | O70: X | P70: Y | Q70: Y | R70: Y
A71: 1115 Craigflower Road | B71: Proline | C71: $65/month (A) | D71: 65 | E71: Esquimalt, BC | F71: 44378 | G71: ACTIVE | H71: IW 5111 K6-G1 | I71: W2-R22 | J71: August | K71: Y | L71: Y | M71: Y | N71: Y | O71: Y | P71: Y | Q71: Y | S71: ANNUAL
A72: 1120 Blanshard Street | B72: Equitex | D72: 50 | E72: Victoria, BC | F72: 44949 | G72: ACTIVE | H72: N/A | I72: TH2-R15 | J72: February | K72: X | L72: Y | M72: ANNUAL | N72: Y | O72: Y | P72: Y | Q72: Y
A73: 1120 Burdett Ave | B73: Devon Properties | D73: 55 | E73: Victoria, BC | F73: 45589 | G73: ACTIVE | H73: B0211 | I73: TH1-R9 | J73: June | K73: Y | L73: Y | M73: Y | N73: Y | O73: Y | P73: Y | Q73: Y | R73: Y
A74: 1120 Richardson Street | B74: Gibraltar | D74: 50 | E74: Victoria, BC | F74: 44949 | G74: ACTIVE | H74: 4 | I74: TH1-R9 | J74: September | K74: Y | L74: Y | M74: Y | N74: Y | O74: Y | P74: Y | Q74: Y | R74: Y
A75: 1120 Yates Street | B75: Chard Property | D75: 50 | E75: Victoria, BC | F75: 44949 | G75: ACTIVE | H75: 321 | I75: TH1-R8 | J75: November | K75: Y | L75: Y | M75: Y | N75: Y | O75: Y | P75: X | Q75: X | R75: Y
A76: 1122 Hilda Street | B76: Pemberton Strata | D76: 50 | E76: Victoria, BC | G76: ACTIVE | H76: 427 | I76: TU2-R13 | J76: November | K76: Y | L76: Y | M76: Y | N76: Y | O76: Y | P76: Y | Q76: Y | R76: Y
A77: 1122 McKenzie Street | B77: Pemberton Holmes | D77: 50 | E77: Victoria, BC | G77: ACTIVE | H77: 100 | I77: M1-R2 | J77: March | K77: Y | L77: Y | M77: ANNUAL | N77: Y | O77: Y | P77: Y | Q77: Y | R77: Y
A78: 1125 Douglas Street | B78: Arpeg Holdings Cactus Club | C78: single panel share with 702 Fort Street | D78: 65 | E78: Victoria, BC | F78: 41153 | G78: ACTIVE | H78: MEET KEN COOPER | I78: TH2-R15 | J78: April | K78: Y | L78: Y | M78: Y | N78: Y | O78: Y | P78: ANNUAL | Q78: Y
A79: 9972 Third Street | B79: Highstreet Fourth Street (2023) LP | D79: 50 | E79: Sidney, BC | F79: 44949 | G79: ACTIVE | H79: No Key | I79: F1-R10 | J79: January | K79: Y | L79: ANNUAL | M79: Y | N79: Y | O79: Y | P79: Y | Q79: Y | R79: Y
A80: 1126 Rockland Avenue | B80: Starlight/Devon | D80: 70 | E80: Victoria, BC | F80: 45170 | G80: ACTIVE | H80: LD 6211 | I80: TH1-R9 | J80: June | K80: Y | L80: Y | M80: Y | N80: Y | O80: Y | P80: ANNUAL | Q80: Y | R80: Y
A81: 1127 Wharf Street | B81: Darcy's Pub | D81: 55 | E81: Victoria, BC | F81: 41791 | G81: ACTIVE | H81: KEY AT SITE | I81: TH2-R15 | J81: April | K81: Y | L81: Y | M81: Y | N81: Y | O81: ANNUAL | P81: Y | Q81: Y
A82: 1130 Fort Street | B82: Pacifica Housing | D82: 65 | E82: Victoria, BC | F82: 45527 | G82: ACTIVE | H82: F 0311 | I82: TH1-R9 | J82: July | K82: Y | L82: Y | M82: Y | N82: X | O82: Y | P82: Y | Q82: ANNUAL | R82: Y
A83: 1132 McClure Street | B83: Devon Properties | D83: 50 | E83: Victoria, BC | F83: 44949 | G83: ACTIVE | H83: 162 | I83: TH1-R9 | J83: August | K83: Y | L83: Y | M83: Y | N83: Y | O83: Y | P83: Y | Q83: Y | R83: Y | S83: ANNUAL
A84: 1133A Reynolds Road | B84: Abbeyfield St. Peters | D84: 55 | E84: Saanich, BC | G84: ACTIVE | H84: PQ 3311 | I84: TU1-R4 | J84: February | K84: Y | L84: Y | M84: Y | N84: Y | O84: X | P84: X | Q84: X | R84: X
A85: 9960 4th Street | B85: Freelance Strata Management | D85: 50 | E85: Sidney, BC | F85: 44949 | G85: ACTIVE | H85: 375 | I85: F1-R10 | J85: May | K85: Y | L85: X | M85: Y | N85: Y | O85: Y | P85: ANNUAL | Q85: Y | R85: Y
A86: 1145 Bay Street | B86: Ashton Oaks c/o Gateway Prop | D86: 50 | E86: Victoria, BC | F86: 44949 | G86: ACTIVE | H86: 322 | I86: M1-R3 | J86: September | K86: Y | L86: Y | M86: Y | N86: Y | O86: Y | P86: Y | Q86: Y | R86: ANNUAL
A87: 1150 Hilda Street | B87: Devon Properties | D87: 60 | E87: Victoria, BC | F87: 45448 | G87: ACTIVE | H87: AH 0511 | I87: M1-R2 | J87: August | K87: Y | L87: Y | M87: Y | N87: Y | O87: Y | P87: Y | Q87: ANNUAL | R87: Y
A88: 1150 Queens Avenue | B88: Pacific Quorum | D88: 65 | E88: Victoria, BC | G88: ACTIVE | H88: 406 | I88: M1-R1 | J88: January | K88: Y | L88: ANNUAL | M88: Y | N88: Y | O88: Y | P88: Y | Q88: Y | R88: Y
A89: 1150 Rockland Avenue | B89: Pemberton Holmes | D89: 50 | E89: Victoria, BC | G89: ACTIVE | H89: 346 | I89: M1-R2 | J89: September | K89: Y | L89: Y | M89: Y | N89: Y | O89: Y | P89: Y | Q89: Y | R89: Y
A90: 1160 Esquimalt Road | B90: Starlight/Devon | D90: 55 | E90: Victoria, BC | F90: 45620 | G90: ACTIVE | H90: Pick keys at site (Lockbox) | I90: W1-R7 | J90: December | K90: ANNUAL | L90: Y | M90: X | N90: Y | O90: Y | P90: X | Q90: Y | R90: Y
A91: 1160 Richardson Street | B91: Lee & Sharpe | D91: 50 | E91: Victoria, BC | G91: ACTIVE | H91: 164 | I91: M1-R2 | J91: March | K91: Y | L91: Y | M91: Y | N91: ANNUAL | O91: Y | P91: Y | Q91: Y | R91: Y
A92: 1165 Meares Street | B92: Pemberton Holmes (new June 13/24) | D92: 55 | E92: Victoria, BC | F92: 42005 | G92: ACTIVE | H92: MA 5611 K2 | I92: M1-R2 | J92: July | K92: Y | L92: Y | M92: Y | N92: Y | O92: Y | P92: ANNUAL | Q92: Y | R92: Y
A93: 1165 Yates Street | B93: Devon properties | D93: 50 | E93: Victoria, BC | G93: ACTIVE | H93: 340 | I93: M1-R1 | J93: February | K93: Y | L93: Y & ANNUAL | M93: Y | N93: Y | O93: Y | P93: Y | Q93: Y | R93: Y
A94: 1166 Rockland Avenue | B94: Freelance | D94: 55 | E94: Victoria, BC | G94: ACTIVE | H94: K 6611 K3 | I94: TH1-R9 | J94: September | K94: Y | L94: Y | M94: Y | N94: Y | O94: Y | P94: Y | Q94: Y | R94: Y
A95: 1177 Esquimalt Road | B95: Devon Properties | D95: 50 | E95: Esquimalt, BC | F95: 44949 | G95: ACTIVE | H95: 368 | I95: W1-R7 | J95: April | K95: Y | L95: Y | M95: Y | N95: ANNUAL | O95: Y | P95: Y | Q95: Y | R95: Y
A96: 1178 Beach Drive | B96: Devon Properties | D96: 50 | E96: Oak Bay, BC | F96: 44949 | G96: ACTIVE | H96: 108 | I96: TU2-R13 | J96: July | K96: Y | L96: Y | M96: Y | N96: Y | O96: Y | P96: Y | Q96: ANNUAL | R96: Y
A97: 118 Croft Street | B97: Brown Bros. | D97: 50 | E97: Victoria, BC | G97: ACTIVE | H97: 366 | I97: W3-R20 | J97: May | K97: Y | L97: Y | M97: Y | N97: Y | O97: ANNUAL | P97: Y | Q97: Y
A98: 1180 Colville Road | B98: Starlight Properties c/o Devon Properties | D98: 65 | E98: Esquimalt, BC | F98: 45253 | G98: ACTIVE | H98: CR 0811 | I98: W2-R22 | J98: September | K98: Y | L98: Y | M98: Y | N98: Y | O98: Y | P98: Y | Q98: Y
A99: 1180 View Street | B99: Devon Properties | D99: 50 | E99: Victoria, BC | G99: ACTIVE | H99: 404 | I99: M1-R1 | J99: July | K99: Y | L99: Y | M99: Y | N99: Y | O99: Y | P99: ANNUAL | Q99: Y | R99: Y
A100: 1185 Yates Street | B100: Devon Properties | D100: 50 | E100: Victoria, BC | F100: 44949 | G100: ACTIVE | H100: 386 | I100: TH1-R9 | J100: May | K100: Y | L100: Y | M100: Y | N100: Y | O100: ANNUAL | P100: Y | Q100: X | R100: Y
A101: 1190 May Street | B101: Devon Properties | D101: 50 | E101: Victoria, BC | F101: 44949 | G101: ACTIVE | H101: 409 | I101: TU2-R13 | J101: February | K101: Y | L101: ANNUAL | M101: Y | N101: Y | O101: Y | P101: Y | Q101: X | R101: Y
...

Sheet Detail3
A1: Details for Count of X - ANNUAL: January, STATUS- (ACTIVE, CANCELLED, ON HOLD): ACTIVE
A3: ADDRESS | B3: PROPERTY MANAGEMENT COMPANY | C3: NOTES | D3: Price/month | E3: Area | F3: start up date | G3: STATUS- (ACTIVE, CANCELLED, ON HOLD) | H3: KEYS | I3: TEST DAY | J3: ANNUAL | K3: Jan-25 | L3: Feb-25 | M3: Mar-25 | N3: Apr-25 | O3: May-25 | P3: Jun-25 | Q3: Jul-25 | R3: Aug-25 | S3: Sep-25 | T3: Oct-25 | U3: Nov-25 | V3: Dec-25
A4: 9972 Third Street | B4: Highstreet Fourth Street (2023) LP | D4: 50 | E4: Sidney, BC | F4: 44949 | G4: ACTIVE | H4: No Key | I4: F1-R10 | J4: January | K4: Y | L4: ANNUAL | M4: Y | N4: Y | O4: Y | P4: Y | Q4: Y | R4: Y
A5: 984 Mckenzie Avenue | B5: Starlight/Devon | D5: 55 | E5: Saanich, BC | F5: 45559 | G5: ACTIVE | H5: ZM 489 | I5: W1-R6 | J5: January | K5: Y | L5: Y | M5: Y | N5: Y | O5: Y | P5: X | Q5: X | R5: Y
A6: 906 Southgate Street | B6: South Island Property Mgmt (was Strata Plan Vis 742 | D6: 55 | E6: Victoria, BC | F6: 41456 | G6: ACTIVE | H6: HT 609 K2 | I6: TU3-R18 | J6: January | K6: ANNUAL | L6: Y | M6: Y | N6: Y | O6: Y | P6: Y | Q6: Y
A7: 890 Academy Close | B7: Breakwater Realty | C7: PO Required $55/month | D7: 55 | E7: Victoria, BC | G7: ACTIVE | H7: S 098 K2 | I7: TU3-R18 | J7: January | K7: ANNUAL | L7: Y | M7: Y | N7: Y | O7: Y | P7: Y | Q7: Y
A8: 838 Fort Street | B8: Minzar Holdings Ltd | D8: 55 | E8: Victoria, BC | F8: 43604 | G8: ACTIVE | H8: E 838 K2-F1 | I8: M1-R2 | J8: January | K8: Y | L8: ANNUAL | M8: Y | N8: Y | O8: Y | P8: Y | Q8: Y | R8: Y
A9: 815 Queens Avenue | B9: Devon Properties | D9: 50 | E9: Victoria, BC | F9: 44949 | G9: ACTIVE | H9: 337 | I9: M1-R3 | J9: January | K9: Y | L9: ANNUAL | M9: Y | N9: Y | O9: Y | P9: Y | Q9: Y | R9: Y
A10: 780 Kings Road | B10: Chek TV | D10: 55 | E10: Victoria, BC | F10: 44986 | G10: ACTIVE | H10: CN 087 | I10: M2-R11 | J10: January | K10: X | L10: Y | M10: Y | N10: X | O10: X | P10: Y | Q10: Y | R10: Y
A11: 747 Fort Street | B11: Associated Building Credits Ltd. c/o Breakwater Realty Inc. | D11: 65 | E11: Victoria, BC | F11: 45253 | G11: ACTIVE | H11: RF 747 | I11: TH2-R15 | J11: January | K11: Y | L11: Y | M11: Y | N11: Y | O11: Y | P11: ANNUAL | Q11: Y
A12: 720 Vancouver Street | B12: Century 21 Queenswood | D12: 50 | E12: Victoria, BC | F12: 44949 | G12: ACTIVE | H12: 69 | I12: TH1-R9 | J12: January | K12: Y & ANNUAL | L12: Y | M12: Y | N12: Y | O12: Y | P12: Y | Q12: Y | R12: Y
A13: 1002 Wharf Street | B13: Malahat Properties | D13: 55 | E13: Victoria, BC | F13: 44174 | G13: ACTIVE | H13: At Reception | I13: TH2-R15 | J13: January | K13: Y | L13: ANNUAL | M13: Y | N13: Y | O13: Y | P13: Y | Q13: Y
A14: 709-715 Yates Street | B14: Churchill on Yates GP C/O Daniel Belanger | D14: 55 | E14: Victoria, BC | F14: 42614 | G14: ACTIVE | H14: R 527 K6-F1 | I14: TH2-R15 | J14: January | K14: ANNUAL | L14: Y | M14: Y | N14: Y | O14: Y | P14: Y | Q14: Y
A15: 651 Jolly Place | B15: Cornerstone | D15: 55 | E15: Victoria, BC | F15: 44094 | G15: ACTIVE | H15: JP 156 | I15: TU1-R4 | J15: January | K15: Y | L15: ANNUAL | M15: Y | N15: Y | O15: Y | P15: X | Q15: Y | R15: Y
A16: 545 Johnson Street | B16: Devon Properties | D16: 50 | E16: Victoria, BC | F16: 44949 | G16: ACTIVE | H16: 401 | I16: TH3-R21 | J16: January | K16: Y | L16: Y | M16: Y | N16: Y | O16: Y | P16: Y | Q16: Y
A17: 539-545 Fisgard Street | B17: Servissio | D17: 70 | E17: Victoria, BC | F17: 45017 | G17: ACTIVE | H17: FA 935 | I17: TH3-R21 | J17: January | K17: ANNUAL | L17: Y | M17: Y | N17: Y | O17: Y | P17: Y | Q17: Y
A18: 520 Rithet Street | B18: Newport Property management | D18: 50 | E18: Victoria, BC | G18: ACTIVE | H18: 403 | I18: M1-R2 | J18: January | K18: ANNUAL | L18: Y | M18: Y | N18: Y | O18: Y | P18: Y | Q18: Y | R18: Y
A19: 500 Rithet Street | B19: Belmont Properties | C19: $50/m for 2024 | D19: 60 | E19: Victoria, BC | F19: 45017 | G19: ACTIVE | H19: 443 (Ring 3) | I19: W3-R20 | J19: January | K19: Y | L19: Y | M19: Y | N19: Y | O19: Y | P19: Y | Q19: Y
A20: 493 Burnside Road East | B20: Devon Properties | D20: 55 | E20: Victoria, BC | F20: 45748 | G20: ACTIVE | H20: SB 394 | I20: TU3-R19 | J20: January | K20: X | L20: X | M20: X | N20: Y | O20: Y | P20: Y | Q20: Y
A21: 3962 Cedar Hill Road | B21: Firm Management | D21: 50 | E21: Saanich, BC | F21: 45283 | G21: ACTIVE | H21: HD 8593 | I21: TU1-R4 | J21: January | K21: ANNUAL | L21: Y | M21: Y | N21: Y | O21: Y | P21: Y | Q21: Y | R21: Y
A22: 1006 Tolmie Avenue | B22: Century 21 Queenswood | D22: 60 | E22: Victoria, BC | G22: ACTIVE | H22: 163 | I22: M1-R1 | J22: January | K22: Y | L22: ANNUAL | M22: Y | N22: Y | O22: Y | P22: Y | Q22: Y | R22: Y
A23: 3958 Cedar Hill Road | B23: Firm Management | D23: 50 | E23: Saanich, BC | F23: 45283 | G23: ACTIVE | H23: HD 8593 | I23: TU1-R4 | J23: January | K23: Y | L23: ANNUAL | M23: Y | N23: Y | O23: Y | P23: Y | Q23: Y | R23: Y
A24: 3005 Cook Street | B24: Kiwanis Village Society | D24: 65 | E24: Victoria, BC | F24: 45713 | G24: ACTIVE | H24: CK 5003 | I24: W1-R6 | J24: January | K24: ANNUAL | L24: Y | M24: Y | N24: Y | O24: Y | P24: Y | Q24: Y | R24: Y
A25: 2771 Jacklin Road | B25: Groupe Denux | D25: 50 | E25: Langford, BC | G25: ACTIVE | H25: 418 | I25: TU1-R5 | J25: January | K25: Y | L25: ANNUAL | M25: Y | N25: Y | O25: Y | P25: Y | Q25: Y | R25: Y
A26: 2421 Sidney Avenue | B26: Complete Residential | D26: 50 | E26: Sidney, BC | F26: 45047 | G26: ACTIVE | H26: 416 | I26: F1-R10 | J26: January | K26: Y | L26: ANNUAL | M26: Y | N26: Y | O26: Y | P26: Y | Q26: Y | R26: Y
A27: 235 Michigan Street | B27: Brown Brothers Property Management | C27: First 3 months are free | D27: 75 | E27: Victoria, BC | F27: 45863 | G27: ACTIVE | H27: CG 532 | I27: W3-R20 | J27: January | K27: X | L27: X | M27: X | N27: X | O27: X | P27: X | Q27: Y
A28: 2243 Beacon Avenue | B28: Mary Winspear Centre | D28: 50 | E28: Sidney, BC | F28: 44949 | G28: ACTIVE | H28: No Key | I28: F1-R10 | J28: January | K28: Y | L28: ANNUAL | M28: X | N28: X | O28: Y | P28: Y | Q28: Y | R28: Y
A29: 2210 Cadboro Bay Road | B29: Brown Bros. | D29: 65 | E29: Oak Bay, BC | F29: 45406 | G29: ACTIVE | H29: DA 0122 | I29: W2-R14 | J29: January | K29: ANNUAL | L29: Y | M29: Y | N29: Y | O29: Y | P29: Y | Q29: Y
A30: 2129 Florence Street | B30: Devon Properties | D30: 50 | E30: Victoria, BC | F30: 44949 | G30: ACTIVE | H30: 305 | I30: W2-R14 | J30: January | K30: Y | L30: Y | M30: ANNUAL | N30: Y | O30: Y | P30: Y | Q30: Y
A31: 2065 Oak Bay Avenue | B31: Brown Bros. | D31: 55 | E31: Oak Bay, BC | G31: ACTIVE | H31: 428 | I31: TU2-R13 | J31: January | K31: Y | L31: Y | M31: Y | N31: Y | O31: ANNUAL | P31: Y | Q31: Y | R31: Y
A32: 2030 Malaview Drive | B32: Slegg L.P. | D32: 50 | E32: Sidney, BC | F32: 44949 | G32: ACTIVE | H32: No Key | I32: F2-R16 | J32: January | K32: Y | L32: ANNUAL | M32: Y | N32: Y | O32: Y | P32: Y | Q32: Y
A33: 1964 Fort Street | B33: Hutton | D33: 50 | E33: Victoria, BC | F33: 44949 | G33: ACTIVE | H33: 181 | I33: W2-R14 | J33: January | K33: ANNUAL | L33: Y | M33: Y | N33: Y | O33: Y | P33: Y | Q33: Y
A34: 1885 Forest Park Drive | B34: Panorama Leisure | D34: 55 | E34: North Saanich, BC | G34: ACTIVE | H34: No Key | I34: F2-R16 | J34: January | K34: Y | L34: ANNUAL | M34: Y | N34: X | O34: X | P34: X | Q34: X
A35: 1581 Hillside Avenue | B35: Brown Brothers Property Management | D35: 55 | E35: Victoria, BC | G35: ACTIVE | H35: W 1851 K2 | I35: W1-R6 | J35: January | K35: Y & ANNUAL | L35: Y | M35: Y | N35: Y | O35: Y | P35: Y | Q35: Y | R35: Y
A36: 1025 Johnson Street | B36: Devon Properties | D36: 60 | E36: Victoria, BC | F36: 45017 | G36: ACTIVE | H36: JD 5201 K5-F2 | I36: TH1-R8 | J36: January | K36: ANNUAL | L36: Y | M36: Y | N36: Y | O36: Y | P36: Y | Q36: Y | R36: Y
A37: 1485 Fort Street | B37: Peter Hejjas | D37: 65 | E37: Victoria, BC | G37: ACTIVE | H37: 138 | I37: M1-R1 | J37: January | K37: Y | L37: Y | M37: Y | N37: ANNUAL | O37: Y | P37: Y | Q37: Y | R37: Y
A38: 1461 Blanshard Street | B38: Congregation Emanu-el | D38: 60 | E38: Victoria, BC | F38: 45283 | G38: ACTIVE | H38: LD 1641 | I38: TH1-R8 | J38: January | K38: Y & ANNUAL | L38: Y | M38: Y | N38: Y | O38: Y | P38: Y | Q38: X | R38: X
A39: 1445 Fort Street | B39: Brown Bros. | D39: 50 | E39: Victoria, BC | F39: 44949 | G39: ACTIVE | H39: 141 | I39: TH1-R8 | J39: January | K39: ANNUAL | L39: Y | M39: Y | N39: Y | O39: Y | P39: Y | Q39: Y | R39: Y
A40: 1369 Mitchell Street | B40: Oak Bay United Church | D40: 55 | E40: Oak Bay, BC | F40: 44501 | G40: ACTIVE | H40: UC 9631 K2 | I40: TU2-R13 | J40: January | K40: ANNUAL | L40: Y | M40: Y | N40: Y | O40: Y | P40: Y | Q40: Y | R40: Y
A41: 1250 Wharf Street | B41: Servissio Property Services Ltd. | D41: 55 | E41: Victoria, BC | F41: 44167 | G41: ACTIVE | H41: TG 0521 K4 | I41: TH3-R21 | J41: January | K41: Y & ANNUAL | L41: Y | M41: Y | N41: Y | O41: X | P41: Y | Q41: Y
A42: 125 Croft Street | B42: Pacific Cove | D42: 60 | E42: Victoria, BC | F42: 45436 | G42: ACTIVE | H42: TC 521 | I42: W3-R20 | J42: January | K42: ANNUAL | L42: Y | M42: Y | N42: Y | O42: Y | P42: Y | Q42: Y
A43: 1236 Verdier Avenue | B43: Starlight/Devon | D43: 50 | E43: Brentwood Bay, BC | F43: 44949 | G43: ACTIVE | H43: 440 | I43: TU2-R12 | J43: January | K43: ANNUAL | L43: Y | M43: Y | N43: Y | O43: Y | P43: Y | Q43: Y | R43: Y | S43: Y
A44: 1230 Verdier Avenue | B44: Starlight/Devon | D44: 50 | E44: Brentwood Bay, BC | F44: 44949 | G44: ACTIVE | H44: 440 | I44: TU2-R12 | J44: January | K44: ANNUAL | L44: Y | M44: Y | N44: Y | O44: Y | P44: Y | Q44: Y | R44: Y | S44: Y
A45: 1216 Johnson Street | B45: Devon Properties | D45: 50 | E45: Victoria, BC | F45: 44949 | G45: ACTIVE | H45: 180 | I45: TH1-R8 | J45: January | K45: ANNUAL | L45: Y | M45: Y | N45: Y | O45: Y | P45: X | Q45: Y | R45: Y
A46: 1150 Queens Avenue | B46: Pacific Quorum | D46: 65 | E46: Victoria, BC | G46: ACTIVE | H46: 406 | I46: M1-R1 | J46: January | K46: Y | L46: ANNUAL | M46: Y | N46: Y | O46: Y | P46: Y | Q46: Y | R46: Y
A47: 1055 Hillside Avenue | B47: Firm Management | D47: 55 | E47: Victoria, BC | F47: 42689 | G47: ACTIVE | H47: LM 5501 | I47: W1-R6 | J47: January | K47: ANNUAL | L47: Y | M47: Y | N47: Y | O47: Y | P47: Y | Q47: Y | R47: Y

Sheet Annual Charts
B2: Row Labels | C2: Count of STATUS- (ACTIVE, CANCELLED, ON HOLD) | F2: STATUS- (ACTIVE, CANCELLED, ON HOLD) | G2: ACTIVE
B3: ACTIVE | C3: 583
B4: CANCELLED | C4: 19 | F4: Row Labels | G4: Count of ANNUAL
B5: ON HOLD | C5: 3 | F5: M1-R1 | G5: 31
B6: WAITING KEYS | C6: 6 | F6: M1-R2 | G6: 29
B7: (blank) | F7: M1-R3 | G7: 29
B8: Grand Total | C8: 611 | F8: TU1-R4 | G8: 27
F9: TU1-R5 | G9: 36
F10: W1-R6 | G10: 34
F11: W1-R7 | G11: 28
B12: STATUS- (ACTIVE, CANCELLED, ON HOLD) | C12: ACTIVE | F12: TH1-R8 | G12: 27
F13: TH1-R9 | G13: 30
B14: Row Labels | C14: Count of ANNUAL | F14: F1-R10 | G14: 28
B15: January | C15: 44 | D15: =GETPIVOTDATA("ANNUAL",$B$14,"ANNUAL","January")/GETPIVOTDATA("ANNUAL",$B$14) -> 0.075471698 | F15: M2-R11 | G15: 12
B16: February | C16: 40 | D16: =GETPIVOTDATA("ANNUAL",$B$14,"ANNUAL","February")/GETPIVOTDATA("ANNUAL",$B$14) -> 0.068610635 | F16: TU2-R12 | G16: 29
B17: March | C17: 62 | D17: =GETPIVOTDATA("ANNUAL",$B$14,"ANNUAL","March")/GETPIVOTDATA("ANNUAL",$B$14) -> 0.10634648 | F17: TU2-R13 | G17: 21
B18: April | C18: 44 | D18: =GETPIVOTDATA("ANNUAL",$B$14,"ANNUAL","April")/GETPIVOTDATA("ANNUAL",$B$14) -> 0.075471698 | F18: W2-R14 | G18: 32
B19: May | C19: 65 | D19: =GETPIVOTDATA("ANNUAL",$B$14,"ANNUAL","May")/GETPIVOTDATA("ANNUAL",$B$14) -> 0.11149228 | F19: TH2-R15 | G19: 29
B20: June | C20: 45 | D20: =GETPIVOTDATA("ANNUAL",$B$14,"ANNUAL","June")/GETPIVOTDATA("ANNUAL",$B$14) -> 0.077186964 | F20: F2-R16 | G20: 27
B21: July | C21: 63 | D21: =GETPIVOTDATA("ANNUAL",$B$14,"ANNUAL","July")/GETPIVOTDATA("ANNUAL",$B$14) -> 0.10806175 | F21: M3-R17 | G21: 13
B22: August | C22: 38 | D22: =GETPIVOTDATA("ANNUAL",$B$14,"ANNUAL","August")/GETPIVOTDATA("ANNUAL",$B$14) -> 0.065180103 | F22: TU3-R18 | G22: 27
B23: September | C23: 63 | D23: =GETPIVOTDATA("ANNUAL",$B$14,"ANNUAL","September")/GETPIVOTDATA("ANNUAL",$B$14) -> 0.10806175 | F23: TU3-R19 | G23: 23
B24: October | C24: 43 | D24: =GETPIVOTDATA("ANNUAL",$B$14,"ANNUAL","October")/GETPIVOTDATA("ANNUAL",$B$14) -> 0.073756432 | F24: W3-R20 | G24: 32
B25: November | C25: 44 | D25: =GETPIVOTDATA("ANNUAL",$B$14,"ANNUAL","November")/GETPIVOTDATA("ANNUAL",$B$14) -> 0.075471698 | F25: TH3-R21 | G25: 24
B26: December | C26: 30 | D26: =GETPIVOTDATA("ANNUAL",$B$14,"ANNUAL","December")/GETPIVOTDATA("ANNUAL",$B$14) -> 0.051457976 | F26: W2-R22 | G26: 15
C27: 1 | D27: =GETPIVOTDATA("ANNUAL",$B$14,"ANNUAL"," ")/GETPIVOTDATA("ANNUAL",$B$14) -> 0.0017152659 | F27: Grand Total | G27: 583
B28: T.O | C28: 1 | D28: =GETPIVOTDATA("ANNUAL",$B$14,"ANNUAL","T.O")/GETPIVOTDATA("ANNUAL",$B$14) -> 0.0017152659
B29: Grand Total | C29: 583

Sheet 2026 Completion Chart
A2: Cantec Monthlies - Completion Chart
A3: Route # | B3: # Of Sites | C3: Average Finish Time (3:30-4pm) | D3: Locked Routes | E3: Total # of Skipped (Per Route) | F3: January | I3: February | L3: March | O3: April | R3: May | U3: June | X3: July | AA3: August | AD3: September | AG3: October | AJ3: November | AM3: December
F4: Finish time | G4: Completed? | H4: # Skipped | I4: Finish time | J4: Completed? | K4: # Skipped | L4: Finish time | M4: Completed? | N4: # Skipped | O4: Finish time | P4: Completed? | Q4: # Skipped | R4: Finish time | S4: Completed? | T4: # Skipped | U4: Finish time | V4: Completed? | W4: # Skipped | X4: Finish time | Y4: Completed? | Z4: # Skipped | AA4: Finish time | AB4: Completed? | AC4: # Skipped | AD4: Finish time | AE4: Completed? | AF4: # Skipped | AG4: Finish time | AH4: Completed? | AI4: # Skipped | AJ4: Finish time | AK4: Completed? | AL4: # Skipped | AM4: Finish time | AN4: Completed? | AO4: # Skipped
A5: R1 | B5: =COUNTIF('Jan 2026 - Dec 2026'!J1:J743, "M1-R1") -> 34 | C5: =AVERAGE(F5,I5,L5,O5,R5,U5,X5,AA5,AD5) -> 0.65138889 | D5: Locked | E5: =SUM(H5,K5,N5,Q5,T5,W5,Z5,AC5,AF5,AI5,AL5,AO5) -> 12 | F5: 0.64652778 | G5: Y | H5: 3 | I5: 0.64861111 | J5: Y | K5: 2 | L5: 0.65625 | M5: Y | N5: 5 | O5: 0.65416667 | P5: Y | Q5: 2
A6: R2 | B6: =COUNTIF('Jan 2026 - Dec 2026'!J1:J744, "M1-R2") -> 31 | C6: =AVERAGE(F6,I6,L6,O6,R6,U6,X6,AA6,AD6,AG6,AJ6,PJ6) -> 0.63194444 | D6: Locked | E6: =SUM(H6,K6,N6,Q6,T6,W6,Z6,AC6,AF6,AI6,AL6,AO6) -> 18 | F6: 0.60277778 | G6: Y | H6: 3 | I6: 0.64583333 | J6: Y | K6: 2 | L6: 0.62152778 | M6: Y | N6: 7 | O6: 0.65763889 | P6: Y | Q6: 6
A7: R3 | B7: =COUNTIF('Jan 2026 - Dec 2026'!J1:J745, "M1-R3") -> 33 | C7: =AVERAGE(F7,I7,L7,O7,R7,U7,X7,AA7,AD7,AG7,AJ7,PJ7) -> 0.66284722 | D7: Locked | E7: =SUM(H7,K7,N7,Q7,T7,W7,Z7,AC7,AF7,AI7,AL7,AO7) -> 14 | F7: 0.67708333 | G7: Y | H7: 2 | I7: 0.67361111 | J7: Y | K7: 3 | L7: 0.66597222 | M7: Y | N7: 4 | O7: 0.63472222 | P7: Y | Q7: 5
A8: R4 | B8: =COUNTIF('Jan 2026 - Dec 2026'!J1:J746, "TU1-R4") -> 16 | C8: =AVERAGE(F8,I8,L8,O8,R8,U8,X8,AA8,AD8,AG8,AJ8,PJ8) -> 0.57309028 | E8: =SUM(H8,K8,N8,Q8,T8,W8,Z8,AC8,AF8,AI8,AL8,AO8) -> 4 | F8: 0.59930556 | G8: Y | H8: 1 | I8: 0.5625 | J8: Y | K8: 1 | L8: 0.52569444 | M8: Y | N8: 0 | O8: 0.60486111 | P8: Y | Q8: 2
A9: R5 | B9: =COUNTIF('Jan 2026 - Dec 2026'!J1:J731, "TU1-R5") -> 26 | C9: =AVERAGE(F9,I9,L9,O9,R9,U9,X9,AA9,AD9,AG9,AJ9,PJ9) -> 0.65763889 | E9: =SUM(H9,K9,N9,Q9,T9,W9,Z9,AC9,AF9,AI9,AL9,AO9) -> 1 | F9: 0.64930556 | G9: Y | H9: 0 | I9: 0.65138889 | J9: Y | K9: 0 | L9: 0.67013889 | M9: Y | N9: 1 | O9: 0.65972222 | P9: Y | Q9: 0
A10: R6 | B10: =COUNTIF('Jan 2026 - Dec 2026'!J1:J732, "W1-R6") -> 33 | C10: =AVERAGE(F10,I10,L10,O10,R10,U10,X10,AA10,AD10,AG10,AJ10,PJ10) -> 0.64704861 | D10: Locked | E10: =SUM(H10,K10,N10,Q10,T10,W10,Z10,AC10,AF10,AI10,AL10,AO10) -> 20 | F10: 0.65347222 | G10: Y | H10: 3 | I10: 0.62638889 | J10: Y | K10: 7 | L10: 0.63541667 | M10: Y | N10: 2 | O10: 0.67291667 | P10: X | Q10: 8
A11: R7 | B11: =COUNTIF('Jan 2026 - Dec 2026'!J2:J733, "w1-r7") -> 30 | C11: =AVERAGE(F11,I11,L11,O11,R11,U11,X11,AA11,AD11,AG11,AJ11,PJ11) -> 0.67708333 | D11: Locked | E11: =SUM(H11,K11,N11,Q11,T11,W11,Z11,AC11,AF11,AI11,AL11,AO11) -> 11 | F11: 0.67222222 | G11: Y | H11: 3 | I11: 0.70416667 | J11: Y | K11: 0 | L11: 0.65972222 | M11: Y | N11: 4 | O11: 0.67222222 | P11: Y | Q11: 4
A12: R8 | B12: =COUNTIF('Jan 2026 - Dec 2026'!J1:J734, "TH1-R8") -> 27 | C12: =AVERAGE(F12,I12,L12,O12,R12,U12,X12,AA12,AD12,AG12,AJ12,PJ12) -> 0.64444444 | D12: Locked | E12: =SUM(H12,K12,N12,Q12,T12,W12,Z12,AC12,AF12,AI12,AL12,AO12) -> 10 | F12: 0.65416667 | G12: Y | H12: 3 | I12: 0.66666667 | J12: Y | K12: 0 | L12: 0.59027778 | M12: Y | N12: 2 | O12: 0.66666667 | P12: X | Q12: 5
A13: R9 | B13: =COUNTIF('Jan 2026 - Dec 2026'!J1:J735, "TH1-R9") -> 32 | C13: =AVERAGE(F13,I13,L13,O13,R13,U13,X13,AA13,AD13,AG13,AJ13,PJ13) -> 0.67447917 | D13: Locked | E13: =SUM(H13,K13,N13,Q13,T13,W13,Z13,AC13,AF13,AI13,AL13,AO13) -> 9 | F13: 0.67361111 | G13: Y | H13: 2 | I13: 0.66111111 | J13: Y | K13: 2 | L13: 0.68263889 | M13: Y | N13: 0 | O13: 0.68055556 | P13: Y | Q13: 5
A14: R10 | B14: =COUNTIF('Jan 2026 - Dec 2026'!J1:J736, "F1-R10") -> 29 | C14: =AVERAGE(F14,I14,L14,O14,R14,U14,X14,AA14,AD14,AG14,AJ14,PJ14) -> 0.64392361 | E14: =SUM(H14,K14,N14,Q14,T14,W14,Z14,AC14,AF14,AI14,AL14,AO14) -> 15 | F14: 0.66944444 | G14: Y | H14: 2 | I14: 0.62152778 | J14: Y | K14: 5 | L14: 0.61111111 | M14: Y | N14: 4 | O14: 0.67361111 | P14: Y | Q14: 4
A15: R11 | B15: =COUNTIF('Jan 2026 - Dec 2026'!J1:J731, "M2-R11") -> 12 | C15: =AVERAGE(F15,I15,L15,O15,R15,U15,X15,AA15,AD15,AG15,AJ15,PJ15) -> 0.64114583 | D15: Locked | E15: =SUM(H15,K15,N15,Q15,T15,W15,Z15,AC15,AF15,AI15,AL15,AO15) -> 7 | F15: 0.65625 | G15: Y | H15: 1 | I15: 0.64236111 | J15: Y | K15: 1 | L15: 0.64236111 | M15: Y | N15: 3 | O15: 0.62361111 | P15: Y | Q15: 2
A16: R12 | B16: =COUNTIF('Jan 2026 - Dec 2026'!J1:J731, "TU2-R12") -> 30 | C16: =AVERAGE(F16,I16,L16,O16,R16,U16,X16,AA16,AD16,AG16,AJ16,PJ16) -> 0.65902778 | D16: Locked | E16: =SUM(H16,K16,N16,Q16,T16,W16,Z16,AC16,AF16,AI16,AL16,AO16) -> 13 | F16: 0.65347222 | G16: Y | H16: 3 | I16: 0.64513889 | J16: X | K16: 6 | L16: 0.67291667 | M16: Y | N16: 1 | O16: 0.66458333 | P16: Y | Q16: 3
A17: R13 | B17: =COUNTIF('Jan 2026 - Dec 2026'!J1:J731, "TU2-R13") -> 25 | C17: =AVERAGE(F17,I17,L17,O17,R17,U17,X17,AA17,AD17,AG17,AJ17,PJ17) -> 0.62523148 | D17: Locked | E17: =SUM(H17,K17,N17,Q17,T17,W17,Z17,AC17,AF17,AI17,AL17,AO17) -> 27 | F17: 0.62430556 | G17: Y | H17: 1 | I17: 0.64444444 | J17: Y | K17: 0 | L17: - | M17: X | N17: 22 | O17: 0.60694444 | P17: Y | Q17: 4
A18: R14 | B18: =COUNTIF('Jan 2026 - Dec 2026'!J1:J732, "W2-R14") -> 31 | C18: =AVERAGE(F18,I18,L18,O18,R18,U18,X18,AA18,AD18,AG18,AJ18,PJ18) -> 0.63923611 | D18: Locked | E18: =SUM(H18,K18,N18,Q18,T18,W18,Z18,AC18,AF18,AI18,AL18,AO18) -> 16 | F18: 0.65347222 | G18: Y | H18: 2 | I18: 0.64236111 | J18: Y | K18: 4 | L18: 0.64930556 | M18: Y | N18: 4 | O18: 0.61180556 | P18: Y | Q18: 6
A19: R15 | B19: =COUNTIF('Jan 2026 - Dec 2026'!J1:J733, "TH2-R15") -> 30 | C19: =AVERAGE(F19,I19,L19,O19,R19,U19,X19,AA19,AD19,AG19,AJ19,PJ19) -> 0.6265625 | D19: Locked | E19: =SUM(H19,K19,N19,Q19,T19,W19,Z19,AC19,AF19,AI19,AL19,AO19) -> 20 | F19: 0.62083333 | G19: Y | H19: 7 | I19: 0.63888889 | J19: Y | K19: 5 | L19: 0.62708333 | M19: Y | N19: 4 | O19: 0.61944444 | P19: Y | Q19: 4
A20: R16 | B20: =COUNTIF('Jan 2026 - Dec 2026'!J1:J734, "F2-R16") -> 26 | C20: =AVERAGE(F20,I20,L20,O20,R20,U20,X20,AA20,AD20,AG20,AJ20,PJ20) -> 0.6421875 | E20: =SUM(H20,K20,N20,Q20,T20,W20,Z20,AC20,AF20,AI20,AL20,AO20) -> 7 | F20: 0.65902778 | G20: Y | H20: 1 | I20: 0.625 | J20: Y | K20: 2 | L20: 0.63888889 | M20: Y | N20: 3 | O20: 0.64583333 | P20: Y | Q20: 1
A21: R17 | B21: =COUNTIF('Jan 2026 - Dec 2026'!J1:J731, "M3-R17") -> 11 | C21: =AVERAGE(F21,I21,L21,O21,R21,U21,X21,AA21,AD21,AG21,AJ21,PJ21) -> 0.62222222 | D21: Locked | E21: =SUM(H21,K21,N21,Q21,T21,W21,Z21,AC21,AF21,AI21,AL21,AO21) -> 9 | F21: 0.67222222 | G21: X | H21: 4 | I21: 0.60902778 | J21: Y | K21: 1 | L21: 0.55694444 | M21: Y | N21: 3 | O21: 0.65069444 | P21: Y | Q21: 1
A22: R18 | B22: =COUNTIF('Jan 2026 - Dec 2026'!J1:J732, "TU3-R18") -> 27 | C22: =AVERAGE(F22,I22,L22,O22,R22,U22,X22,AA22,AD22,AG22,AJ22,PJ22) -> 0.62256944 | E22: =SUM(H22,K22,N22,Q22,T22,W22,Z22,AC22,AF22,AI22,AL22,AO22) -> 8 | F22: 0.62569444 | G22: Y | H22: 2 | I22: 0.62916667 | J22: Y | K22: 2 | L22: 0.56875 | M22: Y | N22: 1 | O22: 0.66666667 | P22: Y | Q22: 3
A23: R19 | B23: =COUNTIF('Jan 2026 - Dec 2026'!J1:J733, "TU3-R19") -> 26 | C23: =AVERAGE(F23,I23,L23,O23,R23,U23,X23,AA23,AD23,AG23,AJ23,PJ23) -> 0.64930556 | E23: =SUM(H23,K23,N23,Q23,T23,W23,Z23,AC23,AF23,AI23,AL23,AO23) -> 6 | F23: 0.67291667 | G23: Y | H23: 2 | I23: 0.65486111 | J23: Y | K23: 1 | L23: 0.62986111 | M23: Y | N23: 2 | O23: 0.63958333 | P23: Y | Q23: 1
A24: R20 | B24: =COUNTIF('Jan 2026 - Dec 2026'!J1:J734, "W3-R20") -> 32 | C24: =AVERAGE(F24,I24,L24,O24,R24,U24,X24,AA24,AD24,AG24,AJ24,PJ24) -> 0.66574074 | D24: Locked | E24: =SUM(H24,K24,N24,Q24,T24,W24,Z24,AC24,AF24,AI24,AL24,AO24) -> 36 | F24: 0.66111111 | G24: Y | H24: 0 | I24: 0.65972222 | J24: Y | K24: 0 | L24: - | M24: X | N24: 31 | O24: 0.67638889 | P24: X | Q24: 5
A25: R21 | B25: =COUNTIF('Jan 2026 - Dec 2026'!J1:J735, "TH3-R21") -> 25 | C25: =AVERAGE(F25,I25,L25,O25,R25,U25,X25,AA25,AD25,AG25,AJ25,PJ25) -> 0.66059028 | E25: =SUM(H25,K25,N25,Q25,T25,W25,Z25,AC25,AF25,AI25,AL25,AO25) -> 14 | F25: 0.64583333 | G25: Y | H25: 6 | I25: 0.66458333 | J25: Y | K25: 2 | L25: 0.65416667 | M25: Y | N25: 2 | O25: 0.67777778 | P25: Y | Q25: 4
A26: R22 | B26: =COUNTIF('Jan 2026 - Dec 2026'!J1:J736, "W2-R22") -> 32 | C26: =AVERAGE(F26,I26,L26,O26,R26,U26,X26,AA26,AD26,AG26,AJ26,PJ26) -> 0.66527778 | D26: Locked | E26: =SUM(H26,K26,N26,Q26,T26,W26,Z26,AC26,AF26,AI26,AL26,AO26) -> 13 | F26: 0.67152778 | G26: Y | H26: 2 | I26: 0.67986111 | J26: X | K26: 6 | L26: 0.66388889 | M26: Y | N26: 3 | O26: 0.64583333 | P26: Y | Q26: 2
A27: R23 | B27: =COUNTIF('Jan 2026 - Dec 2026'!J1:J737, "TH2-R23") -> 20 | C27: =AVERAGE(F27,I27,L27,O27,R27,U27,X27,AA27,AD27,AG27,AJ27,PJ27) -> 0.62256944 | D27: Locked | E27: =SUM(H27,K27,N27,Q27,T27,W27,Z27,AC27,AF27,AI27,AL27,AO27) -> 8 | F27: 0.53125 | G27: Y | H27: 2 | I27: 0.66180556 | J27: Y | K27: 3 | L27: 0.63194444 | M27: Y | N27: 2 | O27: 0.66527778 | P27: Y | Q27: 1
A28: R24 | B28: =COUNTIF('Jan 2026 - Dec 2026'!J1:J738, "F1-R24") -> 14 | C28: =AVERAGE(F28,I28,L28,O28,R28,U28,X28,AA28,AD28,AG28,AJ28,PJ28) -> 0.53819444 | E28: =SUM(H28,K28,N28,Q28,T28,W28,Z28,AC28,AF28,AI28,AL28,AO28) -> 4 | F28: - | G28: - | H28: - | I28: 0.65277778 | J28: Y | K28: 0 | L28: 0.47222222 | M28: Y | N28: 3 | O28: 0.48958333 | P28: Y | Q28: 1
A29: Total sites | B29: =SUM(B3:B28) -> 632 | D29: Total Skipped | E29: =SUM(E5:E27) -> 298
A30: Total skipped (Total Per Month) | F30: January | H30: =SUM(H5:H28) -> 55 | I30: February | K30: =SUM(K5:K28) -> 55 | L30: March | N30: =SUM(N5:N28) -> 113 | O30: April | Q30: =SUM(Q5:Q28) -> 79 | R30: May | T30: - | U30: June | W30: - | X30: July | Z30: - | AA30: August | AC30: - | AD30: September | AF30: - | AG30: October | AI30: - | AJ30: November | AL30: - | AM30: December | AO30: - | AP30: Average 2026 | AQ30: =H30 -> 55
A31: Skipped Per Lack of Time | F31: January | H31: 3 | I31: February | K31: =6+3 -> 9 | L31: March | N31: 0 | O31: April | Q31: =5+2+2 -> 9 | R31: May | T31: - | U31: June | W31: - | X31: July | Z31: - | AA31: August | AC31: - | AD31: September | AF31: - | AG31: October | AI31: - | AJ31: November | AL31: - | AM31: December | AO31: - | AP31: Average 2026 | AQ31: =H31 -> 3
A32: Skipped Per Annuals | F32: January | H32: 38 | I32: February | K32: 34 | L32: March | N32: 52 | O32: April | Q32: 57 | R32: May | T32: - | U32: June | W32: - | X32: July | Z32: - | AA32: August | AC32: - | AD32: September | AF32: - | AG32: October | AI32: - | AJ32: November | AL32: - | AM32: December | AO32: - | AP32: Average 2026 | AQ32: =H32 -> 38
A33: Skipped but Billed for Our Time | F33: January | H33: 3 | I33: February | K33: 0 | L33: March | N33: 2 | O33: April | Q33: 2 | R33: May | T33: - | U33: June | W33: - | X33: July | Z33: - | AA33: August | AC33: - | AD33: September | AF33: - | AG33: October | AI33: - | AJ33: November | AL33: - | AM33: December | AO33: - | AP33: Average 2026 | AQ33: =H33 -> 3
A34: Skipped Per Other Reason | F34: January | H34: 11 | I34: February | K34: 12 | L34: March | N34: =12+49 -> 61 | O34: April | Q34: 13 | R34: May | T34: - | U34: June | W34: - | X34: July | Z34: - | AA34: August | AC34: - | AD34: September | AF34: - | AG34: October | AI34: - | AJ34: November | AL34: - | AM34: December | AO34: - | AP34: Average 2026 | AQ34: =H34 -> 11
B38: Average Finish Time Target: Between 3:30PM - 4:00PM

Sheet X-Keys
A1: ADDRESS | B1: PROPERTY MANAGEMENT COMPANY | C1: NOTES | D1: BARCODE # | E1: STATUS- (ACTIVE, CANCELLED, ON HOLD) | F1: KEYS | G1: This sheet is for updating the database the powers the key page. Please add any new route bags and or x-keys and they will be updated as per the scheduled program on Jamies PC. For new route bags, simply ensure the the KEYS code is in the format "R" + "<Number>" and the system will recognize it as a monthly key bag.
A2: Route 1 | B2: Cantec Fire Alarms | C2: Monthly Key Bag | E2: ACTIVE | F2: R1
A3: Route 2 | B3: Cantec Fire Alarms | C3: Monthly Key Bag | E3: ACTIVE | F3: R2
A4: Route 3 | B4: Cantec Fire Alarms | C4: Monthly Key Bag | E4: ACTIVE | F4: R3
A5: Route 4 | B5: Cantec Fire Alarms | C5: Monthly Key Bag | E5: ACTIVE | F5: R4
A6: Route 5 | B6: Cantec Fire Alarms | C6: Monthly Key Bag | E6: ACTIVE | F6: R5
A7: Route 6 | B7: Cantec Fire Alarms | C7: Monthly Key Bag | E7: ACTIVE | F7: R6
A8: Route 7 | B8: Cantec Fire Alarms | C8: Monthly Key Bag | E8: ACTIVE | F8: R7
A9: Route 8 | B9: Cantec Fire Alarms | C9: Monthly Key Bag | E9: ACTIVE | F9: R8
A10: Route 9 | B10: Cantec Fire Alarms | C10: Monthly Key Bag | E10: ACTIVE | F10: R9
A11: Route 10 | B11: Cantec Fire Alarms | C11: Monthly Key Bag | E11: ACTIVE | F11: R10
A12: Route 11 | B12: Cantec Fire Alarms | C12: Monthly Key Bag | E12: ACTIVE | F12: R11
A13: Route 12 | B13: Cantec Fire Alarms | C13: Monthly Key Bag | E13: ACTIVE | F13: R12
... A25: Route 24 | B25: Cantec Fire Alarms | C25: Monthly Key Bag | E25: ACTIVE | F25: R24

Sheet 2026 Revenue Report
B3: Weekday | C3: Monthly Route # | D3: Route name /service area | E3: Buildings /route | F3: Average hours required to complete | G3: Techs required | H3: Monthly Route Expenses (Avg labour cost $45/hr) + (Truck charge $25/month) | I3: Monthly Route Revenue | J3: Monthly Net | K3: Monthly Net % | L3: Notes | M3: Route Locked (route is full - no new buildings can be added) | O3: MBT PRICING
B4: 1st Monday | C4: Route #1 | D4: Pac Pro 1 | E4: =COUNTIF('Jan 2026 - Dec 2026'!J1:J743, "M1-R1") -> 34 | F4: =MAX(0, (MIN('2026 Completion Chart'!C5, TIME(16,30,0)) - TIME(8,0,0)) * 24 - IF('2026 Completion Chart'!C5 >= TIME(12,0,0), 0.5, 0) ) -> 7.1333333 | G4: 1 | H4: =F4*G4*45+(25) -> 346 | I4: =SUMIF('Jan 2026 - Dec 2026'!$J$2:$J$993, "M1-R1", 'Jan 2026 - Dec 2026'!$E$2:$E$993) -> 2050 | J4: =(I4-H4) -> 1704 | K4: =(J4/I4) -> 0.83121951 | L4: Pac pro route - 1 technician | M4: Locked | O4: Devon Properties | P4: ='[1]Quotation Cheat Sheet'!$G$61 -> 65
B5: 1st Monday | C5: Route #2 | D5: Pac Pro 2 | E5: =COUNTIF('Jan 2026 - Dec 2026'!J1:J743, "M1-R2") -> 31 | F5: =MAX(0, (MIN('2026 Completion Chart'!C6, TIME(16,30,0)) - TIME(8,0,0)) * 24 - IF('2026 Completion Chart'!C6 >= TIME(12,0,0), 0.5, 0) ) -> 6.6666667 | G5: 1 | H5: =F5*G5*45+(25) -> 325 | I5: =SUMIF('Jan 2026 - Dec 2026'!$J$2:$J$993, "M1-R2", 'Jan 2026 - Dec 2026'!$E$2:$E$993) -> 1790 | J5: =(I5-H5) -> 1465 | K5: =(J5/I5) -> 0.81843575 | L5: Pac pro route - 1 technician | M5: Locked | O5: Typical | P5: ='[1]Quotation Cheat Sheet'!$G$62 -> 75
B6: 1st Monday | C6: Route #3 | D6: Fernwood | E6: =COUNTIF('Jan 2026 - Dec 2026'!J1:J743, "M1-R3") -> 33 | F6: =MAX(0, (MIN('2026 Completion Chart'!C7, TIME(16,30,0)) - TIME(8,0,0)) * 24 - IF('2026 Completion Chart'!C7 >= TIME(12,0,0), 0.5, 0) ) -> 7.4083333 | G6: 2 | H6: =F6*G6*45+(25) -> 691.75 | I6: =SUMIF('Jan 2026 - Dec 2026'!$J$2:$J$993, "M1-R3", 'Jan 2026 - Dec 2026'!$E$2:$E$993) -> 1995 | J6: =(I6-H6) -> 1303.25 | K6: =(J6/I6) -> 0.65325815 | M6: Locked | O6: High Rise | P6: ='[1]Quotation Cheat Sheet'!$G$63 -> 125
B7: 1st Tuesday | C7: Route #4 | D7: Saanich | E7: =COUNTIF('Jan 2026 - Dec 2026'!J1:J743, "TU1-R4") -> 16 | F7: =MAX(0, (MIN('2026 Completion Chart'!C8, TIME(16,30,0)) - TIME(8,0,0)) * 24 - IF('2026 Completion Chart'!C8 >= TIME(12,0,0), 0.5, 0) ) -> 5.2541667 | G7: 2 | H7: =F7*G7*45+(25) -> 497.875 | I7: =SUMIF('Jan 2026 - Dec 2026'!$J$2:$J$993, "TU1-R4", 'Jan 2026 - Dec 2026'!$E$2:$E$993) -> 935 | J7: =(I7-H7) -> 437.125 | K7: =(J7/I7) -> 0.46751337 | O7: Monthly Training | P7: ='[1]Quotation Cheat Sheet'!$G$64 -> 250
B8: 1st Tuesday | C8: Route #5 | D8: Westshore | E8: =COUNTIF('Jan 2026 - Dec 2026'!J1:J743, "TU1-R5") -> 26 | F8: =MAX(0, (MIN('2026 Completion Chart'!C9, TIME(16,30,0)) - TIME(8,0,0)) * 24 - IF('2026 Completion Chart'!C9 >= TIME(12,0,0), 0.5, 0) ) -> 7.2833333 | G8: 2 | H8: =F8*G8*45+(25) -> 680.5 | I8: =SUMIF('Jan 2026 - Dec 2026'!$J$2:$J$993, "TU1-R5", 'Jan 2026 - Dec 2026'!$E$2:$E$993) -> 1690 | J8: =(I8-H8) -> 1009.5 | K8: =(J8/I8) -> 0.59733728 | O8: Avg price per building | P8: =I29/E29 -> 64.952532
B9: 1st Wednesday | C9: Route #6 | D9: Hillside | E9: =COUNTIF('Jan 2026 - Dec 2026'!J1:J743, "W1-R6") -> 33 | F9: =MAX(0, (MIN('2026 Completion Chart'!C10, TIME(16,30,0)) - TIME(8,0,0)) * 24 - IF('2026 Completion Chart'!C10 >= TIME(12,0,0), 0.5, 0) ) -> 7.0291667 | G9: 2 | H9: =F9*G9*45+(25) -> 657.625 | I9: =SUMIF('Jan 2026 - Dec 2026'!$J$2:$J$993, "W1-R6", 'Jan 2026 - Dec 2026'!$E$2:$E$993) -> 2075 | J9: =(I9-H9) -> 1417.375 | K9: =(J9/I9) -> 0.68307229 | M9: Locked
B10: 1st Wednesday | C10: Route #7 | D10: Esquimalt | E10: =COUNTIF('Jan 2026 - Dec 2026'!J1:J743, "W1-R7") -> 30 | F10: =MAX(0, (MIN('2026 Completion Chart'!C11, TIME(16,30,0)) - TIME(8,0,0)) * 24 - IF('2026 Completion Chart'!C11 >= TIME(12,0,0), 0.5, 0) ) -> 7.75 | G10: 2 | H10: =F10*G10*45+(25) -> 722.5 | I10: =SUMIF('Jan 2026 - Dec 2026'!$J$2:$J$993, "W1-R7", 'Jan 2026 - Dec 2026'!$E$2:$E$993) -> 1770 | J10: =(I10-H10) -> 1047.5 | K10: =(J10/I10) -> 0.59180791 | M10: Locked
B11: 1st Thursday | C11: Route #8 | D11: Downtown 1 | E11: =COUNTIF('Jan 2026 - Dec 2026'!J1:J743, "TH1-R8") -> 27 | F11: =MAX(0, (MIN('2026 Completion Chart'!C12, TIME(16,30,0)) - TIME(8,0,0)) * 24 - IF('2026 Completion Chart'!C12 >= TIME(12,0,0), 0.5, 0) ) -> 6.9666667 | G11: 2 | H11: =F11*G11*45+(25) -> 652 | I11: =SUMIF('Jan 2026 - Dec 2026'!$J$2:$J$993, "TH1-R8", 'Jan 2026 - Dec 2026'!$E$2:$E$993) -> 1640 | J11: =(I11-H11) -> 988 | K11: =(J11/I11) -> 0.60243902 | M11: Locked
B12: 1st Thursday | C12: Route #9 | D12: Downtown 2 | E12: =COUNTIF('Jan 2026 - Dec 2026'!J1:J743, "TH1-R9") -> 32 | F12: =MAX(0, (MIN('2026 Completion Chart'!C13, TIME(16,30,0)) - TIME(8,0,0)) * 24 - IF('2026 Completion Chart'!C13 >= TIME(12,0,0), 0.5, 0) ) -> 7.6875 | G12: 2 | H12: =F12*G12*45+(25) -> 716.875 | I12: =SUMIF('Jan 2026 - Dec 2026'!$J$2:$J$993, "TH1-R9", 'Jan 2026 - Dec 2026'!$E$2:$E$993) -> 1820 | J12: =(I12-H12) -> 1103.125 | K12: =(J12/I12) -> 0.60611264 | M12: Locked
B13: 1st Friday | C13: Route #10 | D13: Sidney 1 | E13: =COUNTIF('Jan 2026 - Dec 2026'!J1:J743, "F1-R10") -> 29 | F13: =MAX(0, (MIN('2026 Completion Chart'!C14, TIME(16,30,0)) - TIME(8,0,0)) * 24 - IF('2026 Completion Chart'!C14 >= TIME(12,0,0), 0.5, 0) ) -> 6.9541667 | G13: 2 | H13: =F13*G13*45+(25) -> 650.875 | I13: =SUMIF('Jan 2026 - Dec 2026'!$J$2:$J$993, "F1-R10", 'Jan 2026 - Dec 2026'!$E$2:$E$993) -> 1660 | J13: =(I13-H13) -> 1009.125 | K13: =(J13/I13) -> 0.60790663
B14: 2nd Monday | C14: Route #11 | D14: Thrifty's 1 | E14: =COUNTIF('Jan 2026 - Dec 2026'!J1:J743, "M2-R11") -> 12 | F14: =MAX(0, (MIN('2026 Completion Chart'!C15, TIME(16,30,0)) - TIME(8,0,0)) * 24 - IF('2026 Completion Chart'!C15 >= TIME(12,0,0), 0.5, 0) ) -> 6.8875 | G14: 2 | H14: =F14*G14*45+(25) -> 644.875 | I14: =SUMIF('Jan 2026 - Dec 2026'!$J$2:$J$993, "M2-R11", 'Jan 2026 - Dec 2026'!$E$2:$E$993) -> 1400 | J14: =(I14-H14) -> 755.125 | K14: =(J14/I14) -> 0.539375 | L14: Thrifty's (Mill Bay) | M14: Locked
B15: 2nd Tuesday | C15: Route #12 | D15: Central Saanich | E15: =COUNTIF('Jan 2026 - Dec 2026'!J1:J743, "TU2-R12") -> 30 | F15: =MAX(0, (MIN('2026 Completion Chart'!C16, TIME(16,30,0)) - TIME(8,0,0)) * 24 - IF('2026 Completion Chart'!C16 >= TIME(12,0,0), 0.5, 0) ) -> 7.3166667 | G15: 2 | H15: =F15*G15*45+(25) -> 683.5 | I15: =SUMIF('Jan 2026 - Dec 2026'!$J$2:$J$993, "TU2-R12", 'Jan 2026 - Dec 2026'!$E$2:$E$993) -> 1820 | J15: =(I15-H15) -> 1136.5 | K15: =(J15/I15) -> 0.62445055 | M15: Locked
B16: 2nd Tuesday | C16: Route #13 | D16: Uplands | E16: =COUNTIF('Jan 2026 - Dec 2026'!J1:J743, "TU2-R13") -> 25 | F16: =MAX(0, (MIN('2026 Completion Chart'!C17, TIME(16,30,0)) - TIME(8,0,0)) * 24 - IF('2026 Completion Chart'!C17 >= TIME(12,0,0), 0.5, 0) ) -> 6.5055556 | G16: 2 | H16: =F16*G16*45+(25) -> 610.5 | I16: =SUMIF('Jan 2026 - Dec 2026'!$J$2:$J$993, "TU2-R13", 'Jan 2026 - Dec 2026'!$E$2:$E$993) -> 1510 | J16: =(I16-H16) -> 899.5 | K16: =(J16/I16) -> 0.59569536 | L16: 6 hour route
B17: 2nd Wednesday | C17: Route #14 | D17: Oak Bay | E17: =COUNTIF('Jan 2026 - Dec 2026'!J1:J743, "W2-R14") -> 31 | F17: =MAX(0, (MIN('2026 Completion Chart'!C18, TIME(16,30,0)) - TIME(8,0,0)) * 24 - IF('2026 Completion Chart'!C18 >= TIME(12,0,0), 0.5, 0) ) -> 6.8416667 | G17: 2 | H17: =F17*G17*45+(25) -> 640.75 | I17: =SUMIF('Jan 2026 - Dec 2026'!$J$2:$J$993, "W2-R14", 'Jan 2026 - Dec 2026'!$E$2:$E$993) -> 1690 | J17: =(I17-H17) -> 1049.25 | K17: =(J17/I17) -> 0.62085799 | M17: Locked
B18: 2nd Thursday | C18: Route #15 | D18: Downtown 3 | E18: =COUNTIF('Jan 2026 - Dec 2026'!J1:J743, "TH2-R15") -> 30 | F18: =MAX(0, (MIN('2026 Completion Chart'!C19, TIME(16,30,0)) - TIME(8,0,0)) * 24 - IF('2026 Completion Chart'!C19 >= TIME(12,0,0), 0.5, 0) ) -> 6.5375 | G18: 2 | H18: =F18*G18*45+(25) -> 613.375 | I18: =SUMIF('Jan 2026 - Dec 2026'!$J$2:$J$993, "TH2-R15", 'Jan 2026 - Dec 2026'!$E$2:$E$993) -> 1745 | J18: =(I18-H18) -> 1131.625 | K18: =(J18/I18) -> 0.6484957 | L18: Early route (7am start) | M18: Locked
B19: 2nd Friday | C19: Route #16 | D19: Sidney 2 | E19: =COUNTIF('Jan 2026 - Dec 2026'!J1:J743, "F2-R16") -> 26 | F19: =MAX(0, (MIN('2026 Completion Chart'!C20, TIME(16,30,0)) - TIME(8,0,0)) * 24 - IF('2026 Completion Chart'!C20 >= TIME(12,0,0), 0.5, 0) ) -> 6.9125 | G19: 2 | H19: =F19*G19*45+(25) -> 647.125 | I19: =SUMIF('Jan 2026 - Dec 2026'!$J$2:$J$993, "F2-R16", 'Jan 2026 - Dec 2026'!$E$2:$E$993) -> 1510 | J19: =(I19-H19) -> 862.875 | K19: =(J19/I19) -> 0.5714404
B20: 3rd Monday | C20: Route #17 | D20: Thrifty's 2 | E20: =COUNTIF('Jan 2026 - Dec 2026'!J1:J743, "M3-R17") -> 11 | F20: =MAX(0, (MIN('2026 Completion Chart'!C21, TIME(16,30,0)) - TIME(8,0,0)) * 24 - IF('2026 Completion Chart'!C21 >= TIME(12,0,0), 0.5, 0) ) -> 6.4333333 | G20: 2 | H20: =F20*G20*45+(25) -> 604 | I20: =SUMIF('Jan 2026 - Dec 2026'!$J$2:$J$993, "M3-R17", 'Jan 2026 - Dec 2026'!$E$2:$E$993) -> 2380 | J20: =(I20-H20) -> 1776 | K20: =(J20/I20) -> 0.74621849 | M20: Locked
B21: 3rd Tuesday | C21: Route #18 | D21: Beacon Hill | E21: =COUNTIF('Jan 2026 - Dec 2026'!J1:J743, "TU3-R18") -> 27 | F21: =MAX(0, (MIN('2026 Completion Chart'!C22, TIME(16,30,0)) - TIME(8,0,0)) * 24 - IF('2026 Completion Chart'!C22 >= TIME(12,0,0), 0.5, 0) ) -> 6.4416667 | G21: 2 | H21: =F21*G21*45+(25) -> 604.75 | I21: =SUMIF('Jan 2026 - Dec 2026'!$J$2:$J$993, "TU3-R18", 'Jan 2026 - Dec 2026'!$E$2:$E$993) -> 1485 | J21: =(I21-H21) -> 880.25 | K21: =(J21/I21) -> 0.59276094 | L21: 6 hour route
B22: 3rd Tuesday | C22: Route #19 | D22: Mayfair | E22: =COUNTIF('Jan 2026 - Dec 2026'!J1:J743, "TU3-R19") -> 26 | F22: =MAX(0, (MIN('2026 Completion Chart'!C23, TIME(16,30,0)) - TIME(8,0,0)) * 24 - IF('2026 Completion Chart'!C23 >= TIME(12,0,0), 0.5, 0) ) -> 7.0833333 | G22: 2 | H22: =F22*G22*45+(25) -> 662.5 | I22: =SUMIF('Jan 2026 - Dec 2026'!$J$2:$J$993, "TU3-R19", 'Jan 2026 - Dec 2026'!$E$2:$E$993) -> 1475 | J22: =(I22-H22) -> 812.5 | K22: =(J22/I22) -> 0.55084746
B23: 3rd Wednesday | C23: Route #20 | D23: James Bay | E23: =COUNTIF('Jan 2026 - Dec 2026'!J1:J743, "W3-R20") -> 32 | F23: =MAX(0, (MIN('2026 Completion Chart'!C24, TIME(16,30,0)) - TIME(8,0,0)) * 24 - IF('2026 Completion Chart'!C24 >= TIME(12,0,0), 0.5, 0) ) -> 7.4777778 | G23: 2 | H23: =F23*G23*45+(25) -> 698 | I23: =SUMIF('Jan 2026 - Dec 2026'!$J$2:$J$993, "W3-R20", 'Jan 2026 - Dec 2026'!$E$2:$E$993) -> 1975 | J23: =(I23-H23) -> 1277 | K23: =(J23/I23) -> 0.64658228 | M23: Locked
B24: 3rd Thursday | C24: Route #21 | D24: Downtown 4 | E24: =COUNTIF('Jan 2026 - Dec 2026'!J1:J743, "TH3-R21") -> 25 | F24: =MAX(0, (MIN('2026 Completion Chart'!C25, TIME(16,30,0)) - TIME(8,0,0)) * 24 - IF('2026 Completion Chart'!C25 >= TIME(12,0,0), 0.5, 0) ) -> 7.3541667 | G24: 2 | H24: =F24*G24*45+(25) -> 686.875 | I24: =SUMIF('Jan 2026 - Dec 2026'!$J$2:$J$993, "TH3-R21", 'Jan 2026 - Dec 2026'!$E$2:$E$993) -> 1485 | J24: =(I24-H24) -> 798.125 | K24: =(J24/I24) -> 0.53745791
B25: 2nd Wednesday | C25: Route #22 | D25: Gorge | E25: =COUNTIF('Jan 2026 - Dec 2026'!J1:J743, "W2-R22") -> 32 | F25: =MAX(0, (MIN('2026 Completion Chart'!C26, TIME(16,30,0)) - TIME(8,0,0)) * 24 - IF('2026 Completion Chart'!C26 >= TIME(12,0,0), 0.5, 0) ) -> 7.4666667 | G25: 2 | H25: =F25*G25*45+(25) -> 697 | I25: =SUMIF('Jan 2026 - Dec 2026'!$J$2:$J$993, "W2-R22", 'Jan 2026 - Dec 2026'!$E$2:$E$993) -> 2010 | J25: =(I25-H25) -> 1313 | K25: =(J25/I25) -> 0.65323383 | L25: 5 hour route | M25: Locked
B26: 2nd Thursday | C26: Route #23 | D26: UVIC | E26: =COUNTIF('Jan 2026 - Dec 2026'!J1:J743, "TH2-R23") -> 20 | F26: =MAX(0, (MIN('2026 Completion Chart'!C27, TIME(16,30,0)) - TIME(8,0,0)) * 24 - IF('2026 Completion Chart'!C27 >= TIME(12,0,0), 0.5, 0) ) -> 6.4416667 | G26: 2 | H26: =F26*G26*45+(25) -> 604.75 | I26: =SUMIF('Jan 2026 - Dec 2026'!$J$2:$J$993, "TH2-R23", 'Jan 2026 - Dec 2026'!$E$2:$E$993) -> 1570 | J26: =(I26-H26) -> 965.25 | K26: =(J26/I26) -> 0.61480892 | L26: 4 hour route | M26: Locked
B27: 1st Friday | C27: Route #24 | D27: Langford 2 | E27: =COUNTIF('Jan 2026 - Dec 2026'!J2:J744, "F1-R24") -> 14 | F27: =MAX(0, (MIN('2026 Completion Chart'!C28, TIME(16,30,0)) - TIME(8,0,0)) * 24 - IF('2026 Completion Chart'!C28 >= TIME(12,0,0), 0.5, 0) ) -> 4.4166667 | G27: 2 | H27: =F27*G27*45+(25) -> 422.5 | I27: =SUMIF('Jan 2026 - Dec 2026'!$J$2:$J$993, "TH2-R23", 'Jan 2026 - Dec 2026'!$E$2:$E$993) -> 1570 | J27: =(I27-H27) -> 1147.5 | K27: =(J27/I27) -> 0.73089172 | L27: Not active in 2025 - new in 2026
D29: TOTAL (Monthly) | E29: =SUM(E4:E27) -> 632 | H29: =SUM(H4:H27) -> 14761.5 | I29: =SUM(I4:I27) -> 41050 | J29: =(I29-H29) -> 26288.5 | K29: =AVERAGE(K4:K27) -> 0.63050913
H31: Total costs | I31: Total Revenue | J31: Total Net
D32: TOTAL (Annually) | H32: =(H29*12) -> 177138 | I32: =(I29*11) -> 451550 | J32: =(J29*11) -> 289173.5
D34: Total buildings skipped | E34: ='2026 Completion Chart'!E29 -> 298 | I34: Total Revenue | J34: Total Net | K34: Margin
D35: Required "annual" skips | E35: ='2026 Completion Chart'!B29 -> 632 | H35: Adjusted | I35: =I32-E37 -> 473244.15 | J35: =I35-H32 -> 296106.15 | K35: =J35/I35 -> 0.62569426
D36: Unplanned skips | E36: =E34-E35 -> -334 | H36: (adjusted for unplanned Skips)
D37: Missed revenue due to unplanned skips (using average MBT price) | E37: =P8*E36 -> -21694.146
C40: Notes | D40: Monthly buildings are serviced on an 11 month schedule. The 12th month is when the annual inspection takes place. The annual numbers reflect this adjustment.
D41: Route labour costs are calculated with Cantec's average labour cost + weight ($45/hr). There is a truck charge added to each route's monthly expenses ($25).
D42: Numbers above are not a 100% accurate representation of MBT financials, but an estimate

Sheet Jan 2025 - Dec 2025
A1: ADDRESS | B1: PROPERTY MANAGEMENT COMPANY | C1: NOTES | D1: BARCODE # | E1: Price/month | F1: Area | G1: start up date | H1: STATUS- (ACTIVE, CANCELLED, ON HOLD) | I1: KEYS | J1: TEST DAY | K1: ANNUAL | L1: 45658 | M1: 45689 | N1: 45717 | O1: 45748 | P1: 45778 | Q1: 45809 | R1: 45839 | S1: 45870 | T1: 45901 | U1: 45931 | V1: 45962 | W1: 45992
A2: #103-4475 Viewmont | B2: Hansbraun | C2: MONTHLY EXT & ELU TESTS - Cancelled in November 2025 | E2: 75 | F2: Saanich, BC | G2: 45559 | H2: CANCELLED | I2: NONE | J2: - | K2: May | L2: Y | M2: Y | N2: Y | O2: Y | P2: ANNUAL | Q2: Y | R2: Y | S2: Y | T2: Y | U2: Y | V2: X | W2: -
A3: 10 Paul Kane/11 Cooperage Place | B3: Proline | E3: 55 | F3: Esquimalt, BC | G3: 41730 | H3: ACTIVE | I3: UV 01 | J3: W1-R7 | K3: May | L3: Y | M3: X | N3: Y | O3: Y | P3: ANNUAL | Q3: X | R3: Y | S3: Y | T3: Y | U3: Y | V3: Y | W3: X
A4: 1000 Mckenzie Avenue | B4: Starlight/Devon | E4: 55 | F4: Saanich, BC | G4: 45559 | H4: ACTIVE | I4: M 0001 | J4: W1-R6 | K4: May | L4: Y | M4: Y | N4: Y | O4: Y | P4: Y | Q4: ANNUAL | R4: X | S4: X | T4: Y | U4: Y | V4: Y | W4: Y
A5: 1000-1012 Douglas Street | B5: Itziar Management Ltd. (0824606 BC Ltd.) | E5: 60 | F5: Victoria, BC | G5: 45589 | H5: ACTIVE | I5: D 2101 | J5: TH2-R15 | K5: June | L5: Y | M5: Y | N5: Y | O5: Y | P5: Y | Q5: Y | R5: Y | S5: Y | T5: Y | U5: Y | V5: Y | W5: Y
A6: 1001 Wharf Street | B6: Pastoral Developments Ltd. | E6: 55 | F6: Victoria, BC | G6: 43313 | H6: ACTIVE | I6: NA 1001 K2-F1 | J6: TH2-R15 | K6: October | L6: Y | M6: Y | N6: Y | O6: Y | P6: Y | Q6: Y | R6: Y | S6: Y | T6: ANNUAL | U6: Y | V6: Y | W6: Y
A7: 10016 3rd Street | B7: Cornerstone | E7: 50 | F7: Sidney, BC | G7: 44949 | H7: ACTIVE | I7: 358 | J7: F2-R16 | K7: February | L7: Y | M7: Y | N7: ANNUAL | O7: Y | P7: Y | Q7: Y | R7: Y | S7: Y | T7: Y | U7: Y | V7: Y | W7: Y
A8: 10017 Avenger Way | B8: Lumberworld Operations Ltd. | E8: 75 | F8: Sidney, BC | G8: 45863 | H8: ACTIVE | I8: VG 71001 | J8: F2-R16 | K8: October | L8: - | M8: - | N8: - | O8: - | P8: - | Q8: - | R8: X | S8: Y | T8: Y | U8: ANNUAL | V8: Y | W8: Y
A9: 1002 Mckenzie Avenue | B9: Starlight/Devon | E9: 55 | F9: Saanich, BC | G9: 45559 | H9: ACTIVE | I9: M 0001 | J9: W1-R6 | K9: May | L9: Y | M9: Y | N9: Y | O9: Y | P9: Y | Q9: ANNUAL | R9: X | S9: Y | T9: Y | U9: Y | V9: Y | W9: Y
A10: 1002 Pakington | B10: Proline | E10: 50 | F10: Victoria, BC | G10: 44949 | H10: ACTIVE | I10: 146 | J10: TU3-R18 | K10: September | L10: Y | M10: Y | N10: Y | O10: Y | P10: Y | Q10: Y | R10: Y | S10: Y | T10: ANNUAL | U10: Y | V10: Y | W10: Y
A11: 1002 Wharf Street | B11: Malahat Properties | E11: 55 | F11: Victoria, BC | G11: 44174 | H11: ACTIVE | I11: At Reception | J11: TH2-R15 | K11: January | L11: Y | M11: ANNUAL | N11: Y | O11: Y | P11: Y | Q11: Y | R11: Y | S11: Y | T11: Y | U11: Y | V11: Y | W11: Y
A12: 10025 Resthaven Drive | B12: Inken Roller c/o Richmond Property Group | E12: 50 | F12: Sidney, BC | G12: 44949 | H12: ACTIVE | I12: 349 | J12: F2-R16 | K12: February | L12: Y | M12: ANNUAL | N12: X | O12: Y | P12: Y | Q12: Y | R12: Y | S12: Y | T12: Y | U12: Y | V12: Y | W12: Y
A13: 10030 Resthaven Drive | B13: Raven Property Management Ltd. | E13: 75 | F13: Sidney, BC | G13: 44228 | H13: ACTIVE | I13: SC 03001 | J13: F2-R16 | K13: May | L13: Y | M13: Y | N13: Y | O13: Y | P13: Y | Q13: ANNUAL | R13: Y | S13: Y | T13: Y | U13: Y | V13: Y | W13: Y
A14: 1004 Pemberton Road | B14: Raul Caballero | E14: 70 | F14: Victoria, BC | G14: 45161 | H14: ACTIVE | I14: PB 4001 | J14: M1-R1 | K14: December | L14: ANNUAL | M14: Y | N14: Y | O14: Y | P14: Y | Q14: Y | R14: Y | S14: Y | T14: Y | U14: Y | V14: Y | W14: ANNUAL
A15: 1005 & 1009 McKenzie Avenue | B15: Firm Management | E15: 60 | F15: Saanich, BC | H15: ACTIVE | I15: MN 5001 | J15: TU1-R4 | K15: May | L15: X | M15: X | N15: X | O15: X | P15: X | Q15: ANNUAL | R15: Y | S15: Y | T15: Y | U15: Y | V15: Y | W15: Y
A16: 1005 Broad Street | B16: Richmond Property Group | E16: 55 | F16: Victoria, BC | H16: ACTIVE | I16: K 5001 K4 | J16: TH2-R15 | K16: March | L16: Y | M16: Y | N16: ANNUAL | O16: Y | P16: Y | Q16: Y | R16: Y | S16: Y | T16: Y | U16: Y | V16: Y | W16: Y
A17: 1005 Pakington Street | B17: Century 21 Queenswood | E17: 50 | F17: Victoria, BC | G17: 44949 | H17: ACTIVE | I17: 171 | J17: TU3-R18 | K17: August | L17: Y | M17: Y | N17: Y | O17: Y | P17: Y | Q17: Y | R17: Y | S17: Y | T17: ANNUAL | U17: Y | V17: Y | W17: Y
A18: 1005 St. Charles Street | B18: Bross Holdings | E18: 55 | F18: Victoria, BC | G18: 45713 | H18: ACTIVE | I18: HC 5001 | J18: TH1-R9 | K18: May | L18: X | M18: Y | N18: Y | O18: Y | P18: Y | Q18: ANNUAL | R18: Y | S18: Y | T18: Y | U18: Y | V18: Y | W18: Y
A19: 1006 Fort Street | B19: Colliers | E19: 75 | F19: Victoria, BC | G19: 41214 | H19: ACTIVE | I19: ZZ 6001 K3-F1 | J19: M1-R2 | K19: September | L19: Y | M19: Y | N19: Y | O19: Y | P19: Y | Q19: Y | R19: Y | S19: ANNUAL | T19: Y | U19: Y | V19: Y | W19: Y
A20: 1006 Tolmie Avenue | B20: Century 21 Queenswood | E20: 60 | F20: Victoria, BC | H20: ACTIVE | I20: 163 | J20: M1-R1 | K20: January | L20: Y | M20: ANNUAL | N20: Y | O20: Y | P20: Y | Q20: Y | R20: Y | S20: Y | T20: Y | U20: Y | V20: Y | W20: Y
A21: 1007 Esquimalt Road | B21: Starlight Properties | E21: 50 | F21: Esquimalt, BC | H21: ACTIVE | I21: LT 7001 | J21: W1-R7 | K21: May | L21: Y | M21: Y | N21: Y | O21: Y | P21: ANNUAL | Q21: X | R21: Y | S21: Y | T21: Y | U21: Y | V21: Y | W21: X
A22: 101 Ontario Street | B22: Proline Property Management | E22: 55 | F22: Victoria, BC | G22: 45712 | H22: ACTIVE | I22: TO 101 | J22: W3-R20 | K22: November | L22: - | M22: Y | N22: Y | O22: Y | P22: Y | Q22: Y | R22: Y | S22: Y | T22: Y | U22: Y | V22: Y | W22: Y
A23: 1010 Mckenzie Avenue | B23: Starlight/Devon | E23: 55 | F23: Saanich, BC | G23: 45559 | H23: ACTIVE | I23: M 0001 | J23: W1-R6 | K23: February | L23: Y | M23: ANNUAL | N23: Y | O23: Y | P23: Y | Q23: X | R23: X | S23: Y | T23: Y | U23: Y | V23: Y | W23: Y
A24: 1012 Collinson Street | B24: Hutton | E24: 55 | F24: Victoria, BC | H24: ACTIVE | I24: M 2101 K3 | J24: TH1-R9 | K24: October | L24: Y | M24: Y | N24: Y | O24: Y | P24: Y | Q24: Y | R24: Y | S24: Y | T24: Y | U24: ANNUAL | V24: Y | W24: Y
A25: 1013 Vancouver Street | B25: Devon Properties | E25: 50 | F25: Victoria, BC | G25: 44949 | H25: ACTIVE | I25: 183 | J25: TH1-R8 | K25: May | L25: Y | M25: Y | N25: Y | O25: Y | P25: X | Q25: Y | R25: Y | S25: Y | T25: Y | U25: Y | V25: Y | W25: Y
A26: 1015 Kings Road | B26: Darioush Diba | E26: 55 | F26: Victoria, BC | G26: 44075 | H26: ACTIVE | I26: KQ 5101 | J26: M1-R3 | K26: June | L26: Y | M26: Y | N26: Y | O26: Y | P26: Y | Q26: ANNUAL | R26: Y | S26: Y | T26: Y | U26: Y | V26: Y | W26: Y
A27: 10159 Third Street | B27: Realstar Management | E27: 55 | F27: Sidney, BC | H27: ACTIVE | I27: 93 | J27: F2-R16 | K27: October | L27: Y | M27: Y | N27: Y | O27: Y | P27: Y | Q27: Y | R27: Y | S27: Y | T27: Y | U27: ANNUAL | V27: Y | W27: Y
A28: 1017 Queens Avenue | B28: Starlight/Devon | E28: 50 | F28: Victoria, BC | G28: 44949 | H28: ACTIVE | I28: 111 | J28: M1-R3 | K28: March | L28: Y | M28: Y | N28: Y | O28: ANNUAL | P28: Y | Q28: Y | R28: Y | S28: Y | T28: Y | U28: Y | V28: Y | W28: Y
A29: 1019 McClure Street | B29: Strata Plan VIS 308 | E29: 65 | F29: Victoria, BC | G29: 45253 | H29: ACTIVE | I29: CL 9101 | J29: TH1-R9 | K29: April | L29: Y | M29: Y | N29: Y | O29: ANNUAL | P29: Y | Q29: Y | R29: Y | S29: Y | T29: Y | U29: Y | V29: Y | W29: Y
A30: 1019 Rockland Avenue | B30: Century 21 | E30: 55 | F30: Victoria, BC | G30: 42186 | H30: ACTIVE | I30: ST 9101 K2 | J30: M1-R2 | K30: December | L30: Y | M30: Y | N30: Y | O30: ANNUAL | P30: Y | Q30: Y | R30: Y | S30: Y | T30: Y | U30: Y | V30: Y | W30: Y
A31: 1020 Park Boulevard | B31: Pemberton Holmes | E31: 50 | F31: Victoria, BC | G31: 44949 | H31: ACTIVE | I31: 92 | J31: TU3-R18 | K31: October | L31: Y | M31: Y | N31: Y | O31: Y | P31: Y | Q31: Y | R31: Y | S31: Y | T31: Y | U31: ANNUAL | V31: Y | W31: Y
A32: 1020 Pembroke Street | B32: Brown Bros. | E32: 55 | F32: Victoria, BC | G32: 42476 | H32: ACTIVE | I32: RT 0201 K2 | J32: M1-R3 | K32: July | L32: Y | M32: Y | N32: Y | O32: Y | P32: Y | Q32: Y | R32: ANNUAL | S32: Y | T32: Y | U32: X | V32: Y | W32: Y
A33: 1024 Fairfield Road | B33: Firm Management | E33: 55 | F33: Victoria, BC | G33: 41791 | H33: ACTIVE | I33: WT 4201 K3 | J33: TH1-R9 | K33: November | L33: Y | M33: Y | N33: Y | O33: Y | P33: ANNUAL | Q33: Y | R33: Y | S33: Y | T33: Y | U33: Y | V33: ANNUAL | W33: Y
A34: 1025 Johnson Street | B34: Devon Properties | E34: 60 | F34: Victoria, BC | G34: 45017 | H34: ACTIVE | I34: JD 5201 K5-F2 | J34: TH1-R8 | K34: January | L34: ANNUAL | M34: Y | N34: Y | O34: Y | P34: Y | Q34: Y | R34: Y | S34: Y | T34: Y | U34: Y | V34: Y | W34: Y
A35: 1026 Johnson Street | B35: Firm Management | E35: 55 | F35: Victoria, BC | G35: 41821 | H35: ACTIVE | I35: WS 6201 K4-F1 | J35: TH1-R8 | K35: July | L35: Y | M35: Y | N35: Y | O35: Y | P35: Y | Q35: Y | R35: Y | S35: Y | T35: Y | U35: Y | V35: Y | W35: Y
A36: 1030 Pendergast Street | B36: Starlight/Devon | E36: 70 | F36: Victoria, BC | G36: 45192 | H36: ACTIVE | I36: GT 0301 | J36: TU3-R18 | K36: July | L36: Y | M36: Y | N36: Y | O36: Y | P36: Y | Q36: Y | R36: ANNUAL | S36: Y | T36: Y | U36: X | V36: Y | W36: Y
A37: 1031 Burdett Avenue | B37: Hutton | C37: cancelled service- Nov 8/24 (tw) | E37: 55 | F37: Victoria, BC | G37: 42256 | H37: CANCELLED | I37: BA 1301 K2 | J37: - | K37: December | L37: - | M37: - | N37: - | O37: - | P37: - | Q37: - | R37: - | S37: - | T37: - | U37: - | V37: - | W37: -
A38: 1032 North Park | B38: Pacific Quorum | E38: 55 | F38: Victoria, BC | G38: 45039 | H38: ACTIVE | I38: 435 | J38: M1-R3 | K38: March | L38: X | M38: Y | N38: X | O38: ANNUAL | P38: X | Q38: X | R38: X | S38: Y | T38: Y | U38: Y | V38: Y | W38: Y
A39: 1035 Belmont Avenue | B39: Belmont Properties | C39: Months on invoice | E39: 55 | F39: Victoria, BC | G39: 45017 | H39: ACTIVE | I39: 445 | J39: TH1-R9 | K39: August | L39: Y | M39: Y | N39: Y | O39: Y | P39: Y | Q39: Y | R39: Y | S39: Y | T39: ANNUAL | U39: Y | V39: Y | W39: Y
A40: 1035 Pendergast Street | B40: Starlight/Devon | E40: 70 | F40: Victoria, BC | G40: 45192 | H40: ACTIVE | I40: GT 0301 | J40: TU3-R18 | K40: July | L40: Y | M40: Y | N40: Y | O40: Y | P40: Y | Q40: Y | R40: ANNUAL | S40: Y | T40: Y | U40: X | V40: Y | W40: Y
A41: 1036 Stellys Cross Road | B41: Devon Properties | E41: 50 | F41: Brentwood Bay, BC | H41: ACTIVE | I41: 424 | J41: TU2-R12 | K41: December | L41: Y | M41: Y | N41: Y | O41: Y | P41: Y | Q41: Y | R41: Y | S41: Y | T41: Y | U41: Y | V41: Y | W41: ANNUAL
A42: 104 Dallas Road | B42: Strata #1374 The Dolphins | E42: 55 | F42: Victoria, BC | G42: 43891 | H42: ACTIVE | I42: SP 401 K1-F1 | J42: W3-R20 | K42: August | L42: Y | M42: Y | N42: Y | O42: Y | P42: Y | Q42: Y | R42: Y | S42: ANNUAL | T42: Y | U42: Y | V42: Y | W42: Y
A43: 1040 Stellys Cross Road | B43: Devon Properties | E43: 50 | F43: Brentwood Bay, BC | H43: ACTIVE | I43: 424 | J43: TU2-R12 | K43: December | L43: Y | M43: Y | N43: Y | O43: Y | P43: Y | Q43: Y | R43: Y | S43: Y | T43: Y | U43: Y | V43: Y | W43: ANNUAL
A44: 1041 Fairfield Road | B44: Pemberton Holmes | E44: 50 | F44: Victoria, BC | H44: ACTIVE | I44: 68 | J44: M1-R2 | K44: April | L44: Y | M44: Y | N44: Y | O44: ANNUAL | P44: Y | Q44: Y | R44: Y | S44: Y | T44: Y | U44: Y | V44: Y | W44: Y
A45: 1041 Richardson Road | B45: Capital West | E45: 60 | F45: Victoria, BC | G45: 45078 | H45: ACTIVE | I45: RR 1401 | J45: TH1-R9 | K45: June | L45: Y | M45: Y | N45: Y | O45: Y | P45: ANNUAL | Q45: Y | R45: Y | S45: Y | T45: Y | U45: Y | V45: Y | W45: Y
A46: 1045 McClure Street | B46: Brown Bros. | E46: 50 | F46: Victoria, BC | H46: ACTIVE | I46: 332 | J46: M1-R2 | K46: December | L46: Y | M46: Y | N46: Y | O46: Y | P46: Y | Q46: Y | R46: Y | S46: Y | T46: Y | U46: Y | V46: Y | W46: Y
A47: 10459 Resthaven Drive | B47: Proline | E47: 50 | F47: Sidney, BC | G47: 44949 | H47: ACTIVE | I47: 392 | J47: F2-R16 | K47: May | L47: Y | M47: Y | N47: Y | O47: Y | P47: Y | Q47: ANNUAL | R47: Y | S47: Y | T47: Y | U47: Y | V47: Y | W47: Y
A48: 10461 Resthaven Drive | B48: Proline | E48: 50 | F48: Sidney, BC | G48: 44949 | H48: ACTIVE | I48: 392 | J48: F2-R16 | K48: May | L48: Y | M48: Y | N48: Y | O48: Y | P48: Y | Q48: ANNUAL | R48: Y | S48: Y | T48: Y | U48: Y | V48: Y | W48: Y
A49: 1049 Southgate Street | B49: Devon Properties | E49: 50 | F49: Victoria, BC | G49: 44949 | H49: ACTIVE | I49: 186 | J49: TU3-R18 | K49: September | L49: Y | M49: Y | N49: Y | O49: Y | P49: Y | Q49: Y | R49: Y | S49: Y | T49: ANNUAL | U49: Y | V49: Y | W49: Y
A50: 105 Wilson Street | B50: Pacifica Housing | E50: 65 | F50: Esquimalt, BC | G50: 45505 | H50: ACTIVE | I50: W 501 | J50: W1-R7 | K50: July | L50: Y | M50: X | N50: Y | O50: Y | P50: Y | Q50: Y | R50: Y | S50: ANNUAL | T50: Y | U50: Y | V50: Y | W50: X
A51: 1050 Park Boulevard | B51: Hutton | C51: $60/month (incl. hose, ext, mag lock check) | E51: 60 | F51: Victoria, BC | G51: 44559 | H51: ACTIVE | I51: P 0501 K2 | J51: M2-R11 | K51: March | L51: Y | M51: Y | N51: ANNUAL | O51: X | P51: Y | Q51: Y | R51: Y | S51: Y | T51: Y | U51: Y | V51: Y | W51: Y
A52: 10520 McDonald Park | B52: Complete Residential Property Management | E52: 75 | F52: Sidney, BC | G52: 45772 | H52: ACTIVE | I52: DN 02501 | J52: F2-R16 | K52: October | L52: - | M52: - | N52: - | O52: Y | P52: Y | Q52: Y | R52: Y | S52: Y | T52: Y | U52: Y | V52: ANNUAL | W52: Y
A53: 1055 Hillside Avenue | B53: Firm Management | E53: 55 | F53: Victoria, BC | G53: 42689 | H53: ACTIVE | I53: LM 5501 | J53: W1-R6 | K53: January | L53: ANNUAL | M53: Y | N53: Y | O53: Y | P53: Y | Q53: Y | R53: Y | S53: Y | T53: Y | U53: Y | V53: Y | W53: Y
A54: 1057 Moss Street | B54: Tim Slater | C54: Charge CC in ST and email receipt | E54: 60 | F54: Victoria, BC | G54: 45346 | H54: ACTIVE | I54: SM 7501 | J54: TH1-R9 | K54: September | L54: Y | M54: Y | N54: Y | O54: Y | P54: Y | Q54: Y | R54: Y | S54: Y | T54: ANNUAL | U54: Y | V54: Y | W54: Y
A55: 1060 Craigdarroch Road | B55: Pemberton Holmes | E55: 50 | F55: Esquimalt, BC | H55: ACTIVE | I55: 373 | J55: TH1-R9 | K55: March | L55: Y | M55: Y | N55: Y | O55: Y | P55: Y | Q55: Y | R55: Y | S55: Y | T55: Y | U55: X | V55: Y | W55: Y
A56: 1060 Goldstream Avenue | B56: Centurion Properties | C56: Months on invoice | E56: 55 | F56: Langford, BC | G56: 44949 | H56: ACTIVE | I56: 412 | J56: TU1-R5 | K56: September | L56: Y | M56: Y | N56: Y | O56: Y | P56: Y | Q56: Y | R56: Y | S56: Y | T56: ANNUAL | U56: Y | V56: Y | W56: Y
A57: 1060 Southgate Street | B57: Southgate Manor | E57: 50 | F57: Victoria, BC | G57: 44949 | H57: ACTIVE | I57: 42 | J57: TU3-R18 | K57: September | L57: Y | M57: Y | N57: Y | O57: Y | P57: Y | Q57: Y | R57: Y | S57: Y | T57: Y | U57: ANNUAL | V57: Y | W57: Y
A58: 1066 Foul Bay Road | B58: Newport Property | E58: 50 | F58: Victoria, BC | G58: 44949 | H58: ACTIVE | I58: 124 | J58: TU2-R13 | K58: July | L58: Y | M58: Y | N58: Y | O58: Y | P58: Y | Q58: ANNUAL | R58: Y | S58: Y | T58: Y | U58: Y | V58: Y | W58: Y
A59: 1069 Southgate Street | B59: Newport Property Management | E59: 50 | F59: Victoria, BC | H59: ACTIVE | I59: 307 | J59: M1-R2 | K59: March | L59: Y | M59: Y | N59: Y | O59: Y | P59: Y | Q59: Y | R59: Y | S59: Y | T59: Y | U59: Y | V59: Y | W59: Y
A60: 1088 Johnson Street | B60: Centurion Property Associates Inc. | C60: Months on invoice | E60: 125 | F60: Victoria, BC | G60: 45833 | H60: ACTIVE | I60: HJ 8801 | J60: TH1-R8 | K60: May | L60: - | M60: - | N60: - | O60: X | P60: Y | Q60: X | R60: Y | S60: Y | T60: Y | U60: Y | V60: Y | W60: Y
A61: 109 Wilson Street | B61: Pacifica Housing | E61: 65 | F61: Esquimalt, BC | G61: 45505 | H61: ACTIVE | I61: A 901 | J61: W1-R7 | K61: July | L61: Y | M61: X | N61: Y | O61: Y | P61: Y | Q61: Y | R61: Y | S61: ANNUAL | T61: Y | U61: Y | V61: Y | W61: X
A62: 1090 Johnson Street | B62: Firm Management | E62: 60 | F62: Victoria, BC | G62: 45017 | H62: ACTIVE | I62: TM 0901 | J62: TH1-R8 | K62: March | L62: Y | M62: Y | N62: Y | O62: Y | P62: Y | Q62: Y | R62: Y | S62: Y | T62: Y | U62: Y | V62: Y | W62: Y
A63: 1097 View Street | B63: Firm Management | E63: 125 | F63: Victoria, BC | G63: 45346 | H63: ACTIVE | I63: VS 7901 | J63: TH1-R9 | K63: May | L63: Y | M63: Y | N63: Y | O63: Y | P63: Y | Q63: Y | R63: Y | S63: Y | T63: Y | U63: Y | V63: Y | W63: ANNUAL
A64: 110 Douglas Street | B64: Devon Properties | E64: 50 | F64: Victoria, BC | H64: ACTIVE | I64: 344 | J64: TU3-R18 | K64: August | L64: Y | M64: Y | N64: Y | O64: Y | P64: Y | Q64: Y | R64: Y | S64: Y | T64: Y | U64: ANNUAL | V64: Y | W64: Y
A65: 1106 Balmoral Road | B65: Peter Hejjas | E65: 50 | F65: Victoria, BC | G65: 44949 | H65: ACTIVE | I65: 127 | J65: M1-R3 | K65: March | L65: Y | M65: Y | N65: Y | O65: ANNUAL | P65: Y | Q65: Y | R65: Y | S65: Y | T65: Y | U65: Y | V65: Y | W65: Y
A66: 1110 Samar Crescent | B66: Breakwater Realty Inc. | C66: Building A | E66: 75 | F66: Langford, BC | G66: 45833 | H66: ACTIVE | I66: MS 0111 | J66: TU1-R5 | K66: November | L66: - | M66: - | N66: - | O66: - | P66: - | Q66: Y | R66: Y | S66: Y | T66: Y | U66: Y | V66: ANNUAL | W66: Y
A67: 1111 Hillside Avenue | B67: Complete Residential | E67: 55 | F67: Victoria, BC | H67: ACTIVE | I67: OP 1111 | J67: M1-R1 | K67: July | L67: Y | M67: Y | N67: Y | O67: Y | P67: Y | Q67: Y | R67: Y | S67: ANNUAL | T67: Y | U67: Y | V67: Y | W67: Y
A68: 1114 Samar Crescent | B68: Breakwater Realty Inc. | C68: Building B | E68: 75 | F68: Langford, BC | G68: 45833 | H68: ACTIVE | I68: MS 0111 | J68: TU1-R5 | K68: November | L68: - | M68: - | N68: - | O68: - | P68: - | Q68: Y | R68: Y | S68: Y | T68: Y | U68: Y | V68: ANNUAL | W68: Y
A69: 1115 Craigflower Road | B69: Proline | C69: $65/month (A) | E69: 65 | F69: Esquimalt, BC | G69: 44378 | H69: ACTIVE | I69: IW 5111 K6-G1 | J69: W2-R22 | K69: August | L69: Y | M69: Y | N69: Y | O69: Y | P69: Y | Q69: Y | R69: Y | S69: Y | T69: ANNUAL | U69: Y | V69: X | W69: Y
A70: 1120 Blanshard Street | B70: Equitex | E70: 50 | F70: Victoria, BC | G70: 44949 | H70: ACTIVE | I70: N/A | J70: TH2-R15 | K70: February | L70: X | M70: Y | N70: ANNUAL | O70: Y | P70: Y | Q70: Y | R70: Y | S70: Y | T70: Y | U70: Y | V70: Y | W70: Y
A71: 1120 Burdett Ave | B71: Devon Properties | E71: 55 | F71: Victoria, BC | G71: 45589 | H71: ACTIVE | I71: B0211 | J71: TH1-R9 | K71: October | L71: Y | M71: Y | N71: Y | O71: Y | P71: Y | Q71: Y | R71: Y | S71: Y | T71: Y | U71: ANNUAL | V71: Y | W71: Y
A72: 1120 Richardson Street | B72: Gibraltar | E72: 50 | F72: Victoria, BC | G72: 44949 | H72: ACTIVE | I72: 4 | J72: TH1-R9 | K72: September | L72: Y | M72: Y | N72: Y | O72: Y | P72: Y | Q72: Y | R72: Y | S72: Y | T72: Y | U72: Y | V72: Y | W72: Y
A73: 1120 Yates Street | B73: Colliers | E73: 50 | F73: Victoria, BC | G73: 44949 | H73: ACTIVE | I73: 321 | J73: TH1-R8 | K73: November | L73: Y | M73: Y | N73: Y | O73: Y | P73: Y | Q73: X | R73: X | S73: Y | T73: X | U73: X | V73: ANNUAL | W73: Y
A74: 1122 Hilda Street | B74: Pemberton Strata | E74: 50 | F74: Victoria, BC | H74: ACTIVE | I74: 427 | J74: TU2-R13 | K74: November | L74: Y | M74: Y | N74: Y | O74: Y | P74: Y | Q74: Y | R74: Y | S74: Y | T74: Y | U74: Y | V74: ANNUAL | W74: Y
A75: 1122 McKenzie Street | B75: Pemberton Holmes | E75: 50 | F75: Victoria, BC | H75: ACTIVE | I75: 100 | J75: M1-R2 | K75: March | L75: Y | M75: Y | N75: ANNUAL | O75: Y | P75: Y | Q75: Y | R75: Y | S75: Y | T75: Y | U75: Y | V75: Y | W75: Y
A76: 1125 Douglas Street | B76: Arpeg Holdings Cactus Club | C76: single panel share with 702 Fort Street | E76: 65 | F76: Victoria, BC | G76: 41153 | H76: ACTIVE | I76: MEET KEN COOPER | J76: TH2-R15 | K76: April | L76: Y | M76: Y | N76: Y | O76: Y | P76: Y | Q76: ANNUAL | R76: Y | S76: X | T76: Y | U76: Y | V76: Y | W76: Y
A77: 1125 Hillside Avenue | B77: Devon Properties | E77: 55 | F77: Victoria, BC | G77: 45539 | H77: CANCELLED | I77: H 5211 | J77: - | K77: August | L77: Y | M77: Y | N77: Y | O77: Y | P77: - | Q77: - | R77: - | S77: - | T77: - | U77: - | V77: - | W77: -
A78: 1126 Rockland Avenue | B78: Starlight/Devon | E78: 70 | F78: Victoria, BC | G78: 45170 | H78: ACTIVE | I78: LD 6211 | J78: TH1-R9 | K78: June | L78: Y | M78: Y | N78: Y | O78: Y | P78: Y | Q78: ANNUAL | R78: Y | S78: Y | T78: Y | U78: Y | V78: Y | W78: Y
A79: 1127 Wharf Street | B79: Darcy's Pub | E79: 55 | F79: Victoria, BC | G79: 41791 | H79: ACTIVE | I79: KEY AT SITE | J79: TH2-R15 | K79: April | L79: Y | M79: Y | N79: Y | O79: Y | P79: ANNUAL | Q79: Y | R79: Y | S79: Y | T79: Y | U79: Y | V79: Y | W79: Y
A80: 1130 Fort Street | B80: Pacifica Housing | E80: 65 | F80: Victoria, BC | G80: 45527 | H80: ACTIVE | I80: F 0311 | J80: TH1-R9 | K80: July | L80: Y | M80: Y | N80: Y | O80: X | P80: Y | Q80: Y | R80: ANNUAL | S80: Y | T80: Y | U80: Y | V80: X | W80: Y
A81: 1132 McClure Street | B81: Devon Properties | E81: 50 | F81: Victoria, BC | G81: 44949 | H81: ACTIVE | I81: 162 | J81: TH1-R9 | K81: August | L81: Y | M81: Y | N81: Y | O81: Y | P81: Y | Q81: Y | R81: Y | S81: Y | T81: ANNUAL | U81: Y | V81: Y | W81: Y
A82: 1133A Reynolds Road | B82: Abbeyfield St. Peters | E82: 55 | F82: Saanich, BC | H82: ACTIVE | I82: PQ 3311 | J82: TU1-R4 | K82: February | L82: Y | M82: Y | N82: Y | O82: Y | P82: X | Q82: X | R82: X | S82: X | T82: Y | U82: Y | V82: Y | W82: Y
A83: 1137-1139 Yates Street | B83: Equitex Property Management | E83: 75 | F83: Victoria, BC | G83: 45863 | H83: ACTIVE | I83: TY 7311 | J83: M1-R1 | K83: October | L83: - | M83: - | N83: - | O83: - | P83: - | Q83: - | R83: Y | S83: Y | T83: Y | U83: Y | V83: Y | W83: Y
A84: 1145 Bay Street | B84: Ashton Oaks c/o Gateway Prop | E84: 50 | F84: Victoria, BC | G84: 44949 | H84: ACTIVE | I84: 322 | J84: M1-R3 | K84: September | L84: Y | M84: Y | N84: Y | O84: Y | P84: Y | Q84: Y | R84: Y | S84: ANNUAL | T84: Y | U84: Y | V84: Y | W84: Y
A85: 1150 Hilda Street | B85: Devon Properties | E85: 60 | F85: Victoria, BC | G85: 45448 | H85: ACTIVE | I85: AH 0511 | J85: M1-R2 | K85: August | L85: Y | M85: Y | N85: Y | O85: Y | P85: Y | Q85: Y | R85: ANNUAL | S85: Y | T85: Y | U85: Y | V85: Y | W85: Y
A86: 1150 Queens Avenue | B86: Pacific Quorum | E86: 65 | F86: Victoria, BC | H86: ACTIVE | I86: 406 | J86: M1-R1 | K86: January | L86: Y | M86: ANNUAL | N86: Y | O86: Y | P86: Y | Q86: Y | R86: Y | S86: Y | T86: Y | U86: Y | V86: Y | W86: Y
A87: 1150 Rockland Avenue | B87: Pemberton Holmes | E87: 50 | F87: Victoria, BC | H87: ACTIVE | I87: 346 | J87: M1-R2 | K87: September | L87: Y | M87: Y | N87: Y | O87: Y | P87: Y | Q87: Y | R87: Y | S87: Y | T87: ANNUAL | U87: Y | V87: Y | W87: Y
A88: 1160 Esquimalt Road | B88: Starlight/Devon | E88: 55 | F88: Victoria, BC | G88: 45620 | H88: ACTIVE | I88: EQ 611 | J88: W1-R7 | K88: December | L88: ANNUAL | M88: Y | N88: X | O88: Y | P88: Y | Q88: X | R88: Y | S88: Y | T88: Y | U88: Y | V88: Y | W88: X
A89: 1160 Richardson Street | B89: Lee & Sharpe | E89: 50 | F89: Victoria, BC | H89: ACTIVE | I89: 164 | J89: M1-R2 | K89: March | L89: Y | M89: Y | N89: Y | O89: ANNUAL | P89: Y | Q89: Y | R89: Y | S89: Y | T89: Y | U89: Y | V89: Y | W89: Y
A90: 1165 Meares Street | B90: Pemberton Holmes (new June 13/24) | E90: 55 | F90: Victoria, BC | G90: 42005 | H90: ACTIVE | I90: MA 5611 K2 | J90: M1-R2 | K90: July | L90: Y | M90: Y | N90: Y | O90: Y | P90: Y | Q90: ANNUAL | R90: Y | S90: Y | T90: Y | U90: Y | V90: Y | W90: Y
A91: 1165 Yates Street | B91: Devon properties | E91: 50 | F91: Victoria, BC | H91: ACTIVE | I91: 340 | J91: M1-R1 | K91: February | L91: Y | M91: Y & ANNUAL | N91: Y | O91: Y | P91: Y | Q91: Y | R91: Y | S91: Y | T91: Y | U91: Y | V91: Y | W91: Y
A92: 1166 Rockland Avenue | B92: Freelance | E92: 55 | F92: Victoria, BC | H92: ACTIVE | I92: K 6611 K3 | J92: TH1-R9 | K92: September | L92: Y | M92: Y | N92: Y | O92: Y | P92: Y | Q92: Y | R92: Y | S92: Y | T92: ANNUAL | U92: Y | V92: Y | W92: Y
A93: 1177 Esquimalt Road | B93: Devon Properties | E93: 50 | F93: Esquimalt, BC | G93: 44949 | H93: ACTIVE | I93: 368 | J93: W1-R7 | K93: April | L93: Y | M93: Y | N93: Y | O93: ANNUAL | P93: Y | Q93: Y | R93: Y | S93: Y | T93: Y | U93: Y | V93: Y | W93: X
A94: 1178 Beach Drive | B94: Devon Properties | E94: 50 | F94: Oak Bay, BC | G94: 44949 | H94: ACTIVE | I94: 108 | J94: TU2-R13 | K94: July | L94: Y | M94: Y | N94: Y | O94: Y | P94: Y | Q94: Y | R94: ANNUAL | S94: Y | T94: Y | U94: Y | V94: Y | W94: Y
A95: 118 Croft Street | B95: Brown Bros. | E95: 50 | F95: Victoria, BC | H95: ACTIVE | I95: 366 | J95: W3-R20 | K95: May | L95: Y | M95: Y | N95: Y | O95: Y | P95: ANNUAL | Q95: Y | R95: Y | S95: Y | T95: Y | U95: Y | V95: Y | W95: Y
A96: 1180 Colville Road | B96: Starlight Properties c/o Devon Properties | E96: 65 | F96: Esquimalt, BC | G96: 45253 | H96: ACTIVE | I96: CR 0811 | J96: W2-R22 | K96: September | L96: Y | M96: Y | N96: Y | O96: Y | P96: Y | Q96: Y | R96: Y | S96: Y | T96: Y | U96: Y | V96: X | W96: Y
A97: 1180 View Street | B97: Devon Properties | E97: 50 | F97: Victoria, BC | H97: ACTIVE | I97: 404 | J97: M1-R1 | K97: July | L97: Y | M97: Y | N97: Y | O97: Y | P97: Y | Q97: ANNUAL | R97: Y | S97: Y | T97: Y | U97: Y | V97: Y | W97: Y
A98: 1185 Yates Street | B98: Devon Properties | E98: 50 | F98: Victoria, BC | G98: 44949 | H98: ACTIVE | I98: 386 | J98: TH1-R9 | K98: May | L98: Y | M98: Y | N98: Y | O98: Y | P98: ANNUAL | Q98: Y | R98: X | S98: Y | T98: Y | U98: Y | V98: Y | W98: Y
A99: 1190 May Street | B99: Devon Properties | E99: 50 | F99: Victoria, BC | G99: 44949 | H99: ACTIVE | I99: 409 | J99: TU2-R13 | K99: February | L99: Y | M99: ANNUAL | N99: Y | O99: Y | P99: Y | Q99: Y | R99: X | S99: Y | T99: Y | U99: Y | V99: Y | W99: Y
A100: 1194 Esquimalt Road | B100: Capital West | E100: 60 | F100: Esquimalt, BC | G100: 45078 | H100: ACTIVE | I100: FM 4911 | J100: W1-R7 | K100: March | L100: Y | M100: Y | N100: Y | O100: Y | P100: Y | Q100: Y | R100: Y | S100: Y | T100: Y | U100: Y | V100: Y | W100: X
...

Sheet 2025 Completion Chart
A2: Cantec Monthlies - Completion Chart
A3: Route # | B3: # Of Sites | C3: Average Finish Time (3:30-4pm) | D3: Locked Routes | E3: Total # of Skipped (Per Route and without Annuals) | F3: Total # of Skipped (Per Route) | G3: January | J3: February | M3: March | P3: April | S3: May | V3: June | Y3: July | AB3: August | AE3: September | AH3: October | AK3: November | AN3: December
G4: Finish time | H4: Completed? | I4: # Skipped | J4: Finish time | K4: Completed? | L4: # Skipped | M4: Finish time | N4: Completed? | O4: # Skipped | P4: Finish time | Q4: Completed? | R4: # Skipped | S4: Finish time | T4: Completed? | U4: # Skipped | V4: Finish time | W4: Completed? | X4: # Skipped | Y4: Finish time | Z4: Completed? | AA4: # Skipped | AB4: Finish time | AC4: Completed? | AD4: # Skipped | AE4: Finish time | AF4: Completed? | AG4: # Skipped | AH4: Finish time | AI4: Completed? | AJ4: # Skipped | AK4: Finish time | AL4: Completed? | AM4: # Skipped | AN4: Finish time | AO4: Completed? | AP4: # Skipped
A5: R1 | B5: =COUNTIF('Jan 2025 - Dec 2025'!J1:J750, "M1-R1") -> 33 | C5: =AVERAGE(G5,J5,M5,P5,S5,V5,Y5,AB5,AE5) -> 0.63804012 | D5: Locked | E5: =F5-B5 -> -3 | F5: =SUM(I5,L5,O5,R5,U5,X5,AA5,AD5,AG5,AJ5,AM5,AP5) -> 30 | G5: 0.67361111 | H5: Y | I5: 1 | J5: 0.63541667 | K5: Y | L5: 2 | M5: 0.61597222 | N5: Y | O5: 2 | P5: 0.62569444 | Q5: Y | R5: 3 | S5: 0.63888889 | T5: Y | U5: 4 | V5: 0.61805556 | W5: Y | X5: 3 | Y5: 0.65902778 | Z5: Y | AA5: 5 | AB5: 0.64375 | AC5: Y | AD5: 2 | AE5: 0.63194444 | AF5: Y | AG5: 1 | AH5: 0.60625 | AI5: Y | AJ5: 4 | AK5: 0.63541667 | AL5: Y | AM5: 1 | AN5: 0.63888889 | AO5: Y | AP5: 2
A6: R2 | B6: =COUNTIF('Jan 2025 - Dec 2025'!J1:J751, "M1-R2") -> 30 | C6: =AVERAGE(G6,J6,M6,P6,S6,V6,Y6,AB6,AE6,AH6,AK6,PN6) -> 0.59084596 | D6: Locked | E6: =F6-B6 -> -1 | F6: =SUM(I6,L6,O6,R6,U6,X6,AA6,AD6,AG6,AJ6,AM6,AP6) -> 29 | G6: 0.60069444 | H6: Y | I6: 1 | J6: 0.61875 | K6: Y | L6: 2 | M6: 0.56944444 | N6: Y | O6: 3 | P6: 0.57986111 | Q6: Y | R6: 5 | S6: 0.50694444 | T6: Y | U6: 5 | V6: 0.54375 | W6: Y | X6: 2 | Y6: 0.57986111 | Z6: Y | AA6: 2 | AB6: 0.64236111 | AC6: Y | AD6: 2 | AE6: 0.53125 | AF6: Y | AG6: 4 | AH6: 0.67361111 | AI6: Y | AJ6: 2 | AK6: 0.65277778 | AL6: Y | AM6: 1 | AN6: 0.67013889 | AO6: Y | AP6: 0
A7: R3 | B7: =COUNTIF('Jan 2025 - Dec 2025'!J1:J752, "M1-R3") -> 32 | C7: =AVERAGE(G7,J7,M7,P7,S7,V7,Y7,AB7,AE7,AH7,AK7,PN7) -> 0.62462121 | D7: Locked | E7: =F7-B7 -> 8 | F7: =SUM(I7,L7,O7,R7,U7,X7,AA7,AD7,AG7,AJ7,AM7,AP7) -> 40 | G7: 0.67708333 | H7: Y | I7: 3 | J7: 0.59027778 | K7: Y | L7: 3 | M7: 0.63194444 | N7: Y | O7: 2 | P7: 0.60416667 | Q7: Y | R7: 8 | S7: 0.67152778 | T7: Y | U7: 3 | V7: 0.64583333 | W7: Y | X7: 3 | Y7: 0.59097222 | Z7: Y | AA7: 5 | AB7: 0.60069444 | AC7: Y | AD7: 3 | AE7: 0.58680556 | AF7: Y | AG7: 4 | AH7: 0.62708333 | AI7: Y | AJ7: 4 | AK7: 0.64444444 | AL7: Y | AM7: 1 | AN7: 0.67569444 | AO7: Y | AP7: 1
A8: R4 | B8: =COUNTIF('Jan 2025 - Dec 2025'!J1:J753, "TU1-R4") -> 14 | C8: =AVERAGE(G8,J8,M8,P8,S8,V8,Y8,AB8,AE8,AH8,AK8,PN8) -> 0.63655303 | E8: =F8-B8 -> 28 | F8: =SUM(I8,L8,O8,R8,U8,X8,AA8,AD8,AG8,AJ8,AM8,AP8) -> 42 | G8: 0.66666667 | H8: Y | I8: 3 | J8: 0.66458333 | K8: Y | L8: 5 | M8: 0.64583333 | N8: Y | O8: 2 | P8: 0.66319444 | Q8: Y | R8: 3 | S8: 0.58333333 | T8: Y | U8: 4 | V8: 0.66875 | W8: X | X8: 6 | Y8: 0.66805556 | Z8: Y | AA8: 3 | AB8: 0.66666667 | AC8: X | AD8: 6 | AE8: 0.66666667 | AF8: Y | AG8: 1 | AH8: 0.67361111 | AI8: Y | AJ8: 2 | AK8: 0.43472222 | AL8: Y | AM8: 7 | AN8: 0.57291667 | AO8: Y | AP8: 0
A9: R5 | B9: =COUNTIF('Jan 2025 - Dec 2025'!J1:J738, "TU1-R5") -> 31 | C9: =AVERAGE(G9,J9,M9,P9,S9,V9,Y9,AB9,AE9,AH9,AK9,PN9) -> 0.66313131 | D9: Locked | E9: =F9-B9 -> 17 | F9: =SUM(I9,L9,O9,R9,U9,X9,AA9,AD9,AG9,AJ9,AM9,AP9) -> 48 | G9: 0.66666667 | H9: X | I9: 6 | J9: 0.67986111 | K9: Y | L9: 2 | M9: 0.64652778 | N9: Y | O9: 2 | P9: 0.64722222 | Q9: Y | R9: 1 | S9: 0.66180556 | T9: Y | U9: 1 | V9: 0.66527778 | W9: Y | X9: 3 | Y9: 0.67222222 | Z9: Y | AA9: 3 | AB9: 0.66180556 | AC9: Y | AD9: 10 | AE9: 0.66319444 | AF9: Y | AG9: 5 | AH9: 0.66319444 | AI9: Y | AJ9: 5 | AK9: 0.66666667 | AL9: X | AM9: 6 | AN9: 0.66875 | AO9: Y | AP9: 4
A10: R6 | B10: =COUNTIF('Jan 2025 - Dec 2025'!J1:J739, "W1-R6") -> 32 | C10: =AVERAGE(G10,J10,M10,P10,S10,V10,Y10,AB10,AE10,AH10,AK10,PN10) -> 0.65700758 | E10: =F10-B10 -> 31 | F10: =SUM(I10,L10,O10,R10,U10,X10,AA10,AD10,AG10,AJ10,AM10,AP10) -> 63 | G10: 0.63888889 | H10: Y | I10: 4 | J10: 0.67777778 | K10: Y | L10: 4 | M10: 0.64444444 | N10: Y | O10: 3 | P10: 0.68402778 | Q10: Y | R10: 3 | S10: 0.66944444 | T10: X | U10: 6 | V10: 0.58333333 | W10: X | X10: 13 | Y10: 0.67916667 | Z10: X | AA10: 12 | AB10: 0.68402778 | AC10: Y | AD10: 6 | AE10: 0.64930556 | AF10: Y | AG10: 6 | AH10: 0.65208333 | AI10: Y | AJ10: 3 | AK10: 0.66458333 | AL10: Y | AM10: 0 | AN10: 0.66111111 | AO10: Y | AP10: 3
A11: R7 | B11: =COUNTIF('Jan 2025 - Dec 2025'!J2:J740, "w1-r7") -> 29 | C11: =AVERAGE(G11,J11,M11,P11,S11,V11,Y11,AB11,AE11,AH11,AK11,PN11) -> 0.65366162 | E11: =F11-B11 -> 37 | F11: =SUM(I11,L11,O11,R11,U11,X11,AA11,AD11,AG11,AJ11,AM11,AP11) -> 66 | G11: 0.69027778 | H11: Y | I11: 1 | J11: 0.68055556 | K11: X | L11: 6 | M11: 0.68402778 | N11: Y | O11: 4 | P11: 0.64930556 | Q11: Y | R11: 4 | S11: 0.57847222 | T11: Y | U11: 8 | V11: 0.61736111 | W11: Y | X11: 4 | Y11: 0.67361111 | Z11: Y | AA11: 2 | AB11: 0.64791667 | AC11: Y | AD11: 3 | AE11: 0.67361111 | AF11: Y | AG11: 1 | AH11: 0.66388889 | AI11: Y | AJ11: 4 | AK11: 0.63125 | AL11: Y | AM11: 0 | AN11: - | AO11: X | AP11: 29
A12: R8 | B12: =COUNTIF('Jan 2025 - Dec 2025'!J1:J741, "TH1-R8") -> 25 | C12: =AVERAGE(G12,J12,M12,P12,S12,V12,Y12,AB12,AE12,AH12,AK12,PN12) -> 0.66167929 | D12: Locked | E12: =F12-B12 -> 43 | F12: =SUM(I12,L12,O12,R12,U12,X12,AA12,AD12,AG12,AJ12,AM12,AP12) -> 68 | G12: 0.60277778 | H12: Y | I12: 4 | J12: 0.65277778 | K12: Y | L12: 0 | M12: 0.65277778 | N12: Y | O12: 2 | P12: 0.64652778 | Q12: Y | R12: 2 | S12: 0.67361111 | T12: X | U12: 7 | V12: 0.68125 | W12: X | X12: 13 | Y12: 0.67708333 | Z12: X | AA12: 9 | AB12: 0.69097222 | AC12: X | AD12: 8 | AE12: 0.67361111 | AF12: X | AG12: 7 | AH12: 0.67083333 | AI12: X | AJ12: 7 | AK12: 0.65625 | AL12: X | AM12: 7 | AN12: 0.68958333 | AO12: X | AP12: 2
A13: R9 | B13: =COUNTIF('Jan 2025 - Dec 2025'!J1:J742, "TH1-R9") -> 32 | C13: =AVERAGE(G13,J13,M13,P13,S13,V13,Y13,AB13,AE13,AH13,AK13,PN13) -> 0.61710859 | E13: =F13-B13 -> 6 | F13: =SUM(I13,L13,O13,R13,U13,X13,AA13,AD13,AG13,AJ13,AM13,AP13) -> 38 | G13: 0.65277778 | H13: Y | I13: 1 | J13: 0.6 | K13: Y | L13: 2 | M13: 0.58680556 | N13: Y | O13: 1 | P13: 0.57361111 | Q13: Y | R13: 6 | S13: 0.54166667 | T13: Y | U13: 7 | V13: 0.60763889 | W13: Y | X13: 6 | Y13: 0.64444444 | Z13: Y | AA13: 3 | AB13: 0.66805556 | AC13: Y | AD13: 1 | AE13: 0.61805556 | AF13: Y | AG13: 5 | AH13: 0.61180556 | AI13: Y | AJ13: 2 | AK13: 0.68333333 | AL13: Y | AM13: 2 | AN13: 0.65833333 | AO13: Y | AP13: 2
A14: R10 | B14: =COUNTIF('Jan 2025 - Dec 2025'!J1:J743, "F1-R10") -> 28 | C14: =AVERAGE(G14,J14,M14,P14,S14,V14,Y14,AB14,AE14,AH14,AK14,PN14) -> 0.62784091 | D14: Locked | E14: =F14-B14 -> 6 | F14: =SUM(I14,L14,O14,R14,U14,X14,AA14,AD14,AG14,AJ14,AM14,AP14) -> 34 | G14: 0.64722222 | H14: Y | I14: 2 | J14: 0.60069444 | K14: Y | L14: 7 | M14: 0.63194444 | N14: Y | O14: 4 | P14: 0.64375 | Q14: Y | R14: 4 | S14: 0.65972222 | T14: Y | U14: 4 | V14: 0.59375 | W14: Y | X14: 2 | Y14: 0.63402778 | Z14: Y | AA14: 3 | AB14: 0.64444444 | AC14: Y | AD14: 0 | AE14: 0.62708333 | AF14: Y | AG14: 0 | AH14: 0.5875 | AI14: Y | AJ14: 3 | AK14: 0.63611111 | AL14: Y | AM14: 3 | AN14: 0.65347222 | AO14: Y | AP14: 2
A15: R11 | B15: =COUNTIF('Jan 2025 - Dec 2025'!J1:J738, "M2-R11") -> 12 | C15: =AVERAGE(G15,J15,M15,P15,S15,V15,Y15,AB15,AE15,AH15,AK15,PN15) -> 0.64236111 | E15: =F15-B15 -> 14 | F15: =SUM(I15,L15,O15,R15,U15,X15,AA15,AD15,AG15,AJ15,AM15,AP15) -> 26 | G15: 0.63541667 | H15: Y | I15: 1 | J15: 0.65 | K15: Y | L15: 0 | M15: 0.61458333 | N15: Y | O15: 2 | P15: - | Q15: X | R15: 12 | S15: 0.65486111 | T15: Y | U15: 1 | V15: 0.65138889 | W15: Y | X15: 1 | Y15: 0.61944444 | Z15: Y | AA15: 0 | AB15: 0.63541667 | AC15: Y | AD15: 1 | AE15: 0.66805556 | AF15: X | AG15: 3 | AH15: 0.64236111 | AI15: Y | AJ15: 3 | AK15: 0.65208333 | AL15: Y | AM15: 1 | AN15: 0.64236111 | AO15: Y | AP15: 1
A16: R12 | B16: =COUNTIF('Jan 2025 - Dec 2025'!J1:J738, "TU2-R12") -> 29 | C16: =AVERAGE(G16,J16,M16,P16,S16,V16,Y16,AB16,AE16,AH16,AK16,PN16) -> 0.66073232 | D16: Locked | E16: =F16-B16 -> 8 | F16: =SUM(I16,L16,O16,R16,U16,X16,AA16,AD16,AG16,AJ16,AM16,AP16) -> 37 | G16: 0.68402778 | H16: Y | I16: 3 | J16: 0.66666667 | K16: Y | L16: 3 | M16: 0.66736111 | N16: X | O16: 4 | P16: 0.62291667 | Q16: Y | R16: 4 | S16: 0.64166667 | T16: Y | U16: 2 | V16: 0.68263889 | W16: Y | X16: 2 | Y16: 0.67013889 | Z16: Y | AA16: 1 | AB16: 0.65694444 | AC16: Y | AD16: 2 | AE16: 0.66319444 | AF16: Y | AG16: 2 | AH16: 0.66666667 | AI16: Y | AJ16: 1 | AK16: 0.64583333 | AL16: Y | AM16: 6 | AN16: 0.65555556 | AO16: Y | AP16: 7
A17: R13 | B17: =COUNTIF('Jan 2025 - Dec 2025'!J1:J738, "TU2-R13") -> 22 | C17: =AVERAGE(G17,J17,M17,P17,S17,V17,Y17,AB17,AE17,AH17,AK17,PN17) -> 0.57777778 | E17: =F17-B17 -> 4 | F17: =SUM(I17,L17,O17,R17,U17,X17,AA17,AD17,AG17,AJ17,AM17,AP17) -> 26 | G17: 0.57638889 | H17: Y | I17: 2 | J17: 0.57569444 | K17: Y | L17: 1 | M17: 0.55902778 | N17: Y | O17: 2 | P17: 0.56388889 | Q17: Y | R17: 1 | S17: 0.58333333 | T17: Y | U17: 3 | V17: 0.53402778 | W17: Y | X17: 4 | Y17: 0.57638889 | Z17: Y | AA17: 4 | AB17: 0.57986111 | AC17: Y | AD17: 3 | AE17: 0.59791667 | AF17: Y | AG17: 3 | AH17: 0.60416667 | AI17: Y | AJ17: 0 | AK17: 0.60486111 | AL17: Y | AM17: 1 | AN17: 0.56875 | AO17: Y | AP17: 2
A18: R14 | B18: =COUNTIF('Jan 2025 - Dec 2025'!J1:J739, "W2-R14") -> 31 | C18: =AVERAGE(G18,J18,M18,P18,S18,V18,Y18,AB18,AE18,AH18,AK18,PN18) -> 0.65669192 | E18: =F18-B18 -> 20 | F18: =SUM(I18,L18,O18,R18,U18,X18,AA18,AD18,AG18,AJ18,AM18,AP18) -> 51 | G18: 0.67777778 | H18: Y | I18: 5 | J18: 0.67847222 | K18: Y | L18: 4 | M18: 0.675 | N18: Y | O18: 5 | P18: 0.66666667 | Q18: Y | R18: 5 | S18: 0.66111111 | T18: Y | U18: 4 | V18: 0.625 | W18: Y | X18: 6 | Y18: 0.60347222 | Z18: Y | AA18: 7 | AB18: 0.62361111 | AC18: Y | AD18: 5 | AE18: 0.6625 | AF18: X | AG18: 4 | AH18: 0.66666667 | AI18: Y | AJ18: 1 | AK18: 0.68333333 | AL18: Y | AM18: 1 | AN18: 0.64930556 | AO18: Y | AP18: 4
A19: R15 | B19: =COUNTIF('Jan 2025 - Dec 2025'!J1:J740, "TH2-R15") -> 30 | C19: =AVERAGE(G19,J19,M19,P19,S19,V19,Y19,AB19,AE19,AH19,AK19,PN19) -> 0.62291667 | E19: =F19-B19 -> 23 | F19: =SUM(I19,L19,O19,R19,U19,X19,AA19,AD19,AG19,AJ19,AM19,AP19) -> 53 | G19: 0.67013889 | H19: Y | I19: 6 | J19: 0.62847222 | K19: Y | L19: 3 | M19: 0.62986111 | N19: Y | O19: 5 | P19: 0.63194444 | Q19: Y | R19: 0 | S19: 0.625 | T19: Y | U19: 2 | V19: 0.61944444 | W19: Y | X19: 9 | Y19: 0.61458333 | Z19: Y | AA19: 2 | AB19: 0.62916667 | AC19: Y | AD19: 5 | AE19: 0.59166667 | AF19: Y | AG19: 5 | AH19: 0.58472222 | AI19: Y | AJ19: 6 | AK19: 0.62708333 | AL19: Y | AM19: 5 | AN19: 0.62152778 | AO19: Y | AP19: 5
A20: R16 | B20: =COUNTIF('Jan 2025 - Dec 2025'!J1:J741, "F2-R16") -> 28 | C20: =AVERAGE(G20,J20,M20,P20,S20,V20,Y20,AB20,AE20,AH20,AK20,PN20) -> 0.65738636 | E20: =F20-B20 -> 16 | F20: =SUM(I20,L20,O20,R20,U20,X20,AA20,AD20,AG20,AJ20,AM20,AP20) -> 44 | G20: 0.62013889 | H20: Y | I20: 0 | J20: 0.67152778 | K20: Y | L20: 5 | M20: 0.64583333 | N20: Y | O20: 4 | P20: 0.66319444 | Q20: X | R20: 4 | S20: 0.66666667 | T20: X | U20: 2 | V20: 0.66666667 | W20: Y | X20: 7 | Y20: 0.62638889 | Z20: X | AA20: 6 | AB20: 0.67083333 | AC20: Y | AD20: 4 | AE20: 0.66180556 | AF20: X | AG20: 5 | AH20: 0.64027778 | AI20: Y | AJ20: 4 | AK20: 0.69791667 | AL20: Y | AM20: 3 | AN20: 0.65555556 | AO20: Y | AP20: 0
A21: R17 | B21: =COUNTIF('Jan 2025 - Dec 2025'!J1:J738, "M3-R17") -> 13 | C21: =AVERAGE(G21,J21,M21,P21,S21,V21,Y21,AB21,AE21,AH21,AK21,PN21) -> 0.64659091 | D21: Locked | E21: =F21-B21 -> 10 | F21: =SUM(I21,L21,O21,R21,U21,X21,AA21,AD21,AG21,AJ21,AM21,AP21) -> 23 | G21: 0.63888889 | H21: Y | I21: 1 | J21: 0.64583333 | K21: Y | L21: 1 | M21: 0.61458333 | N21: Y | O21: 3 | P21: 0.67777778 | Q21: Y | R21: 3 | S21: 0.67291667 | T21: X | U21: 3 | V21: 0.64027778 | W21: Y | X21: 1 | Y21: 0.63888889 | Z21: Y | AA21: 0 | AB21: 0.66388889 | AC21: Y | AD21: 1 | AE21: 0.59375 | AF21: Y | AG21: 1 | AH21: 0.65972222 | AI21: X | AJ21: 2 | AK21: 0.66597222 | AL21: Y | AM21: 2 | AN21: 0.66458333 | AO21: X | AP21: 5
A22: R18 | B22: =COUNTIF('Jan 2025 - Dec 2025'!J1:J739, "TU3-R18") -> 27 | C22: =AVERAGE(G22,J22,M22,P22,S22,V22,Y22,AB22,AE22,AH22,AK22,PN22) -> 0.59419192 | E22: =F22-B22 -> 2 | F22: =SUM(I22,L22,O22,R22,U22,X22,AA22,AD22,AG22,AJ22,AM22,AP22) -> 29 | G22: 0.6375 | H22: Y | I22: 3 | J22: 0.57847222 | K22: Y | L22: 3 | M22: 0.66319444 | N22: Y | O22: 2 | P22: 0.58888889 | Q22: Y | R22: 1 | S22: 0.61805556 | T22: Y | U22: 2 | V22: 0.56736111 | W22: Y | X22: 1 | Y22: 0.51805556 | Z22: Y | AA22: 4 | AB22: 0.60138889 | AC22: Y | AD22: 0 | AE22: 0.52430556 | AF22: Y | AG22: 4 | AH22: 0.64583333 | AI22: Y | AJ22: 5 | AK22: 0.59305556 | AL22: Y | AM22: 1 | AN22: 0.60069444 | AO22: Y | AP22: 3
A23: R19 | B23: =COUNTIF('Jan 2025 - Dec 2025'!J1:J740, "TU3-R19") -> 25 | C23: =AVERAGE(G23,J23,M23,P23,S23,V23,Y23,AB23,AE23,AH23,AK23,PN23) -> 0.61698232 | D23: Locked | E23: =F23-B23 -> 5 | F23: =SUM(I23,L23,O23,R23,U23,X23,AA23,AD23,AG23,AJ23,AM23,AP23) -> 30 | G23: 0.60763889 | H23: Y | I23: 4 | J23: 0.65972222 | K23: Y | L23: 1 | M23: 0.57986111 | N23: Y | O23: 1 | P23: 0.55694444 | Q23: Y | R23: 1 | S23: 0.59375 | T23: Y | U23: 7 | V23: 0.60416667 | W23: Y | X23: 3 | Y23: 0.62847222 | Z23: Y | AA23: 5 | AB23: 0.625 | AC23: Y | AD23: 1 | AE23: 0.63680556 | AF23: Y | AG23: 2 | AH23: 0.63541667 | AI23: Y | AJ23: 2 | AK23: 0.65902778 | AL23: Y | AM23: 2 | AN23: 0.6875 | AO23: X | AP23: 1
A24: R20 | B24: =COUNTIF('Jan 2025 - Dec 2025'!J1:J741, "W3-R20") -> 31 | C24: =AVERAGE(G24,J24,M24,P24,S24,V24,Y24,AB24,AE24,AH24,AK24,PN24) -> 0.66388889 | D24: Locked | E24: =F24-B24 -> 4 | F24: =SUM(I24,L24,O24,R24,U24,X24,AA24,AD24,AG24,AJ24,AM24,AP24) -> 35 | G24: 0.67569444 | H24: Y | I24: 2 | J24: 0.6875 | K24: Y | L24: 1 | M24: 0.70486111 | N24: Y | O24: 2 | P24: 0.66666667 | Q24: Y | R24: 3 | S24: 0.64930556 | T24: Y | U24: 3 | V24: 0.65972222 | W24: Y | X24: 3 | Y24: 0.6625 | Z24: Y | AA24: 4 | AB24: 0.59166667 | AC24: Y | AD24: 7 | AE24: 0.65972222 | AF24: Y | AG24: 2 | AH24: 0.67152778 | AI24: Y | AJ24: 4 | AK24: 0.67361111 | AL24: Y | AM24: 2 | AN24: 0.68402778 | AO24: Y | AP24: 2
A25: R21 | B25: =COUNTIF('Jan 2025 - Dec 2025'!J1:J742, "TH3-R21") -> 25 | C25: =AVERAGE(G25,J25,M25,P25,S25,V25,Y25,AB25,AE25,AH25,AK25,PN25) -> 0.66237374 | D25: Locked | E25: =F25-B25 -> 11 | F25: =SUM(I25,L25,O25,R25,U25,X25,AA25,AD25,AG25,AJ25,AM25,AP25) -> 36 | G25: 0.65972222 | H25: Y | I25: 3 | J25: 0.65625 | K25: Y | L25: 1 | M25: 0.65902778 | N25: Y | O25: 4 | P25: 0.6375 | Q25: Y | R25: 3 | S25: 0.67638889 | T25: Y | U25: 5 | V25: 0.67569444 | W25: Y | X25: 2 | Y25: 0.66666667 | Z25: Y | AA25: 3 | AB25: 0.64097222 | AC25: Y | AD25: 5 | AE25: 0.66666667 | AF25: Y | AG25: 2 | AH25: 0.66666667 | AI25: Y | AJ25: 4 | AK25: 0.68055556 | AL25: Y | AM25: 1 | AN25: 0.67708333 | AO25: Y | AP25: 3
A26: R22 | B26: =COUNTIF('Jan 2025 - Dec 2025'!J1:J743, "W2-R22") -> 34 | C26: =AVERAGE(G26,J26,M26,P26,S26,V26,Y26,AB26,AE26,AH26,AK26,PN26) -> 0.52996032 | E26: =F26-B26 -> 16 | F26: =SUM(I26,L26,O26,R26,U26,X26,AA26,AD26,AG26,AJ26,AM26,AP26) -> 50 | G26: N/A | P26: 0.49930556 | Q26: Y | R26: 0 | S26: 0.51736111 | T26: Y | U26: 3 | V26: 0.67847222 | W26: Y | X26: 7 | Y26: 0.48125 | Z26: Y | AA26: 1 | AB26: 0.49236111 | AC26: Y | AD26: 5 | AE26: 0.51944444 | AF26: Y | AG26: 4 | AH26: 0.52152778 | AI26: Y | AJ26: 0 | AK26: - | AL26: X | AM26: 24 | AN26: 0.67708333 | AO26: X | AP26: 6
A27: R23 | B27: =COUNTIF('Jan 2025 - Dec 2025'!J1:J744, "TH2-R23") -> 15 | C27: 0.47569444 | E27: =F27-B27 -> -13 | F27: =SUM(I27,L27,O27,R27,U27,X27,AA27,AD27,AG27,AJ27,AM27,AP27) -> 2 | G27: N/A | AK27: 0.47222222 | AL27: Y | AM27: 2 | AN27: 0.48125 | AO27: Y | AP27: 0
A28: R24 | B28: =COUNTIF('Jan 2025 - Dec 2025'!J1:J745, "F1-R24") -> 0 | C28: - | E28: =F28-B28 -> 0 | F28: =SUM(I28,L28,O28,R28,U28,X28,AA28,AD28,AG28,AJ28,AM28,AP28) -> 0
A29: Total sites | B29: =SUM(B3:B27) -> 608 | D29: Total Skipped | E29: =SUM(E5:E27) -> 292 | F29: =SUM(F5:F27) -> 900
A30: Total skipped (Per Month) | G30: January | I30: =SUM(I5:I26) -> 56 | J30: February | L30: =SUM(L5:L26) -> 56 | M30: March | O30: =SUM(O5:O26) -> 59 | P30: April | R30: =SUM(R5:R26) -> 76 | S30: May | U30: =SUM(U5:U26) -> 86 | V30: June | X30: =SUM(X5:X26) -> 101 | Y30: July | AA30: =SUM(AA5:AA26) -> 84 | AB30: August | AD30: =SUM(AD5:AD26) -> 80 | AE30: September | AG30: =SUM(AG5:AG26) -> 71 | AH30: October | AJ30: =SUM(AJ5:AJ26) -> 68 | AK30: November | AM30: =SUM(AM5:AM27)-24 -> 55 | AN30: December | AP30: =SUM(AP5:AP27)-29 -> 55 | AQ30: =(AP30/AS30)-1 -> -0.23611111 | AR30: Average 2025 | AS30: =(I30+L30+O30+R30+U30+X30+AA30+AD30+AG30+AJ30+AM30)/11 -> 72
A31: Total skipped (Per lack of time) | G31: January | I31: =I9 -> 6 | J31: February | L31: =L11 -> 6 | M31: March | O31: =O16 -> 4 | P31: April | R31: =R15+2 -> 14 | S31: May | U31: =4+5+2+2 -> 13 | V31: June | X31: =3+9+9 -> 21 | Y31: July | AA31: =10+5+3 -> 18 | AB31: August | AD31: =2+3 -> 5 | AE31: September | AG31: =3+3+3+3 -> 12 | AH31: October | AJ31: =5+1 -> 6 | AK31: November | AM31: =4+1 -> 5 | AN31: December | AP31: =1+4+1+5 -> 11 | AQ31: =(AP31)/AS31-1 -> 0.1 | AR31: Average 2025 | AS31: =(I31+L31+O31+R31+U31+X31+AA31+AD31+AG31+AJ31+AM31)/11 -> 10
B33: Skipped = annual, lack of time or other reasons.
B34: Average Finish Time Target: Between 3:30PM - 4:00PM

Sheet 2025 Revenue Report
B3: Weekday | C3: Monthly Route # | D3: Route name /service area | E3: Buildings /route | F3: Average hours required to complete | G3: Techs required | H3: Monthly Route Expenses (Avg labour cost $45/hr) + (Truck charge $25/month) | I3: Monthly Route Revenue | J3: Monthly Net | K3: Monthly Net % | L3: Notes | M3: Route Locked (route is full - no new buildings can be added) | O3: MBT PRICING
B4: 1st Monday | C4: Route #1 | D4: Pac Pro 1 | E4: =COUNTIF('Jan 2025 - Dec 2025'!J1:J750, "M1-R1") -> 33 | F4: =MAX(0, (MIN('2025 Completion Chart'!C5, TIME(16,30,0)) - TIME(8,0,0)) * 24 - IF('2025 Completion Chart'!C5 >= TIME(12,0,0), 0.5, 0) ) -> 6.812963 | G4: 1 | H4: =F4*G4*45+(25) -> 331.58333 | I4: =SUMIF('Jan 2025 - Dec 2025'!$J$2:$J$1000, "M1-R1", 'Jan 2025 - Dec 2025'!$E$2:$E$1000) -> 1955 | J4: =(I4-H4) -> 1623.4167 | K4: =(J4/I4) -> 0.83039216 | L4: Pac pro route - 1 technician | O4: Devon Properties | P4: ='[1]Quotation Cheat Sheet'!$G$61 -> 65
B5: 1st Monday | C5: Route #2 | D5: Pac Pro 2 | E5: =COUNTIF('Jan 2025 - Dec 2025'!J1:J750, "M1-R2") -> 30 | F5: =MAX(0, (MIN('2025 Completion Chart'!C6, TIME(16,30,0)) - TIME(8,0,0)) * 24 - IF('2025 Completion Chart'!C6 >= TIME(12,0,0), 0.5, 0) ) -> 5.680303 | G5: 1 | H5: =F5*G5*45+(25) -> 280.61364 | I5: =SUMIF('Jan 2025 - Dec 2025'!$J$2:$J$1000, "M1-R2", 'Jan 2025 - Dec 2025'!$E$2:$E$1000) -> 1660 | J5: =(I5-H5) -> 1379.3864 | K5: =(J5/I5) -> 0.83095564 | L5: Pac pro route - 1 technician | O5: Typical | P5: ='[1]Quotation Cheat Sheet'!$G$62 -> 75
B6: 1st Monday | C6: Route #3 | D6: Fernwood | E6: =COUNTIF('Jan 2025 - Dec 2025'!J1:J750, "M1-R3") -> 32 | F6: =MAX(0, (MIN('2025 Completion Chart'!C7, TIME(16,30,0)) - TIME(8,0,0)) * 24 - IF('2025 Completion Chart'!C7 >= TIME(12,0,0), 0.5, 0) ) -> 6.4909091 | G6: 2 | H6: =F6*G6*45+(25) -> 609.18182 | I6: =SUMIF('Jan 2025 - Dec 2025'!$J$2:$J$1000, "M1-R3", 'Jan 2025 - Dec 2025'!$E$2:$E$1000) -> 1870 | J6: =(I6-H6) -> 1260.8182 | K6: =(J6/I6) -> 0.67423432 | O6: High Rise | P6: ='[1]Quotation Cheat Sheet'!$G$63 -> 125
B7: 1st Tuesday | C7: Route #4 | D7: Saanich | E7: =COUNTIF('Jan 2025 - Dec 2025'!J1:J750, "TU1-R4") -> 14 | F7: =MAX(0, (MIN('2025 Completion Chart'!C8, TIME(16,30,0)) - TIME(8,0,0)) * 24 - IF('2025 Completion Chart'!C8 >= TIME(12,0,0), 0.5, 0) ) -> 6.7772727 | G7: 2 | H7: =F7*G7*45+(25) -> 634.95455 | I7: =SUMIF('Jan 2025 - Dec 2025'!$J$2:$J$1000, "TU1-R4", 'Jan 2025 - Dec 2025'!$E$2:$E$1000) -> 715 | J7: =(I7-H7) -> 80.045455 | K7: =(J7/I7) -> 0.11195168 | O7: Monthly Training | P7: ='[1]Quotation Cheat Sheet'!$G$64 -> 250
B8: 1st Tuesday | C8: Route #5 | D8: Westshore | E8: =COUNTIF('Jan 2025 - Dec 2025'!J1:J750, "TU1-R5") -> 31 | F8: =MAX(0, (MIN('2025 Completion Chart'!C9, TIME(16,30,0)) - TIME(8,0,0)) * 24 - IF('2025 Completion Chart'!C9 >= TIME(12,0,0), 0.5, 0) ) -> 7.4151515 | G8: 2 | H8: =F8*G8*45+(25) -> 692.36364 | I8: =SUMIF('Jan 2025 - Dec 2025'!$J$2:$J$1000, "TU1-R5", 'Jan 2025 - Dec 2025'!$E$2:$E$1000) -> 1935 | J8: =(I8-H8) -> 1242.6364 | K8: =(J8/I8) -> 0.64218934 | M8: Locked | O8: Avg price per building | P8: =I29/E29 -> 61.949013
B9: 1st Wednesday | C9: Route #6 | D9: Hillside | E9: =COUNTIF('Jan 2025 - Dec 2025'!J1:J750, "W1-R6") -> 32 | F9: =MAX(0, (MIN('2025 Completion Chart'!C10, TIME(16,30,0)) - TIME(8,0,0)) * 24 - IF('2025 Completion Chart'!C10 >= TIME(12,0,0), 0.5, 0) ) -> 7.2681818 | G9: 2 | H9: =F9*G9*45+(25) -> 679.13636 | I9: =SUMIF('Jan 2025 - Dec 2025'!$J$2:$J$1000, "W1-R6", 'Jan 2025 - Dec 2025'!$E$2:$E$1000) -> 1945 | J9: =(I9-H9) -> 1265.8636 | K9: =(J9/I9) -> 0.65082963
B10: 1st Wednesday | C10: Route #7 | D10: Esquimalt | E10: =COUNTIF('Jan 2025 - Dec 2025'!J1:J750, "W1-R7") -> 29 | F10: =MAX(0, (MIN('2025 Completion Chart'!C11, TIME(16,30,0)) - TIME(8,0,0)) * 24 - IF('2025 Completion Chart'!C11 >= TIME(12,0,0), 0.5, 0) ) -> 7.1878788 | G10: 2 | H10: =F10*G10*45+(25) -> 671.90909 | I10: =SUMIF('Jan 2025 - Dec 2025'!$J$2:$J$1000, "W1-R7", 'Jan 2025 - Dec 2025'!$E$2:$E$1000) -> 1625 | J10: =(I10-H10) -> 953.09091 | K10: =(J10/I10) -> 0.58651748
B11: 1st Thursday | C11: Route #8 | D11: Downtown 1 | E11: =COUNTIF('Jan 2025 - Dec 2025'!J1:J750, "TH1-R8") -> 25 | F11: =MAX(0, (MIN('2025 Completion Chart'!C12, TIME(16,30,0)) - TIME(8,0,0)) * 24 - IF('2025 Completion Chart'!C12 >= TIME(12,0,0), 0.5, 0) ) -> 7.380303 | G11: 2 | H11: =F11*G11*45+(25) -> 689.22727 | I11: =SUMIF('Jan 2025 - Dec 2025'!$J$2:$J$1000, "TH1-R8", 'Jan 2025 - Dec 2025'!$E$2:$E$1000) -> 1555 | J11: =(I11-H11) -> 865.77273 | K11: =(J11/I11) -> 0.55676703
B12: 1st Thursday | C12: Route #9 | D12: Downtown 2 | E12: =COUNTIF('Jan 2025 - Dec 2025'!J1:J750, "TH1-R9") -> 32 | F12: =MAX(0, (MIN('2025 Completion Chart'!C13, TIME(16,30,0)) - TIME(8,0,0)) * 24 - IF('2025 Completion Chart'!C13 >= TIME(12,0,0), 0.5, 0) ) -> 6.3106061 | G12: 2 | H12: =F12*G12*45+(25) -> 592.95455 | I12: =SUMIF('Jan 2025 - Dec 2025'!$J$2:$J$1000, "TH1-R9", 'Jan 2025 - Dec 2025'!$E$2:$E$1000) -> 1805 | J12: =(I12-H12) -> 1212.0455 | K12: =(J12/I12) -> 0.67149333
B13: 1st Friday | C13: Route #10 | D13: Sidney 1 | E13: =COUNTIF('Jan 2025 - Dec 2025'!J1:J750, "F1-R10") -> 28 | F13: =MAX(0, (MIN('2025 Completion Chart'!C14, TIME(16,30,0)) - TIME(8,0,0)) * 24 - IF('2025 Completion Chart'!C14 >= TIME(12,0,0), 0.5, 0) ) -> 6.5681818 | G13: 2 | H13: =F13*G13*45+(25) -> 616.13636 | I13: =SUMIF('Jan 2025 - Dec 2025'!$J$2:$J$1000, "F1-R10", 'Jan 2025 - Dec 2025'!$E$2:$E$1000) -> 1555 | J13: =(I13-H13) -> 938.86364 | K13: =(J13/I13) -> 0.60377083
B14: 2nd Monday | C14: Route #11 | D14: Thrifty's 1 | E14: =COUNTIF('Jan 2025 - Dec 2025'!J1:J750, "M2-R11") -> 12 | F14: =MAX(0, (MIN('2025 Completion Chart'!C15, TIME(16,30,0)) - TIME(8,0,0)) * 24 - IF('2025 Completion Chart'!C15 >= TIME(12,0,0), 0.5, 0) ) -> 6.9166667 | G14: 2 | H14: =F14*G14*45+(25) -> 647.5 | I14: =SUMIF('Jan 2025 - Dec 2025'!$J$2:$J$1000, "M2-R11", 'Jan 2025 - Dec 2025'!$E$2:$E$1000) -> 1400 | J14: =(I14-H14) -> 752.5 | K14: =(J14/I14) -> 0.5375 | L14: Thrifty's (Mill Bay)
B15: 2nd Tuesday | C15: Route #12 | D15: Central Saanich | E15: =COUNTIF('Jan 2025 - Dec 2025'!J1:J750, "TU2-R12") -> 29 | F15: =MAX(0, (MIN('2025 Completion Chart'!C16, TIME(16,30,0)) - TIME(8,0,0)) * 24 - IF('2025 Completion Chart'!C16 >= TIME(12,0,0), 0.5, 0) ) -> 7.3575758 | G15: 2 | H15: =F15*G15*45+(25) -> 687.18182 | I15: =SUMIF('Jan 2025 - Dec 2025'!$J$2:$J$1000, "TU2-R12", 'Jan 2025 - Dec 2025'!$E$2:$E$1000) -> 1685 | J15: =(I15-H15) -> 997.81818 | K15: =(J15/I15) -> 0.59217696 | M15: Locked
B16: 2nd Tuesday | C16: Route #13 | D16: Uplands | E16: =COUNTIF('Jan 2025 - Dec 2025'!J1:J750, "TU2-R13") -> 22 | F16: =MAX(0, (MIN('2025 Completion Chart'!C17, TIME(16,30,0)) - TIME(8,0,0)) * 24 - IF('2025 Completion Chart'!C17 >= TIME(12,0,0), 0.5, 0) ) -> 5.3666667 | G16: 2 | H16: =F16*G16*45+(25) -> 508 | I16: =SUMIF('Jan 2025 - Dec 2025'!$J$2:$J$1000, "TU2-R13", 'Jan 2025 - Dec 2025'!$E$2:$E$1000) -> 1215 | J16: =(I16-H16) -> 707 | K16: =(J16/I16) -> 0.581893 | L16: 6 hours route
B17: 2nd Wednesday | C17: Route #14 | D17: Oak Bay | E17: =COUNTIF('Jan 2025 - Dec 2025'!J1:J750, "W2-R14") -> 31 | F17: =MAX(0, (MIN('2025 Completion Chart'!C18, TIME(16,30,0)) - TIME(8,0,0)) * 24 - IF('2025 Completion Chart'!C18 >= TIME(12,0,0), 0.5, 0) ) -> 7.2606061 | G17: 2 | H17: =F17*G17*45+(25) -> 678.45455 | I17: =SUMIF('Jan 2025 - Dec 2025'!$J$2:$J$1000, "W2-R14", 'Jan 2025 - Dec 2025'!$E$2:$E$1000) -> 1650 | J17: =(I17-H17) -> 971.54545 | K17: =(J17/I17) -> 0.58881543 | M17: Locked
B18: 2nd Thursday | C18: Route #15 | D18: Downtown 3 | E18: =COUNTIF('Jan 2025 - Dec 2025'!J1:J750, "TH2-R15") -> 30 | F18: =MAX(0, (MIN('2025 Completion Chart'!C19, TIME(16,30,0)) - TIME(8,0,0)) * 24 - IF('2025 Completion Chart'!C19 >= TIME(12,0,0), 0.5, 0) ) -> 6.45 | G18: 2 | H18: =F18*G18*45+(25) -> 605.5 | I18: =SUMIF('Jan 2025 - Dec 2025'!$J$2:$J$1000, "TH2-R15", 'Jan 2025 - Dec 2025'!$E$2:$E$1000) -> 1745 | J18: =(I18-H18) -> 1139.5 | K18: =(J18/I18) -> 0.6530086 | L18: Early route (7am start)
B19: 2nd Friday | C19: Route #16 | D19: Sidney 2 | E19: =COUNTIF('Jan 2025 - Dec 2025'!J1:J750, "F2-R16") -> 28 | F19: =MAX(0, (MIN('2025 Completion Chart'!C20, TIME(16,30,0)) - TIME(8,0,0)) * 24 - IF('2025 Completion Chart'!C20 >= TIME(12,0,0), 0.5, 0) ) -> 7.2772727 | G19: 2 | H19: =F19*G19*45+(25) -> 679.95455 | I19: =SUMIF('Jan 2025 - Dec 2025'!$J$2:$J$1000, "F2-R16", 'Jan 2025 - Dec 2025'!$E$2:$E$1000) -> 1625 | J19: =(I19-H19) -> 945.04545 | K19: =(J19/I19) -> 0.58156643 | M19: Locked
B20: 3rd Monday | C20: Route #17 | D20: Thrifty's 2 | E20: =COUNTIF('Jan 2025 - Dec 2025'!J1:J750, "M3-R17") -> 13 | F20: =MAX(0, (MIN('2025 Completion Chart'!C21, TIME(16,30,0)) - TIME(8,0,0)) * 24 - IF('2025 Completion Chart'!C21 >= TIME(12,0,0), 0.5, 0) ) -> 7.0181818 | G20: 2 | H20: =F20*G20*45+(25) -> 656.63636 | I20: =SUMIF('Jan 2025 - Dec 2025'!$J$2:$J$1000, "M3-R17", 'Jan 2025 - Dec 2025'!$E$2:$E$1000) -> 2535 | J20: =(I20-H20) -> 1878.3636 | K20: =(J20/I20) -> 0.74097185 | M20: Locked
B21: 3rd Tuesday | C21: Route #18 | D21: Beacon Hill | E21: =COUNTIF('Jan 2025 - Dec 2025'!J1:J750, "TU3-R18") -> 27 | F21: =MAX(0, (MIN('2025 Completion Chart'!C22, TIME(16,30,0)) - TIME(8,0,0)) * 24 - IF('2025 Completion Chart'!C22 >= TIME(12,0,0), 0.5, 0) ) -> 5.7606061 | G21: 2 | H21: =F21*G21*45+(25) -> 543.45455 | I21: =SUMIF('Jan 2025 - Dec 2025'!$J$2:$J$1000, "TU3-R18", 'Jan 2025 - Dec 2025'!$E$2:$E$1000) -> 1455 | J21: =(I21-H21) -> 911.54545 | K21: =(J21/I21) -> 0.62649172 | L21: 6 hours route
B22: 3rd Tuesday | C22: Route #19 | D22: Mayfair | E22: =COUNTIF('Jan 2025 - Dec 2025'!J1:J750, "TU3-R19") -> 25 | F22: =MAX(0, (MIN('2025 Completion Chart'!C23, TIME(16,30,0)) - TIME(8,0,0)) * 24 - IF('2025 Completion Chart'!C23 >= TIME(12,0,0), 0.5, 0) ) -> 6.3075758 | G22: 2 | H22: =F22*G22*45+(25) -> 592.68182 | I22: =SUMIF('Jan 2025 - Dec 2025'!$J$2:$J$1000, "TU3-R19", 'Jan 2025 - Dec 2025'!$E$2:$E$1000) -> 1465 | J22: =(I22-H22) -> 872.31818 | K22: =(J22/I22) -> 0.59543903
B23: 3rd Wednesday | C23: Route #20 | D23: James Bay | E23: =COUNTIF('Jan 2025 - Dec 2025'!J1:J750, "W3-R20") -> 31 | F23: =MAX(0, (MIN('2025 Completion Chart'!C24, TIME(16,30,0)) - TIME(8,0,0)) * 24 - IF('2025 Completion Chart'!C24 >= TIME(12,0,0), 0.5, 0) ) -> 7.4333333 | G23: 2 | H23: =F23*G23*45+(25) -> 694 | I23: =SUMIF('Jan 2025 - Dec 2025'!$J$2:$J$1000, "W3-R20", 'Jan 2025 - Dec 2025'!$E$2:$E$1000) -> 1825 | J23: =(I23-H23) -> 1131 | K23: =(J23/I23) -> 0.61972603 | M23: Locked
